Workbook

Sheet Comparison
A3: BAR | B3: BAR Sum of Net Invoice Amount | C3: AOS Pre Export | D3: Diff
A4: 250528 | B4: 0 | C4: =VLOOKUP(A4,'AOS Pivot'!A:B,2,FALSE) -> 0 | D4: =(B4-C4) -> 0
A5: 251886 | B5: 6741.12 | C5: =VLOOKUP(A5,'AOS Pivot'!A:B,2,FALSE) -> 6741.12 | D5: =(B5-C5) -> 9.094947e-13
A6: 252135 | B6: 0 | C6: =VLOOKUP(A6,'AOS Pivot'!A:B,2,FALSE) -> 0 | D6: =(B6-C6) -> 0
A7: 252314 | B7: 0 | C7: =VLOOKUP(A7,'AOS Pivot'!A:B,2,FALSE) -> 0 | D7: =(B7-C7) -> 0
A8: 252340 | B8: 30427.14 | C8: =VLOOKUP(A8,'AOS Pivot'!A:B,2,FALSE) -> 30427.135 | D8: =(B8-C8) -> 0.005
A9: 252732 | B9: 55223.11 | C9: =VLOOKUP(A9,'AOS Pivot'!A:B,2,FALSE) -> 55218.55 | D9: =(B9-C9) -> 4.56
A10: 252733 | B10: 30355.25 | C10: =VLOOKUP(A10,'AOS Pivot'!A:B,2,FALSE) -> 30351.205 | D10: =(B10-C10) -> 4.045
A11: 252736 | B11: 40743.07 | C11: =VLOOKUP(A11,'AOS Pivot'!A:B,2,FALSE) -> 40738.018 | D11: =(B11-C11) -> 5.052
A12: 253348 | B12: 7190.04 | C12: =VLOOKUP(A12,'AOS Pivot'!A:B,2,FALSE) -> 7189.9211 | D12: =(B12-C12) -> 0.1189
A13: 253612 | B13: 0 | C13: =VLOOKUP(A13,'AOS Pivot'!A:B,2,FALSE) -> 0 | D13: =(B13-C13) -> 0
A14: 254371 | B14: 965.55 | C14: =VLOOKUP(A14,'AOS Pivot'!A:B,2,FALSE) -> 8689.4958 | D14: =(B14-C14) -> -7723.9458
A15: 256852 | B15: 165693.24 | C15: =VLOOKUP(A15,'AOS Pivot'!A:B,2,FALSE) -> 331386.48 | D15: =(B15-C15) -> -165693.24
... A214: 272533 | B214: 6409.48 | C214: =VLOOKUP(A214,'AOS Pivot'!A:B,2,FALSE) -> 12818.96 | D214: =(B214-C214) -> -6409.48
A215: Grand Total | B215: 29131400 | C215: =VLOOKUP(A215,'AOS Pivot'!A:B,2,FALSE) -> 56204191 | D215: =(B215-C215) -> -27072791

Sheet BAR Pivot
A3: BAR | B3: BAR Sum of Net Invoice Amount
A4: 250528 | B4: 0
A5: 251886 | B5: 6741.12
A6: 252135 | B6: 0
A7: 252314 | B7: 0
A8: 252340 | B8: 30427.14
A9: 252732 | B9: 55223.11
A10: 252733 | B10: 30355.25
A11: 252736 | B11: 40743.07
A12: 253348 | B12: 7190.04
A13: 253612 | B13: 0
A14: 254371 | B14: 965.55
A15: 256852 | B15: 165693.24
... A214: 272533 | B214: 6409.48
A215: Grand Total | B215: 29131400

Sheet Cash BAR
A1: Agency | B1: Agency ID | C1: Advertiser ID | D1: Advertiser | E1: Sales Order | F1: Sales Order ID | G1: Parent Line Item | H1: Parent Line Item ID | I1: Sales Line Item | J1: PS Line Item ID | K1: Placement Property | L1: Cost Method | M1: Net Unit Cost | N1: Billable Metric | O1: Billable Impressions | P1: Billable Revenue | Q1: Price | R1: Revised Billed Impressions | S1: Revised Billed Revenue | T1: Parent Line Item Revenue | U1: Reason for Revision | V1: Special Billing Instructions | W1: 1P Imps | X1: 3P Imps | Y1: 1P Demo Imps | Z1: 3P Demo Imps | AA1: Viewability | AB1: Demo Comp | AC1: Equivalization Factor | AD1: Equivalized Imps | AE1: Billing Scenario | AF1: Net Invoice Amount | AG1: Quantity | AH1: Net Cost | AI1: Campaign | AJ1: Campaign ID | AK1: Demo Band | AL1: External PO Ref | AM1: Sales Region | AN1: Primary Salesperson | AO1: Sales Line Item Type | AP1: Product | AQ1: Invoice ID | AR1: Billing Period End Date | AS1: Parent Line Item Start Date | AT1: Parent Line Item End Date | AU1: Product Category | AV1: Previously Billed | AW1: Report Date
A2: A24 FILMS | B2: 20096 | C2: 12011 | D2: A24 FILMS | E2: A24 Death of Robin Hood/Digital/Scatter/AllFOX & Abs A/25.26/2Q26 | F2: 262385 | G2: DIO - ROV - 1F SEN - Pre/Mid - ROS - FW - SXD - Package (AAT A25-54 and Fandango Fans) | H2: 565285 | I2: DIO - LFV - 1F - Tubi - Pre/Mid - ROS - DT/MB/CTV - FW - SXD (AAT A25-54 and Fandango Fans) | J2: 94341364 | K2: Fox Sold Tubi | L2: CPM | M2: 21.25 | N2: 1P Audience Target | O2: 4071061 | P2: 84000 | S2: =IF(ISBLANK(R2)," ",ROUND(R2*(IF(ISBLANK(Q2),(M2/1000),(Q2/1000))),2)) | T2: =IF(IF(COUNTIF(H$2:$H2,H2)=1,1,"")=1,SUMIF($H$2:$H$7997,H2,$S$2:$S$7997),"") -> 0 | W2: 4071061 | X2: 4071061 | Y2: 0 | Z2: 0 | AA2: 1 | AB2: 0 | AC2: 0 | AD2: 0 | AE2: Bill on Actuals - 3rd Party Performance | AF2: 42000 | AG2: 3952941 | AH2: 84000 | AI2: A24 Death of Robin Hood/Digital/Scatter/AllFOX & Abs A/25.26/2Q26 | AJ2: 94341361 | AK2: Audience Target | AL2: n/a | AN2: Kimberly Caraig | AO2: Guaranteed | AP2: DIO - LFV - 1F - Tubi - Pre/Mid - ROS - DT/MB/CTV - FW - SXD | AQ2: 129821 | AR2: 46203 | AS2: 46174 | AT2: 46201 | AU2: Direct LFV | AW2: 46208.537
A3: A24 FILMS | B3: 20096 | C3: 12011 | D3: A24 FILMS | E3: A24 Death of Robin Hood/Digital/Scatter/AllFOX & Abs A/25.26/2Q26 | F3: 262385 | G3: DIO - ROV - 1F SEN - Pre/Mid - ROS - FW - SXD - Package (AAT A25-54 and Fandango Fans) | H3: 565285 | I3: DIO - ROV - 1F - SEN - Pre/Mid - ROS - DT/MB/CTV - SXD (AAT A25-54 and Fandango Fans) | J3: 94341367 | K3: OneFOX | L3: CPM | M3: 21.25 | N3: 1P Audience Target | O3: 6037472 | P3: 126000.01 | S3: =IF(ISBLANK(R3)," ",ROUND(R3*(IF(ISBLANK(Q3),(M3/1000),(Q3/1000))),2)) | T3: =IF(IF(COUNTIF(H$2:$H3,H3)=1,1,"")=1,SUMIF($H$2:$H$7997,H3,$S$2:$S$7997),"") | W3: 6037472 | X3: 6037472 | Y3: 0 | Z3: 0 | AA3: 1 | AB3: 0 | AC3: 0 | AD3: 0 | AE3: Bill on Actuals - 3rd Party Performance | AF3: 63000.01 | AG3: 5929412 | AH3: 126000.01 | AI3: A24 Death of Robin Hood/Digital/Scatter/AllFOX & Abs A/25.26/2Q26 | AJ3: 94341361 | AK3: Audience Target | AL3: n/a | AN3: Kimberly Caraig | AO3: Guaranteed | AP3: DIO - ROV - 1F - SEN - Pre/Mid - ROS - DT/MB/CTV - SXD | AQ3: 129821 | AR3: 46203 | AS3: 46174 | AT3: 46201 | AU3: Direct ROV | AW3: 46208.537
A4: A24 FILMS | B4: 20096 | C4: 12011 | D4: A24 FILMS | E4: A24 Death of Robin Hood/Digital/Scatter/AllFOX & Abs A/25.26/2Q26 | F4: 262385 | G4: DIO - LFV - RON Ent - Absolute A - Show Mix - DT/MB/CTV/STB (Masked Singer and Fear Factor) | H4: 565482 | I4: DIO - LFV - RON Ent - Absolute A - Show Mix - DT/MB/CTV/STB (Masked Singer and Fear Factor) | J4: 94341371 | K4: RON - Ent | L4: CPM | M4: 30 | N4: Absolute A | O4: 1359729 | P4: 40000.02 | S4: =IF(ISBLANK(R4)," ",ROUND(R4*(IF(ISBLANK(Q4),(M4/1000),(Q4/1000))),2)) | T4: =IF(IF(COUNTIF(H$2:$H4,H4)=1,1,"")=1,SUMIF($H$2:$H$7997,H4,$S$2:$S$7997),"") -> 0 | W4: 1133108 | X4: 1133108 | Y4: 1359729 | Z4: 1359729 | AA4: 1 | AB4: 1.2 | AC4: 0 | AD4: 0 | AE4: Bill on Actuals - 3rd Party Performance | AF4: 33993.24 | AG4: 1333334 | AH4: 40000.02 | AI4: A24 Death of Robin Hood/Digital/Scatter/AllFOX & Abs A/25.26/2Q26 | AJ4: 94341361 | AK4: P2+ | AL4: n/a | AN4: Kimberly Caraig | AO4: Guaranteed | AP4: DIO - LFV - RON Ent - Absolute A - Show Mix - DT/MB/CTV/STB | AQ4: 129821 | AR4: 46203 | AS4: 46174 | AT4: 46201 | AU4: Direct LFV | AW4: 46208.537
A5: ADVERTISING COUNCIL | B5: 11885 | C5: 1148 | D5: ADVERTISING COUNCIL | E5: Ad Council/2025/Dig/Pro-bono/2Q26/OneFox | F5: 265136 | G5: Ad Council - LFV - 1F - Pre/Mid - ROS - FW - SXD - Package- 2Q'26 - Pro-Bono | H5: 574526 | I5: Ad Council - DIO - ROV - 1F - SEN - Pre/Mid - ROS - DT/MB/CTV - SXD - 2Q'26 | J5: 92762829 | K5: OneFOX | L5: CPM | M5: 25 | N5: 3P Imps | O5: 1043604 | P5: 0 | S5: =IF(ISBLANK(R5)," ",ROUND(R5*(IF(ISBLANK(Q5),(M5/1000),(Q5/1000))),2)) | T5: =IF(IF(COUNTIF(H$2:$H5,H5)=1,1,"")=1,SUMIF($H$2:$H$7997,H5,$S$2:$S$7997),"") -> 0 | W5: 737435 | X5: 1043604 | Y5: 0 | Z5: 0 | AA5: 1 | AB5: 0 | AC5: 0 | AD5: 0 | AE5: Bill on Actuals - 3rd Party Performance | AF5: 0 | AG5: 3000000 | AH5: 0 | AI5: Ad Council/2025/Dig/Pro-bono/2Q26/OneFox | AJ5: 92762823 | AK5: P2+ | AN5: Nicholas Vara | AO5: Guaranteed | AP5: DIO - ROV - 1F - SEN - Pre/Mid - ROS - DT/MB/CTV - SXD | AQ5: 121448 | AR5: 46203 | AS5: 46113 | AT5: 46203 | AU5: Direct ROV | AW5: 46208.537
A6: ADVERTISING COUNCIL | B6: 11885 | C6: 1148 | D6: ADVERTISING COUNCIL | E6: Ad Council/2025/Dig/Pro-bono/2Q26/OneFox | F6: 265136 | G6: Ad Council - LFV - 1F - Pre/Mid - ROS - FW - SXD - Package- 2Q'26 - Pro-Bono | H6: 574526 | I6: Ad Council - LFV - 1F - Tubi - Pre/Mid - ROS - DT/MB/CTV - FW - SXD - 2Q'26 | J6: 92762826 | K6: Fox Sold Tubi | L6: CPM | M6: 25 | N6: 3P Imps | O6: 1017750 | P6: 0 | S6: =IF(ISBLANK(R6)," ",ROUND(R6*(IF(ISBLANK(Q6),(M6/1000),(Q6/1000))),2)) | T6: =IF(IF(COUNTIF(H$2:$H6,H6)=1,1,"")=1,SUMIF($H$2:$H$7997,H6,$S$2:$S$7997),"") | W6: 741825 | X6: 1017750 | Y6: 0 | Z6: 0 | AA6: 1 | AB6: 0 | AC6: 0 | AD6: 0 | AE6: Bill on Actuals - 3rd Party Performance | AF6: 0 | AG6: 3000000 | AH6: 0 | AI6: Ad Council/2025/Dig/Pro-bono/2Q26/OneFox | AJ6: 92762823 | AK6: P2+ | AN6: Nicholas Vara | AO6: Guaranteed | AP6: LFV - 1F - Tubi - Pre/Mid - ROS - DT/MB/CTV - FW - SXD | AQ6: 121448 | AR6: 46203 | AS6: 46113 | AT6: 46203 | AU6: Direct LFV | AW6: 46208.537
A7: AEGIS INNOV8 LLC | B7: 11309 | C7: 8106 | D7: HEINEKEN | E7: HEINEKEN- Deportes - Digital - UF 2025/26- 2Q26 | F7: 264662 | G7: Heineken - Deportes - ROS - A21-54 - Upfront 25/26 - 2Q'26 | H7: 572919 | I7: Heineken - Deportes - DIO - SFV - FSEN - Pre - ROS - DT/MB/CTV - non-CoV | J7: 94782838 | K7: FSEN | L7: Flat Rate | M7: 27.92 | N7: Bill on Contract | O7: 53006 | P7: 1479.94 | S7: =IF(ISBLANK(R7)," ",ROUND(R7*(IF(ISBLANK(Q7),(M7/1000),(Q7/1000))),2)) | T7: =IF(IF(COUNTIF(H$2:$H7,H7)=1,1,"")=1,SUMIF($H$2:$H$7997,H7,$S$2:$S$7997),"") -> 0 | W7: 325960 | X7: 325960 | Y7: 133244 | Z7: 133244 | AA7: 1 | AB7: 0.40877502 | AC7: 0 | AD7: 0 | AE7: Bill on Contract - Straightline | AF7: 1479.94 | AG7: 159083 | AH7: 4441.6 | AI7: HEINEKEN- Deportes - Digital - UF 2025/26- 2Q26 | AJ7: 92798069 | AK7: P21-54 | AL7: O-DNH1JO | AN7: Mike Maresca | AO7: Guaranteed | AP7: DIO - SFV - FSEN - Pre - ROS - DT/MB/CTV - non-CoV | AQ7: 121258 | AR7: 46203 | AS7: 46113 | AT7: 46203 | AU7: Direct SFV | AW7: 46208.537
A8: AEGIS INNOV8 LLC | B8: 11309 | C8: 8106 | D8: HEINEKEN | E8: HEINEKEN- Deportes - Digital - UF 2025/26- 2Q26 | F8: 264662 | G8: Heineken - Deportes - ROS - A21-54 - Upfront 25/26 - 2Q'26 | H8: 572919 | I8: Heineken - Deportes - LFV - FSLS - Pre/Mid - A21-54 - ROS - DT/MB/CTV - 2Q'26 | J8: 92798072 | K8: FOX Sports Streaming | L8: CPM | M8: 27.92 | N8: 3P CoView Imps | O8: 8570 | P8: 186.06 | S8: =IF(ISBLANK(R8)," ",ROUND(R8*(IF(ISBLANK(Q8),(M8/1000),(Q8/1000))),2)) | T8: =IF(IF(COUNTIF(H$2:$H8,H8)=1,1,"")=1,SUMIF($H$2:$H$7997,H8,$S$2:$S$7997),"") | V8: Show Only Net; NONE | W8: 18547 | X8: 11410 | Y8: 13931 | Z8: 8570 | AA8: 1 | AB8: 0.75111878 | AC8: 0 | AD8: 0 | AE8: Bill on Contract - Straightline | AF8: 186.06 | AG8: 20000 | AH8: 558.4 | AI8: HEINEKEN- Deportes - Digital - UF 2025/26- 2Q26 | AJ8: 92798069 | AK8: P21-54 | AL8: O-DNH1JO | AN8: Mike Maresca | AO8: Guaranteed | AP8: LFV - FSLS - Pre/Mid - ROS - DT/MB/CTV | AQ8: 121258 | AR8: 46203 | AS8: 46113 | AT8: 46203 | AU8: Direct LFV | AW8: 46208.537
A9: AEGIS INNOV8 LLC | B9: 11309 | C9: 8106 | D9: HEINEKEN | E9: Heineken/2Q-3Q'26 Scatter/Digital/MWC | F9: 270111 | G9: Heineken - Run of World Cup Video - AAT 21+ - Package | H9: 590783 | I9: Heineken - DIO - LFV - TUB - Pre/Mid - MWC - AAT 21+ - DT/MB/CTV | J9: 94404208 | K9: Fox Sold Tubi | L9: CPM | M9: 40 | N9: 3P Audience Target | O9: 2037014 | P9: 81480.56 | S9: =IF(ISBLANK(R9)," ",ROUND(R9*(IF(ISBLANK(Q9),(M9/1000),(Q9/1000))),2)) | T9: =IF(IF(COUNTIF(H$2:$H9,H9)=1,1,"")=1,SUMIF($H$2:$H$7997,H9,$S$2:$S$7997),"") -> 0 | W9: 2037014 | X9: 2037014 | Y9: 0 | Z9: 0 | AA9: 1 | AB9: 0 | AC9: 0 | AD9: 0 | AE9: Bill on Actuals - 3rd Party Performance | AF9: 47629.22 | AG9: 3062500 | AH9: 122500 | AI9: Heineken/2Q-3Q'26 Scatter/Digital/MWC | AJ9: 94404205 | AK9: Audience Target | AL9: O-D3098T8 | AN9: Mike Maresca | AO9: Guaranteed | AP9: DIO - LFV - TUB - Pre/Mid - MWC - DT/MB/CTV | AQ9: 129870 | AR9: 46203 | AS9: 46174 | AT9: 46222 | AU9: Direct LFV | AW9: 46208.537
A10: AEGIS INNOV8 LLC | B10: 11309 | C10: 8106 | D10: HEINEKEN | E10: Heineken/2Q-3Q'26 Scatter/Digital/MWC | F10: 270111 | G10: Heineken - Run of World Cup Video - AAT 21+ - Package | H10: 590783 | I10: Heineken - DIO - ROV - FS - Pre/Mid - MWC - AAT 21+ - DT/MB/CTV | J10: 94404211 | K10: FOX Sports | L10: CPM | M10: 40 | N10: 3P Audience Target | O10: 890204 | P10: 35608.16 | S10: =IF(ISBLANK(R10)," ",ROUND(R10*(IF(ISBLANK(Q10),(M10/1000),(Q10/1000))),2)) | T10: =IF(IF(COUNTIF(H$2:$H10,H10)=1,1,"")=1,SUMIF($H$2:$H$7997,H10,$S$2:$S$7997),"") | W10: 890204 | X10: 890204 | Y10: 0 | Z10: 0 | AA10: 1 | AB10: 0 | AC10: 0 | AD10: 0 | AE10: Bill on Actuals - 3rd Party Performance | AF10: 20412.52 | AG10: 1312500 | AH10: 52500 | AI10: Heineken/2Q-3Q'26 Scatter/Digital/MWC | AJ10: 94404205 | AK10: Audience Target | AL10: O-D3098T8 | AN10: Mike Maresca | AO10: Guaranteed | AP10: DIO - ROV - FS - Pre/Mid - MWC - DT/MB/CTV | AQ10: 129870 | AR10: 46203 | AS10: 46174 | AT10: 46222 | AU10: Direct ROV | AW10: 46208.537
A11: AEGIS INNOV8 LLC | B11: 11309 | C11: 8106 | D11: HEINEKEN | E11: Heineken/2Q-3Q'26 Scatter/Digital/MWC | F11: 270111 | G11: Heineken - World Cup Social Sponsorship Content - Package | H11: 590855 | I11: Heineken - DIO - SOC - FOX Sports - X - MWC | J11: 590857 | K11: FOX Sports - Twitter | L11: Flat Rate | M11: 225000 | N11: Bill on Contract | O11: 0 | P11: 68877.55 | S11: =IF(ISBLANK(R11)," ",ROUND(R11*(IF(ISBLANK(Q11),(M11/1000),(Q11/1000))),2)) | T11: =IF(IF(COUNTIF(H$2:$H11,H11)=1,1,"")=1,SUMIF($H$2:$H$7997,H11,$S$2:$S$7997),"") -> 0 | W11: 0 | X11: 0 | Y11: 0 | Z11: 0 | AA11: 1 | AB11: 0 | AC11: 0 | AD11: 0 | AE11: Bill on Contract - Pro-rated | AF11: 68877.55 | AG11: 225000 | AH11: 225000 | AI11: Heineken/2Q-3Q'26 Scatter/Digital/MWC | AJ11: 270111 | AK11: P2+ | AL11: O-D3098T8 | AN11: Mike Maresca | AO11: Guaranteed | AP11: DIO - SOC - FOX Sports - X - MWC | AQ11: 129870 | AR11: 46203 | AS11: 46174 | AT11: 46222 | AU11: Social X | AW11: 46208.537
A12: APEX EXCHANGE | B12: 10564 | C12: 8880 | D12: ABBVIE | E12: AbbVie Skyrizi PS DSA1 /25-26/Digital/Scatter/Entertainment/ | F12: 264043 | G12: Abbvie Skyrizi PS DSA1 - DIO - LFV - Entertainment ROS | H12: 578383 | I12: Abbvie Skyrizi PS DSA1 - DIO - LFV - RON Ent - Pre/Mid - ROS - CTV June | J12: 92973566 | K12: RON - Ent | L12: CPM | M12: 13.6 | N12: 3P CoView Imps | O12: 4309974 | P12: 53169.23 | S12: =IF(ISBLANK(R12)," ",ROUND(R12*(IF(ISBLANK(Q12),(M12/1000),(Q12/1000))),2)) | T12: =IF(IF(COUNTIF(H$2:$H12,H12)=1,1,"")=1,SUMIF($H$2:$H$7997,H12,$S$2:$S$7997),"") -> 0 | V12: Show Only Net; NONE | W12: 3390322 | X12: 3390322 | Y12: 4309974 | Z12: 4309974 | AA12: 1 | AB12: 1.2712582 | AC12: 0 | AD12: 0 | AE12: Bill on Actuals - 3rd Party Performance | AF12: 50940.75 | AG12: 3909502 | AH12: 53169.23 | AI12: AbbVie Skyrizi PS DSA1 /25-26/Digital/Scatter/Entertainment/ | AJ12: 92973560 | AK12: P2+ | AL12: O-D2PDCUV | AN12: Carly Sartwell | AO12: Guaranteed | AP12: DIO - LFV - RON Ent - Pre/Mid - ROS - DT/MB/CTV/STB | AQ12: 123490 | AR12: 46203 | AS12: 46113 | AT12: 46203 | AU12: Direct LFV | AW12: 46208.537
A13: APEX EXCHANGE | B13: 10564 | C13: 8880 | D13: ABBVIE | E13: AbbVie Skyrizi PS DSA1 /25-26/Digital/Scatter/Entertainment/ | F13: 264043 | G13: Abbvie Skyrizi PS DSA1 - DIO - LFV - Entertainment ROS | H13: 578383 | I13: Abbvie Skyrizi PS DSA1 - DIO - LFV - RON Ent - Pre/Mid - ROS - DT/MB/TB June | J13: 92973575 | K13: RON - Ent | L13: CPM | M13: 13.6 | N13: 3P Imps | O13: 1526883 | P13: 20765.61 | S13: =IF(ISBLANK(R13)," ",ROUND(R13*(IF(ISBLANK(Q13),(M13/1000),(Q13/1000))),2)) | T13: =IF(IF(COUNTIF(H$2:$H13,H13)=1,1,"")=1,SUMIF($H$2:$H$7997,H13,$S$2:$S$7997),"") | W13: 1526883 | X13: 1526883 | Y13: 0 | Z13: 0 | AA13: 1 | AB13: 0 | AC13: 0 | AD13: 0 | AE13: Bill on Actuals - 3rd Party Performance | AF13: 28654.17 | AG13: 2199095 | AH13: 29907.69 | AI13: AbbVie Skyrizi PS DSA1 /25-26/Digital/Scatter/Entertainment/ | AJ13: 92973560 | AK13: P2+ | AL13: O-D2PDCUV | AN13: Carly Sartwell | AO13: Guaranteed | AP13: DIO - LFV - RON Ent - Pre/Mid - ROS - DT/MB/CTV/STB | AQ13: 123490 | AR13: 46203 | AS13: 46113 | AT13: 46203 | AU13: Direct LFV | AW13: 46208.537
A14: APEX EXCHANGE | B14: 10564 | C14: 7472 | D14: PARAMOUNT PICTURES | E14: Paramount Pictures - Jackass 5/Digital/Satter/2Q26 | F14: 270352 | G14: APEX - Paramount Pictures - Jackass 5 - Entertainment ROS - AAT M18-34 - 2Q'26 Package | H14: 591418 | I14: APEX - Paramount Pictures - DIO - LFV - RON Ent - Pre/Mid - ROS - DT/MB/CTV/STB - AAT M18-34 - Jackass 5 - 2Q'26 | J14: 94320519 | K14: RON - Ent | L14: CPM | M14: 20 | N14: 3P Audience Target | O14: 3041031 | P14: 60000 | S14: =IF(ISBLANK(R14)," ",ROUND(R14*(IF(ISBLANK(Q14),(M14/1000),(Q14/1000))),2)) | T14: =IF(IF(COUNTIF(H$2:$H14,H14)=1,1,"")=1,SUMIF($H$2:$H$7997,H14,$S$2:$S$7997),"") -> 0 | V14: Show Only Net; NONE | W14: 3041031 | X14: 3041031 | Y14: 0 | Z14: 0 | AA14: 1 | AB14: 0 | AC14: 0 | AD14: 0 | AE14: Bill on Actuals - 3rd Party Performance | AF14: 60000 | AG14: 3000000 | AH14: 60000 | AI14: Paramount Pictures - Jackass 5/Digital/Satter/2Q26 | AJ14: 94320445 | AK14: Audience Target | AL14: O-D30JBH2 | AN14: Jeanne Feeley | AO14: Guaranteed | AP14: DIO - LFV - RON Ent - Pre/Mid - ROS - DT/MB/CTV/STB | AQ14: 129661 | AR14: 46203 | AS14: 46174 | AT14: 46201 | AU14: Direct LFV | AW14: 46208.537
A15: APEX EXCHANGE | B15: 10564 | C15: 7472 | D15: PARAMOUNT PICTURES | E15: Scary Movie/Digital/Scatter/2Q26 | F15: 269597 | G15: APEX - Paramount Pictures - Scary Movie - Entertainment ROS - AAT A18-34 - 2Q'26 Package | H15: 588711 | I15: APEX - Scary Movie - DIO - LFV - RON Ent - Pre/Mid - ROS - DT/MB/CTV/STB - AAT 18-34 - 2Q'26 | J15: 93993815 | K15: RON - Ent | L15: CPM | M15: 20 | N15: 3P Audience Target | O15: 2321592 | P15: 46431.84 | S15: =IF(ISBLANK(R15)," ",ROUND(R15*(IF(ISBLANK(Q15),(M15/1000),(Q15/1000))),2)) | T15: =IF(IF(COUNTIF(H$2:$H15,H15)=1,1,"")=1,SUMIF($H$2:$H$7997,H15,$S$2:$S$7997),"") -> 0 | V15: Show Only Net; NONE | W15: 698080 | X15: 2321592 | Y15: 0 | Z15: 0 | AA15: 1 | AB15: 0 | AC15: 0 | AD15: 0 | AE15: Bill on Actuals - 3rd Party Performance | AF15: 13568.16 | AG15: 3000000 | AH15: 60000 | AI15: Scary Movie/Digital/Scatter/2Q26 | AJ15: 93993360 | AK15: Audience Target | AL15: O-D2V5ENF-R0 | AN15: Jeanne Feeley | AO15: Guaranteed | AP15: DIO - LFV - RON Ent - Pre/Mid - ROS - DT/MB/CTV/STB | AQ15: 128349 | AR15: 46203 | AS15: 46155 | AT15: 46180 | AU15: Direct LFV | AW15: 46208.537
A16: BLISS POINT MEDIA | B16: 10966 | C16: 5472 | D16: ALBERT | E16: Albert/25-26/2Q'26/Digital/One Fox | F16: 265792 | G16: Albert - DIO - ROV - 1F SEN - Pre/Mid - ROS - FW - SXD - 2Q'26 | H16: 591110 | I16: Albert - DIO - LFV - 1F - Tubi - Pre/Mid - ROS - DT/MB/CTV - FW - SXD - 2Q'26 | J16: 94295266 | K16: Fox Sold Tubi | L16: CPM | M16: 17 | N16: 3P Imps | O16: 45614 | P16: 750.18 | S16: =IF(ISBLANK(R16)," ",ROUND(R16*(IF(ISBLANK(Q16),(M16/1000),(Q16/1000))),2)) | T16: =IF(IF(COUNTIF(H$2:$H16,H16)=1,1,"")=1,SUMIF($H$2:$H$7997,H16,$S$2:$S$7997),"") -> 0 | W16: 45614 | X16: 45614 | Y16: 0 | Z16: 0 | AA16: 1 | AB16: 0 | AC16: 0 | AD16: 0 | AE16: Bill on Actuals - 3rd Party Performance | AF16: 304.7 | AG16: 44128 | AH16: 750.18 | AI16: Albert/25-26/2Q'26/Digital/One Fox | AJ16: 93089294 | AK16: P2+ | AL16: 43091.1 | AN16: Jon Renz | AO16: Guaranteed | AP16: DIO - LFV - 1F - Tubi - Pre/Mid - ROS - DT/MB/CTV - FW - SXD | AQ16: 129468 | AR16: 46203 | AS16: 46174 | AT16: 46180 | AU16: Direct LFV | AW16: 46208.537
A17: BLISS POINT MEDIA | B17: 10966 | C17: 5472 | D17: ALBERT | E17: Albert/25-26/2Q'26/Digital/One Fox | F17: 265792 | G17: Albert - DIO - ROV - 1F SEN - Pre/Mid - ROS - FW - SXD - 2Q'26 | H17: 591110 | I17: Albert - DIO - ROV - 1F - SEN - Pre/Mid - ROS - DT/MB/CTV - SXD - 2Q'26 | J17: 94295272 | K17: OneFOX | L17: CPM | M17: 17 | N17: 3P Imps | O17: 105965 | P17: 1749.9 | S17: =IF(ISBLANK(R17)," ",ROUND(R17*(IF(ISBLANK(Q17),(M17/1000),(Q17/1000))),2)) | T17: =IF(IF(COUNTIF(H$2:$H17,H17)=1,1,"")=1,SUMIF($H$2:$H$7997,H17,$S$2:$S$7997),"") | W17: 105965 | X17: 105965 | Y17: 0 | Z17: 0 | AA17: 1 | AB17: 0 | AC17: 0 | AD17: 0 | AE17: Bill on Actuals - 3rd Party Performance | AF17: 710.76 | AG17: 102935 | AH17: 1749.9 | AI17: Albert/25-26/2Q'26/Digital/One Fox | AJ17: 93089294 | AK17: P2+ | AL17: 43091.1 | AN17: Jon Renz | AO17: Guaranteed | AP17: DIO - ROV - 1F - SEN - Pre/Mid - ROS - DT/MB/CTV - SXD | AQ17: 129468 | AR17: 46203 | AS17: 46174 | AT17: 46180 | AU17: Direct ROV | AW17: 46208.537
A18: BLISS POINT MEDIA | B18: 10966 | C18: 5472 | D18: ALBERT | E18: Albert/25-26/2Q'26/Digital/One Fox | F18: 265792 | G18: Albert - DIO - ROV - 1F SEN - Pre/Mid - ROS - FW - SXD - 2Q'26 | H18: 591123 | I18: Albert - DIO - LFV - 1F - Tubi - Pre/Mid - ROS - DT/MB/CTV - FW - SXD - 2Q'26 | J18: 94295269 | K18: Fox Sold Tubi | L18: CPM | M18: 17 | N18: 3P Imps | O18: 45803 | P18: 750.18 | S18: =IF(ISBLANK(R18)," ",ROUND(R18*(IF(ISBLANK(Q18),(M18/1000),(Q18/1000))),2)) | T18: =IF(IF(COUNTIF(H$2:$H18,H18)=1,1,"")=1,SUMIF($H$2:$H$7997,H18,$S$2:$S$7997),"") -> 0 | W18: 45803 | X18: 45803 | Y18: 0 | Z18: 0 | AA18: 1 | AB18: 0 | AC18: 0 | AD18: 0 | AE18: Bill on Actuals - 3rd Party Performance | AF18: 357.71 | AG18: 44128 | AH18: 750.18 | AI18: Albert/25-26/2Q'26/Digital/One Fox | AJ18: 93089294 | AK18: P2+ | AL18: 43091.1 | AN18: Jon Renz | AO18: Guaranteed | AP18: DIO - LFV - 1F - Tubi - Pre/Mid - ROS - DT/MB/CTV - FW - SXD | AQ18: 129468 | AR18: 46203 | AS18: 46181 | AT18: 46187 | AU18: Direct LFV | AW18: 46208.537
A19: BLISS POINT MEDIA | B19: 10966 | C19: 5472 | D19: ALBERT | E19: Albert/25-26/2Q'26/Digital/One Fox | F19: 265792 | G19: Albert - DIO - ROV - 1F SEN - Pre/Mid - ROS - FW - SXD - 2Q'26 | H19: 591123 | I19: Albert - DIO - ROV - 1F - SEN - Pre/Mid - ROS - DT/MB/CTV - SXD - 2Q'26 | J19: 94295262 | K19: OneFOX | L19: CPM | M19: 17 | N19: 3P Imps | O19: 106238 | P19: 1749.9 | S19: =IF(ISBLANK(R19)," ",ROUND(R19*(IF(ISBLANK(Q19),(M19/1000),(Q19/1000))),2)) | T19: =IF(IF(COUNTIF(H$2:$H19,H19)=1,1,"")=1,SUMIF($H$2:$H$7997,H19,$S$2:$S$7997),"") | W19: 106238 | X19: 106238 | Y19: 0 | Z19: 0 | AA19: 1 | AB19: 0 | AC19: 0 | AD19: 0 | AE19: Bill on Actuals - 3rd Party Performance | AF19: 834.41 | AG19: 102935 | AH19: 1749.9 | AI19: Albert/25-26/2Q'26/Digital/One Fox | AJ19: 93089294 | AK19: P2+ | AL19: 43091.1 | AN19: Jon Renz | AO19: Guaranteed | AP19: DIO - ROV - 1F - SEN - Pre/Mid - ROS - DT/MB/CTV - SXD | AQ19: 129468 | AR19: 46203 | AS19: 46181 | AT19: 46187 | AU19: Direct ROV | AW19: 46208.537
A20: BLISS POINT MEDIA | B20: 10966 | C20: 5472 | D20: ALBERT | E20: Albert/25-26/2Q'26/Digital/One Fox | F20: 265792 | G20: Albert - DIO - ROV - 1F SEN - Pre/Mid - ROS - FW - SXD - 2Q'26 | H20: 591126 | I20: Albert - DIO - LFV - 1F - Tubi - Pre/Mid - ROS - DT/MB/CTV - FW - SXD - 2Q'26 | J20: 94295284 | K20: Fox Sold Tubi | L20: CPM | M20: 17 | N20: 3P Imps | O20: 46061 | P20: 750.18 | S20: =IF(ISBLANK(R20)," ",ROUND(R20*(IF(ISBLANK(Q20),(M20/1000),(Q20/1000))),2)) | T20: =IF(IF(COUNTIF(H$2:$H20,H20)=1,1,"")=1,SUMIF($H$2:$H$7997,H20,$S$2:$S$7997),"") -> 0 | W20: 46061 | X20: 46061 | Y20: 0 | Z20: 0 | AA20: 1 | AB20: 0 | AC20: 0 | AD20: 0 | AE20: Bill on Actuals - 3rd Party Performance | AF20: 375.09 | AG20: 44128 | AH20: 750.18 | AI20: Albert/25-26/2Q'26/Digital/One Fox | AJ20: 93089294 | AK20: P2+ | AL20: 43091.1 | AN20: Jon Renz | AO20: Guaranteed | AP20: DIO - LFV - 1F - Tubi - Pre/Mid - ROS - DT/MB/CTV - FW - SXD | AQ20: 129468 | AR20: 46203 | AS20: 46188 | AT20: 46194 | AU20: Direct LFV | AW20: 46208.537
A21: BLISS POINT MEDIA | B21: 10966 | C21: 5472 | D21: ALBERT | E21: Albert/25-26/2Q'26/Digital/One Fox | F21: 265792 | G21: Albert - DIO - ROV - 1F SEN - Pre/Mid - ROS - FW - SXD - 2Q'26 | H21: 591126 | I21: Albert - DIO - ROV - 1F - SEN - Pre/Mid - ROS - DT/MB/CTV - SXD - 2Q'26 | J21: 94295295 | K21: OneFOX | L21: CPM | M21: 17 | N21: 3P Imps | O21: 106022 | P21: 1749.9 | S21: =IF(ISBLANK(R21)," ",ROUND(R21*(IF(ISBLANK(Q21),(M21/1000),(Q21/1000))),2)) | T21: =IF(IF(COUNTIF(H$2:$H21,H21)=1,1,"")=1,SUMIF($H$2:$H$7997,H21,$S$2:$S$7997),"") | W21: 106022 | X21: 106022 | Y21: 0 | Z21: 0 | AA21: 1 | AB21: 0 | AC21: 0 | AD21: 0 | AE21: Bill on Actuals - 3rd Party Performance | AF21: 874.95 | AG21: 102935 | AH21: 1749.9 | AI21: Albert/25-26/2Q'26/Digital/One Fox | AJ21: 93089294 | AK21: P2+ | AL21: 43091.1 | AN21: Jon Renz | AO21: Guaranteed | AP21: DIO - ROV - 1F - SEN - Pre/Mid - ROS - DT/MB/CTV - SXD | AQ21: 129468 | AR21: 46203 | AS21: 46188 | AT21: 46194 | AU21: Direct ROV | AW21: 46208.537
A22: BLISS POINT MEDIA | B22: 10966 | C22: 5472 | D22: ALBERT | E22: Albert/25-26/2Q'26/Digital/One Fox | F22: 265792 | G22: Albert - DIO - ROV - 1F SEN - Pre/Mid - ROS - FW - SXD - 2Q'26 | H22: 591129 | I22: Albert - DIO - LFV - 1F - Tubi - Pre/Mid - ROS - DT/MB/CTV - FW - SXD - 2Q'26 | J22: 94295278 | K22: Fox Sold Tubi | L22: CPM | M22: 17 | N22: 3P Imps | O22: 45961 | P22: 750.18 | S22: =IF(ISBLANK(R22)," ",ROUND(R22*(IF(ISBLANK(Q22),(M22/1000),(Q22/1000))),2)) | T22: =IF(IF(COUNTIF(H$2:$H22,H22)=1,1,"")=1,SUMIF($H$2:$H$7997,H22,$S$2:$S$7997),"") -> 0 | W22: 45961 | X22: 45961 | Y22: 0 | Z22: 0 | AA22: 1 | AB22: 0 | AC22: 0 | AD22: 0 | AE22: Bill on Actuals - 3rd Party Performance | AF22: 375.09 | AG22: 44128 | AH22: 750.18 | AI22: Albert/25-26/2Q'26/Digital/One Fox | AJ22: 93089294 | AK22: P2+ | AL22: 43091.1 | AN22: Jon Renz | AO22: Guaranteed | AP22: DIO - LFV - 1F - Tubi - Pre/Mid - ROS - DT/MB/CTV - FW - SXD | AQ22: 129468 | AR22: 46203 | AS22: 46195 | AT22: 46201 | AU22: Direct LFV | AW22: 46208.537
A23: BLISS POINT MEDIA | B23: 10966 | C23: 5472 | D23: ALBERT | E23: Albert/25-26/2Q'26/Digital/One Fox | F23: 265792 | G23: Albert - DIO - ROV - 1F SEN - Pre/Mid - ROS - FW - SXD - 2Q'26 | H23: 591129 | I23: Albert - DIO - ROV - 1F - SEN - Pre/Mid - ROS - DT/MB/CTV - SXD - 2Q'26 | J23: 94295291 | K23: OneFOX | L23: CPM | M23: 17 | N23: 3P Imps | O23: 97068 | P23: 1650.16 | S23: =IF(ISBLANK(R23)," ",ROUND(R23*(IF(ISBLANK(Q23),(M23/1000),(Q23/1000))),2)) | T23: =IF(IF(COUNTIF(H$2:$H23,H23)=1,1,"")=1,SUMIF($H$2:$H$7997,H23,$S$2:$S$7997),"") | W23: 97068 | X23: 97068 | Y23: 0 | Z23: 0 | AA23: 1 | AB23: 0 | AC23: 0 | AD23: 0 | AE23: Bill on Actuals - 3rd Party Performance | AF23: 874.95 | AG23: 102935 | AH23: 1749.9 | AI23: Albert/25-26/2Q'26/Digital/One Fox | AJ23: 93089294 | AK23: P2+ | AL23: 43091.1 | AN23: Jon Renz | AO23: Guaranteed | AP23: DIO - ROV - 1F - SEN - Pre/Mid - ROS - DT/MB/CTV - SXD | AQ23: 129468 | AR23: 46203 | AS23: 46195 | AT23: 46201 | AU23: Direct ROV | AW23: 46208.537
A24: BLISS POINT MEDIA | B24: 10966 | C24: 19872 | D24: KALSHI INC | E24: KALSHI INC / SCATTER / DIGITAL / FY 25-26 / World Cup digital | F24: 267803 | G24: Kalshi - Run of World Cup Video - MWC 2Q3Q26 | H24: 585576 | I24: Kalshi - DIO - LFV - TUB - Pre/Mid - MWC - DT/MB/CTV | J24: 94169082 | K24: Fox Sold Tubi | L24: CPM | M24: 44 | N24: 3P Imps | O24: 7048008 | P24: 310112.35 | S24: =IF(ISBLANK(R24)," ",ROUND(R24*(IF(ISBLANK(Q24),(M24/1000),(Q24/1000))),2)) | T24: =IF(IF(COUNTIF(H$2:$H24,H24)=1,1,"")=1,SUMIF($H$2:$H$7997,H24,$S$2:$S$7997),"") -> 0 | W24: 7048008 | X24: 7048008 | Y24: 0 | Z24: 0 | AA24: 1 | AB24: 0 | AC24: 0 | AD24: 0 | AE24: Bill on Actuals - 3rd Party Performance | AF24: 155241.83 | AG24: 10698864 | AH24: 470750.02 | AI24: KALSHI INC / SCATTER / DIGITAL / FY 25-26 / World Cup digital | AJ24: 94169055 | AK24: P2+ | AL24: 43543.4 | AN24: Adam Chardavoyne | AO24: Guaranteed | AP24: DIO - LFV - TUB - Pre/Mid - MWC - DT/MB/CTV | AQ24: 128876 | AR24: 46203 | AS24: 46174 | AT24: 46222 | AU24: Direct LFV | AW24: 46208.537
A25: BLISS POINT MEDIA | B25: 10966 | C25: 19872 | D25: KALSHI INC | E25: KALSHI INC / SCATTER / DIGITAL / FY 25-26 / World Cup digital | F25: 267803 | G25: Kalshi - Run of World Cup Video - MWC 2Q3Q26 | H25: 585576 | I25: Kalshi - DIO - ROV - FS - Pre/Mid - MWC - DT/MB/CTV | J25: 94169070 | K25: FOX Sports | L25: CPM | M25: 44 | N25: 3P Imps | O25: 3074716 | P25: 135287.5 | S25: =IF(ISBLANK(R25)," ",ROUND(R25*(IF(ISBLANK(Q25),(M25/1000),(Q25/1000))),2)) | T25: =IF(IF(COUNTIF(H$2:$H25,H25)=1,1,"")=1,SUMIF($H$2:$H$7997,H25,$S$2:$S$7997),"") | W25: 3074716 | X25: 3074716 | Y25: 0 | Z25: 0 | AA25: 1 | AB25: 0 | AC25: 0 | AD25: 0 | AE25: Bill on Actuals - 3rd Party Performance | AF25: 66532.21 | AG25: 4585227 | AH25: 201749.99 | AI25: KALSHI INC / SCATTER / DIGITAL / FY 25-26 / World Cup digital | AJ25: 94169055 | AK25: P2+ | AL25: 43543.4 | AN25: Adam Chardavoyne | AO25: Guaranteed | AP25: DIO - ROV - FS - Pre/Mid - MWC - DT/MB/CTV | AQ25: 128876 | AR25: 46203 | AS25: 46174 | AT25: 46222 | AU25: Direct ROV | AW25: 46208.537
A26: BLISS POINT MEDIA | B26: 10966 | C26: 19872 | D26: KALSHI INC | E26: KALSHI INC / SCATTER / DIGITAL / FY 25-26 / World Cup digital | F26: 267803 | G26: Kalshi - Run of AllFOX Video - Soccer Fans - MWC 2Q3Q26 - AAT | H26: 585595 | I26: Kalshi - DIO - LFV - 1F - Tubi - Pre/Mid - ROS - DT/MB/CTV - FW - SXD - AAT | J26: 94169089 | K26: Fox Sold Tubi | L26: CPM | M26: 20 | N26: 3P Audience Target | O26: 2008796 | P26: 40175.92 | S26: =IF(ISBLANK(R26)," ",ROUND(R26*(IF(ISBLANK(Q26),(M26/1000),(Q26/1000))),2)) | T26: =IF(IF(COUNTIF(H$2:$H26,H26)=1,1,"")=1,SUMIF($H$2:$H$7997,H26,$S$2:$S$7997),"") -> 0 | W26: 2008796 | X26: 2008796 | Y26: 0 | Z26: 0 | AA26: 1 | AB26: 0 | AC26: 0 | AD26: 0 | AE26: Bill on Actuals - 3rd Party Performance | AF26: 18376.07 | AG26: 6337500 | AH26: 126750 | AI26: KALSHI INC / SCATTER / DIGITAL / FY 25-26 / World Cup digital | AJ26: 94169055 | AK26: Audience Target | AL26: 43543.4 | AN26: Adam Chardavoyne | AO26: Guaranteed | AP26: DIO - LFV - 1F - Tubi - Pre/Mid - ROS - DT/MB/CTV - FW - SXD | AQ26: 128876 | AR26: 46203 | AS26: 46174 | AT26: 46292 | AU26: Direct LFV | AW26: 46208.537
A27: BLISS POINT MEDIA | B27: 10966 | C27: 19872 | D27: KALSHI INC | E27: KALSHI INC / SCATTER / DIGITAL / FY 25-26 / World Cup digital | F27: 267803 | G27: Kalshi - Run of AllFOX Video - Soccer Fans - MWC 2Q3Q26 - AAT | H27: 585595 | I27: Kalshi - DIO - ROV - 1F - SEN - Pre/Mid - ROS - DT/MB/CTV - SXD - AAT | J27: 94169061 | K27: OneFOX | L27: CPM | M27: 20 | N27: 3P Audience Target | O27: 4121095 | P27: 82421.9 | S27: =IF(ISBLANK(R27)," ",ROUND(R27*(IF(ISBLANK(Q27),(M27/1000),(Q27/1000))),2)) | T27: =IF(IF(COUNTIF(H$2:$H27,H27)=1,1,"")=1,SUMIF($H$2:$H$7997,H27,$S$2:$S$7997),"") | W27: 4121095 | X27: 4121095 | Y27: 0 | Z27: 0 | AA27: 1 | AB27: 0 | AC27: 0 | AD27: 0 | AE27: Bill on Actuals - 3rd Party Performance | AF27: 42877.49 | AG27: 14787500 | AH27: 295750 | AI27: KALSHI INC / SCATTER / DIGITAL / FY 25-26 / World Cup digital | AJ27: 94169055 | AK27: Audience Target | AL27: 43543.4 | AN27: Adam Chardavoyne | AO27: Guaranteed | AP27: DIO - ROV - 1F - SEN - Pre/Mid - ROS - DT/MB/CTV - SXD | AQ27: 128876 | AR27: 46203 | AS27: 46174 | AT27: 46292 | AU27: Direct ROV | AW27: 46208.537
... A34: BLISS POINT MEDIA | B34: 10966 | C34: 17500 | D34: RAMP.COM | E34: RAMP.COM / SCATTER / DIGITAL / SPORTS / FY Q4 25-26 / | F34: 266692 | G34: RAMP - DIO - ROV - FS - Pre/Mid - ROS - DT/MB - 2Q'26 | H34: 590846 | I34: RAMP - DIO - ROV - FS - Pre/Mid - ROS - DT/MB - 2Q'26 | J34: 94264168 | K34: FOX Sports | L34: CPM | M34: 28.75 | N34: 3P Imps | O34: 760 | P34: 21.85 | S34: =IF(ISBLANK(R34)," ",ROUND(R34*(IF(ISBLANK(Q34),(M34/1000),(Q34/1000))),2)) | T34: =IF(IF(COUNTIF(H$2:$H34,H34)=1,1,"")=1,SUMIF($H$2:$H$7997,H34,$S$2:$S$7997),"") -> 0 | W34: 760 | X34: 760 | Y34: 0 | Z34: 0 | AA34: 1 | AB34: 0 | AC34: 0 | AD34: 0 | AE34: Bill on Actuals - 3rd Party Performance | AF34: 9.99 | AG34: 48696 | AH34: 1400.01 | AI34: RAMP.COM / SCATTER / DIGITAL / SPORTS / FY Q4 25-26 / | AJ34: 93031315 | AK34: P2+ | AL34: 43210.1 | AN34: Adam Chardavoyne | AO34: Guaranteed | AP34: DIO - ROV - FS - Pre/Mid - ROS - DT/MB/CTV | AQ34: 129296 | AR34: 46203 | AS34: 46195 | AT34: 46201 | AU34: Direct ROV | AW34: 46208.537
A35: BPN | B35: 11163 | C35: 7672 | D35: BRISTOL MYERS SQUIBB | E35: BMS/25-26/Upfront/Digital/ENT/CAMZYOS | F35: 259418 | G35: BMS/UF/RON/25-26/AAT/2Q'26/CAMZYOS | H35: 556247 | I35: BMS/UF/RON/25-26/AAT/P35-64/2Q'26/CAMZYOS | J35: 90410993 | K35: RON - Ent | L35: CPM | M35: 42.4 | N35: 3P Audience Target | O35: 577030 | P35: 24466.07 | S35: =IF(ISBLANK(R35)," ",ROUND(R35*(IF(ISBLANK(Q35),(M35/1000),(Q35/1000))),2)) | T35: =IF(IF(COUNTIF(H$2:$H35,H35)=1,1,"")=1,SUMIF($H$2:$H$7997,H35,$S$2:$S$7997),"") -> 0 | V35: Show Only Net; NONE | W35: 216609 | X35: 577030 | Y35: 0 | Z35: 0 | AA35: 1 | AB35: 0 | AC35: 0 | AD35: 0 | AE35: Bill on Actuals - 3rd Party Performance | AF35: 9778.25 | AG35: 1768868 | AH35: 75000 | AI35: BMS/25-26/Upfront/Digital/ENT/CAMZYOS | AJ35: 90410989 | AK35: Audience Target | AL35: O-D2DMHIP-R10 | AN35: Jeanne Feeley | AO35: Guaranteed | AP35: DIO - LFV - RON Ent - Pre/Mid - ROS - DT/MB/CTV/STB | AQ35: 108708 | AR35: 46203 | AS35: 46113 | AT35: 46203 | AU35: Direct LFV | AW35: 46208.537
A36: BPN | B36: 11163 | C36: 7672 | D36: BRISTOL MYERS SQUIBB | E36: BMS/25-26/Upfront/Digital/ENT/COBENFY | F36: 259419 | G36: BMS/UF/RON/25-26/AAT/2Q'26/COBENFY | H36: 556624 | I36: BMS/UF/RON/25-26/AAT/P18-64/2Q'26/COBENFY | J36: 90411497 | K36: RON - Ent | L36: CPM | M36: 42.4 | N36: 3P Audience Target | O36: 0 | P36: 0 | S36: =IF(ISBLANK(R36)," ",ROUND(R36*(IF(ISBLANK(Q36),(M36/1000),(Q36/1000))),2)) | T36: =IF(IF(COUNTIF(H$2:$H36,H36)=1,1,"")=1,SUMIF($H$2:$H$7997,H36,$S$2:$S$7997),"") -> 0 | V36: Show Only Net; NONE | W36: 0 | X36: 0 | Y36: 0 | Z36: 0 | AA36: 1 | AB36: 0 | AC36: 0 | AD36: 0 | AE36: Bill on Actuals - 3rd Party Performance | AF36: 0 | AG36: 682694 | AH36: 28946.23 | AI36: BMS/25-26/Upfront/Digital/ENT/COBENFY | AJ36: 259419 | AK36: Audience Target | AL36: O-D2DMHCP-R11 | AN36: Jeanne Feeley | AO36: Guaranteed | AP36: DIO - LFV - RON Ent - Pre/Mid - ROS - DT/MB/CTV/STB | AQ36: 108718 | AR36: 46203 | AS36: 46113 | AT36: 46195 | AU36: Direct LFV | AW36: 46208.537
A37: BPN | B37: 11163 | C37: 7672 | D37: BRISTOL MYERS SQUIBB | E37: BMS/25-26/Upfront/Digital/ENT/QVANTIG | F37: 259421 | G37: BMS/UF/RON/25-26/AAT/2Q'26/QVANTIG | H37: 556628 | I37: BMS/UF/RON/25-26/AAT/P50+/2Q'26/QVANTIG | J37: 90411416 | K37: RON - Ent | L37: CPM | M37: 52.25 | N37: 3P Audience Target | O37: 309362 | P37: 16164.16 | S37: =IF(ISBLANK(R37)," ",ROUND(R37*(IF(ISBLANK(Q37),(M37/1000),(Q37/1000))),2)) | T37: =IF(IF(COUNTIF(H$2:$H37,H37)=1,1,"")=1,SUMIF($H$2:$H$7997,H37,$S$2:$S$7997),"") -> 0 | V37: Show Only Net; NONE | W37: 94262 | X37: 309362 | Y37: 0 | Z37: 0 | AA37: 1 | AB37: 0 | AC37: 0 | AD37: 0 | AE37: Bill on Actuals - 3rd Party Performance | AF37: 0.05 | AG37: 956938 | AH37: 50000.01 | AI37: BMS/25-26/Upfront/Digital/ENT/QVANTIG | AJ37: 90411410 | AK37: Audience Target | AL37: O-D2DMHIP-R10 | AN37: Jeanne Feeley | AO37: Guaranteed | AP37: DIO - LFV - RON Ent - Pre/Mid - ROS - DT/MB/CTV/STB | AQ37: 108730 | AR37: 46203 | AS37: 46113 | AT37: 46203 | AU37: Direct LFV | AW37: 46208.537
A38: BPN | B38: 11163 | C38: 7672 | D38: BRISTOL MYERS SQUIBB | E38: BMS/25-26/Upfront/Digital/Sports/CAMZYOS | F38: 259423 | G38: BMS/UF/SPORTS/D/25-26/LFV/AAT/2Q'26/CAMZYOS | H38: 556448 | I38: BMS/UF/SPORTS/D/25-26/LFV/AAT/P35-64/2Q'26/CAMZYOS/JUNE | J38: 93774048 | K38: FOX Sports Streaming | L38: CPM | M38: 59 | N38: 3P Audience Target | O38: 93597 | P38: 5522.22 | S38: =IF(ISBLANK(R38)," ",ROUND(R38*(IF(ISBLANK(Q38),(M38/1000),(Q38/1000))),2)) | T38: =IF(IF(COUNTIF(H$2:$H38,H38)=1,1,"")=1,SUMIF($H$2:$H$7997,H38,$S$2:$S$7997),"") -> 0 | W38: 93597 | X38: 93597 | Y38: 0 | Z38: 0 | AA38: 1 | AB38: 0 | AC38: 0 | AD38: 0 | AE38: Bill on Actuals - 3rd Party Performance | AF38: 1731.34 | AG38: 649532 | AH38: 38322.39 | AI38: BMS/25-26/Upfront/Digital/Sports/CAMZYOS | AJ38: 90408543 | AK38: Audience Target | AL38: O-D2G2382-R5 | AN38: Colleen Cahill | AO38: Guaranteed | AP38: DIO - LFV - FSLS - Pre/Mid - ROS - DT/MB/CTV | AQ38: 108737 | AR38: 46203 | AS38: 46113 | AT38: 46203 | AU38: Direct LFV | AW38: 46208.537
A39: BPN | B39: 11163 | C39: 7672 | D39: BRISTOL MYERS SQUIBB | E39: BMS/25-26/Upfront/Digital/Sports/COBENFY | F39: 259424 | G39: BMS/UF/SPORTS/D/25-26/LFV/AAT/2Q'26/COBENFY | H39: 556649 | I39: BMS/UF/SPORTS/D/25-26/LFV/AAT/P18-64/2Q'26/COBENFY/JUNE | J39: 93476104 | K39: FOX Sports Streaming | L39: CPM | M39: 59 | N39: 3P Audience Target | O39: 61072 | P39: 3564.13 | S39: =IF(ISBLANK(R39)," ",ROUND(R39*(IF(ISBLANK(Q39),(M39/1000),(Q39/1000))),2)) | T39: =IF(IF(COUNTIF(H$2:$H39,H39)=1,1,"")=1,SUMIF($H$2:$H$7997,H39,$S$2:$S$7997),"") -> 0 | W39: 61072 | X39: 61072 | Y39: 0 | Z39: 0 | AA39: 1 | AB39: 0 | AC39: 0 | AD39: 0 | AE39: Bill on Actuals - 3rd Party Performance | AF39: 1516.17 | AG39: 60409 | AH39: 3564.13 | AI39: BMS/25-26/Upfront/Digital/Sports/COBENFY | AJ39: 90465521 | AK39: Audience Target | AL39: O-D2G1SUF-R4 | AN39: Colleen Cahill | AO39: Guaranteed | AP39: DIO - LFV - FSLS - Pre/Mid - ROS - DT/MB/CTV | AQ39: 109443 | AR39: 46203 | AS39: 46113 | AT39: 46191 | AU39: Direct LFV | AW39: 46208.537
A40: CANVAS WORLDWIDE | B40: 11499 | C40: 4805 | D40: HYUNDAI | E40: Hyundai/Digital/Scatter/Sports/MWC/25-26 | F40: 261946 | G40: Hyundai - Run of World Cup Display - Package - 728x90, 300x250,320x50 - OMP | H40: 581295 | I40: Hyundai - DIS - FS - Display Unit - MWC - 728x90, 300x250,320x50 - OMP - JUNE | J40: 7291488921 | K40: FOX Sports | L40: CPM | M40: 10 | N40: 3P Imps | O40: 0 | P40: 0 | S40: =IF(ISBLANK(R40)," ",ROUND(R40*(IF(ISBLANK(Q40),(M40/1000),(Q40/1000))),2)) | T40: =IF(IF(COUNTIF(H$2:$H40,H40)=1,1,"")=1,SUMIF($H$2:$H$7997,H40,$S$2:$S$7997),"") -> 0 | W40: 0 | X40: 0 | Y40: 0 | Z40: 0 | AA40: 1 | AB40: 0 | AC40: 0 | AD40: 0 | AE40: Bill on Actuals - 3rd Party Performance | AF40: 15548.13 | AG40: 3672026 | AH40: 36720.26 | AI40: Hyundai/Digital/Scatter/Sports/MWC/25-26 | AJ40: 261946 | AK40: P2+ | AL40: tbd | AN40: Dylan Giordano | AO40: Guaranteed | AP40: DIS - FS - Display Unit - MWC | AQ40: 126577 | AR40: 46203 | AS40: 46174 | AT40: 46222 | AU40: Direct Display | AW40: 46208.537
A41: CANVAS WORLDWIDE | B41: 11499 | C41: 4805 | D41: HYUNDAI | E41: Hyundai/Digital/Scatter/Sports/MWC/25-26 | F41: 261946 | G41: Hyundai - World Cup Social Sponsorship Content - Package | H41: 582460 | I41: Hyundai - DIO - SOC - FOX Sports - Facebook/Instagram - MWC | J41: 582461 | K41: FOX Sports - FB-Inst | L41: Flat Rate | M41: 0.15 | N41: Bill on Contract | O41: 83333533 | P41: 12500.03 | S41: =IF(ISBLANK(R41)," ",ROUND(R41*(IF(ISBLANK(Q41),(M41/1000),(Q41/1000))),2)) | T41: =IF(IF(COUNTIF(H$2:$H41,H41)=1,1,"")=1,SUMIF($H$2:$H$7997,H41,$S$2:$S$7997),"") -> 0 | W41: 0 | X41: 0 | Y41: 0 | Z41: 0 | AA41: 1 | AB41: 0 | AC41: 0 | AD41: 0 | AE41: Bill on Contract - Straightline | AF41: 12500.03 | AG41: 333334 | AH41: 50000.1 | AI41: Hyundai/Digital/Scatter/Sports/MWC/25-26 | AJ41: 261946 | AK41: P2+ | AL41: tbd | AN41: Dylan Giordano | AO41: Guaranteed | AP41: DIO - SOC - FOX Sports - Facebook/Instagram - MWC | AQ41: 126577 | AR41: 46203 | AS41: 46174 | AT41: 46222 | AU41: Social Facebook/Instagram | AW41: 46208.537
A42: CANVAS WORLDWIDE | B42: 11499 | C42: 4805 | D42: HYUNDAI | E42: Hyundai/Digital/Scatter/Sports/MWC/25-26 | F42: 261946 | G42: Hyundai - World Cup Social Sponsorship Content - Package | H42: 582460 | I42: Hyundai - DIO - SOC - FOX Sports - TikTok - MWC | J42: 582464 | K42: FOX Sports - TikTok | L42: Flat Rate | M42: 0.15 | N42: Bill on Contract | O42: 83333533 | P42: 12500.03 | S42: =IF(ISBLANK(R42)," ",ROUND(R42*(IF(ISBLANK(Q42),(M42/1000),(Q42/1000))),2)) | T42: =IF(IF(COUNTIF(H$2:$H42,H42)=1,1,"")=1,SUMIF($H$2:$H$7997,H42,$S$2:$S$7997),"") | W42: 0 | X42: 0 | Y42: 0 | Z42: 0 | AA42: 1 | AB42: 0 | AC42: 0 | AD42: 0 | AE42: Bill on Contract - Straightline | AF42: 12500.03 | AG42: 333334 | AH42: 50000.1 | AI42: Hyundai/Digital/Scatter/Sports/MWC/25-26 | AJ42: 261946 | AK42: P2+ | AL42: tbd | AN42: Dylan Giordano | AO42: Guaranteed | AP42: DIO - SOC - FOX Sports - TikTok - MWC | AQ42: 126577 | AR42: 46203 | AS42: 46174 | AT42: 46222 | AU42: Social TikTok | AW42: 46208.537
A43: CANVAS WORLDWIDE | B43: 11499 | C43: 4805 | D43: HYUNDAI | E43: Hyundai/Digital/Scatter/Sports/MWC/25-26 | F43: 261946 | G43: Hyundai - World Cup Social Sponsorship Content - Package | H43: 582460 | I43: Hyundai - DIO - SOC - FOX Sports - Youtube - Custom Content - MWC | J43: 582463 | K43: FOX Sports | L43: Flat Rate | M43: 0.15 | N43: Bill on Contract | O43: 83333533 | P43: 12500.03 | S43: =IF(ISBLANK(R43)," ",ROUND(R43*(IF(ISBLANK(Q43),(M43/1000),(Q43/1000))),2)) | T43: =IF(IF(COUNTIF(H$2:$H43,H43)=1,1,"")=1,SUMIF($H$2:$H$7997,H43,$S$2:$S$7997),"") | W43: 0 | X43: 0 | Y43: 0 | Z43: 0 | AA43: 1 | AB43: 0 | AC43: 0 | AD43: 0 | AE43: Bill on Contract - Straightline | AF43: 12500.03 | AG43: 333334 | AH43: 50000.1 | AI43: Hyundai/Digital/Scatter/Sports/MWC/25-26 | AJ43: 261946 | AK43: P2+ | AL43: tbd | AN43: Dylan Giordano | AO43: Guaranteed | AP43: DIO - SOC - FOX Sports - Youtube - Custom Content - MWC | AQ43: 126577 | AR43: 46203 | AS43: 46174 | AT43: 46222 | AU43: Social | AW43: 46208.537
A44: CANVAS WORLDWIDE | B44: 11499 | C44: 4805 | D44: HYUNDAI | E44: Hyundai/Digital/Scatter/Sports/MWC/25-26 | F44: 261946 | G44: Hyundai - Run of World Cup Video - Package - OMP | H44: 582466 | I44: Hyundai - DIO - LFV - TUB - Pre/Mid - MWC - DT/MB/CTV - JUNE | J44: 93585697 | K44: Fox Sold Tubi | L44: CPM | M44: 40 | N44: 1P Imps | O44: 2624855 | P44: 104994.2 | S44: =IF(ISBLANK(R44)," ",ROUND(R44*(IF(ISBLANK(Q44),(M44/1000),(Q44/1000))),2)) | T44: =IF(IF(COUNTIF(H$2:$H44,H44)=1,1,"")=1,SUMIF($H$2:$H$7997,H44,$S$2:$S$7997),"") -> 0 | W44: 2624855 | X44: 2624855 | Y44: 0 | Z44: 0 | AA44: 1 | AB44: 0 | AC44: 0 | AD44: 0 | AE44: Bill on Actuals - 3rd Party Performance | AF44: 28843.55 | AG44: 2625000 | AH44: 105000 | AI44: Hyundai/Digital/Scatter/Sports/MWC/25-26 | AJ44: 93585683 | AK44: P2+ | AL44: tbd | AN44: Dylan Giordano | AO44: Guaranteed | AP44: DIO - LFV - TUB - Pre/Mid - MWC - DT/MB/CTV | AQ44: 126577 | AR44: 46203 | AS44: 46174 | AT44: 46222 | AU44: Direct LFV | AW44: 46208.537
A45: CANVAS WORLDWIDE | B45: 11499 | C45: 4805 | D45: HYUNDAI | E45: Hyundai/Digital/Scatter/Sports/MWC/25-26 | F45: 261946 | G45: Hyundai - Run of World Cup Video - Package - OMP | H45: 582466 | I45: Hyundai - DIO - ROV - FS - Pre/Mid - MWC - DT/MB/CTV - JUNE | J45: 93585700 | K45: FOX Sports | L45: CPM | M45: 40 | N45: 3P Imps | O45: 1140265 | P45: 45000 | S45: =IF(ISBLANK(R45)," ",ROUND(R45*(IF(ISBLANK(Q45),(M45/1000),(Q45/1000))),2)) | T45: =IF(IF(COUNTIF(H$2:$H45,H45)=1,1,"")=1,SUMIF($H$2:$H$7997,H45,$S$2:$S$7997),"") | W45: 1140265 | X45: 1140265 | Y45: 0 | Z45: 0 | AA45: 1 | AB45: 0 | AC45: 0 | AD45: 0 | AE45: Bill on Actuals - 3rd Party Performance | AF45: 12361.52 | AG45: 1125000 | AH45: 45000 | AI45: Hyundai/Digital/Scatter/Sports/MWC/25-26 | AJ45: 93585683 | AK45: P2+ | AL45: tbd | AN45: Dylan Giordano | AO45: Guaranteed | AP45: DIO - ROV - FS - Pre/Mid - MWC - DT/MB/CTV | AQ45: 126577 | AR45: 46203 | AS45: 46174 | AT45: 46222 | AU45: Direct ROV | AW45: 46208.537
A46: CANVAS WORLDWIDE | B46: 11499 | C46: 4805 | D46: HYUNDAI | E46: Hyundai/Digital/Scatter/Sports/MWC/25-26 | F46: 261946 | G46: Hyundai - Run of FOX Sports Display - Package - 728x90, 300x250,320x50, 300x600 - OMP | H46: 582471 | I46: Hyundai - DIS - FS - Display Unit - ROS - 728x90, 300x250,320x50, 300x600 - OMP - JUNE | J46: 7293780886 | K46: FOX Sports | L46: CPM | M46: 5 | N46: 3P Imps | O46: 0 | P46: 0 | S46: =IF(ISBLANK(R46)," ",ROUND(R46*(IF(ISBLANK(Q46),(M46/1000),(Q46/1000))),2)) | T46: =IF(IF(COUNTIF(H$2:$H46,H46)=1,1,"")=1,SUMIF($H$2:$H$7997,H46,$S$2:$S$7997),"") -> 0 | W46: 0 | X46: 0 | Y46: 0 | Z46: 0 | AA46: 1 | AB46: 0 | AC46: 0 | AD46: 0 | AE46: Bill on Actuals - 3rd Party Performance | AF46: 26860.94 | AG46: 13000000 | AH46: 65000 | AI46: Hyundai/Digital/Scatter/Sports/MWC/25-26 | AJ46: 261946 | AK46: P2+ | AL46: tbd | AN46: Dylan Giordano | AO46: Guaranteed | AP46: DIS - FS - Display Unit - ROS | AQ46: 126577 | AR46: 46203 | AS46: 46174 | AT46: 46234 | AU46: Direct Display | AW46: 46208.537
A47: CANVAS WORLDWIDE | B47: 11499 | C47: 4805 | D47: HYUNDAI | E47: Hyundai/Digital/Scatter/Sports/MWC/25-26 | F47: 261946 | G47: Hyundai - Run of AllFOX Video - Package | H47: 582565 | I47: Hyundai - DIO - LFV - 1F - Tubi - Pre/Mid - ROS - DT/MB/CTV - FW - SXD - JUNE | J47: 93585694 | K47: Fox Sold Tubi | L47: CPM | M47: 23 | N47: 3P Audience Target | O47: 656743 | P47: 14625.01 | S47: =IF(ISBLANK(R47)," ",ROUND(R47*(IF(ISBLANK(Q47),(M47/1000),(Q47/1000))),2)) | T47: =IF(IF(COUNTIF(H$2:$H47,H47)=1,1,"")=1,SUMIF($H$2:$H$7997,H47,$S$2:$S$7997),"") -> 0 | W47: 656743 | X47: 656743 | Y47: 0 | Z47: 0 | AA47: 1 | AB47: 0 | AC47: 0 | AD47: 0 | AE47: Bill on Actuals - 3rd Party Performance | AF47: 3611.61 | AG47: 635870 | AH47: 14625.01 | AI47: Hyundai/Digital/Scatter/Sports/MWC/25-26 | AJ47: 93585683 | AK47: Audience Target | AL47: tbd | AN47: Dylan Giordano | AO47: Guaranteed | AP47: DIO - LFV - 1F - Tubi - Pre/Mid - ROS - DT/MB/CTV - FW - SXD | AQ47: 126577 | AR47: 46203 | AS47: 46174 | AT47: 46222 | AU47: Direct LFV | AW47: 46208.537
A48: CANVAS WORLDWIDE | B48: 11499 | C48: 4805 | D48: HYUNDAI | E48: Hyundai/Digital/Scatter/Sports/MWC/25-26 | F48: 261946 | G48: Hyundai - Run of AllFOX Video - Package | H48: 582565 | I48: Hyundai - DIO - ROV - 1F - SEN - Pre/Mid - ROS - DT/MB/CTV - SXD - JUNE | J48: 93585686 | K48: OneFOX | L48: CPM | M48: 23 | N48: 3P Audience Target | O48: 1723595 | P48: 39642.68 | S48: =IF(ISBLANK(R48)," ",ROUND(R48*(IF(ISBLANK(Q48),(M48/1000),(Q48/1000))),2)) | T48: =IF(IF(COUNTIF(H$2:$H48,H48)=1,1,"")=1,SUMIF($H$2:$H$7997,H48,$S$2:$S$7997),"") | W48: 1723595 | X48: 1723595 | Y48: 0 | Z48: 0 | AA48: 1 | AB48: 0 | AC48: 0 | AD48: 0 | AE48: Bill on Actuals - 3rd Party Performance | AF48: 14909.46 | AG48: 2625000 | AH48: 60375 | AI48: Hyundai/Digital/Scatter/Sports/MWC/25-26 | AJ48: 93585683 | AK48: Audience Target | AL48: tbd | AN48: Dylan Giordano | AO48: Guaranteed | AP48: DIO - ROV - 1F - SEN - Pre/Mid - ROS - DT/MB/CTV - SXD | AQ48: 126577 | AR48: 46203 | AS48: 46174 | AT48: 46222 | AU48: Direct ROV | AW48: 46208.537
A49: CANVAS WORLDWIDE | B49: 11499 | C49: 2619 | D49: KIA | E49: Kia/Digital/Scatter/Sports/MWC/25-26 | F49: 268009 | G49: KIA - Run of World Cup Display - Package -320x50, 300x250, 728x90 - OMP | H49: 585836 | I49: KIA - DIS - FS - Display Unit - MWC - 320x50, 300x250, 728x90 - OMP - JUNE | J49: 7299310220 | K49: FOX Sports | L49: CPM | M49: 6 | N49: 3P Imps | O49: 0 | P49: 0 | S49: =IF(ISBLANK(R49)," ",ROUND(R49*(IF(ISBLANK(Q49),(M49/1000),(Q49/1000))),2)) | T49: =IF(IF(COUNTIF(H$2:$H49,H49)=1,1,"")=1,SUMIF($H$2:$H$7997,H49,$S$2:$S$7997),"") -> 0 | W49: 0 | X49: 0 | Y49: 0 | Z49: 0 | AA49: 1 | AB49: 0 | AC49: 0 | AD49: 0 | AE49: Bill on Actuals - 3rd Party Performance | AF49: 22326.58 | AG49: 8831668 | AH49: 52990.01 | AI49: Kia/Digital/Scatter/Sports/MWC/25-26 | AJ49: 268009 | AK49: P2+ | AL49: O-D2RBLEI-R2 | AN49: Dylan Giordano | AO49: Guaranteed | AP49: DIS - FS - Display Unit - MWC | AQ49: 127039 | AR49: 46203 | AS49: 46184 | AT49: 46222 | AU49: Direct Display | AW49: 46208.537
... A56: CANVAS WORLDWIDE | B56: 11499 | C56: 2619 | D56: KIA | E56: Kia/Digital/Scatter/Sports/MWC/25-26 | F56: 268009 | G56: KIA - Run of AllFOX Video - Package | H56: 585848 | I56: KIA - DIO - ROV - 1F - SEN - Pre/Mid - ROS - DT/MB/CTV - SXD - JUNE | J56: 93722480 | K56: OneFOX | L56: CPM | M56: 23 | N56: 3P Audience Target | O56: 4244625 | P56: 94948.72 | S56: =IF(ISBLANK(R56)," ",ROUND(R56*(IF(ISBLANK(Q56),(M56/1000),(Q56/1000))),2)) | T56: =IF(IF(COUNTIF(H$2:$H56,H56)=1,1,"")=1,SUMIF($H$2:$H$7997,H56,$S$2:$S$7997),"") | W56: 4244625 | X56: 4244625 | Y56: 0 | Z56: 0 | AA56: 1 | AB56: 0 | AC56: 0 | AD56: 0 | AE56: Bill on Actuals - 3rd Party Performance | AF56: 33018.01 | AG56: 4128205 | AH56: 94948.72 | AI56: Kia/Digital/Scatter/Sports/MWC/25-26 | AJ56: 93722464 | AK56: Audience Target | AL56: O-D2RBLEI-R2 | AN56: Dylan Giordano | AO56: Guaranteed | AP56: DIO - ROV - 1F - SEN - Pre/Mid - ROS - DT/MB/CTV - SXD | AQ56: 127039 | AR56: 46203 | AS56: 46184 | AT56: 46222 | AU56: Direct ROV | AW56: 46208.537
A57: CANVAS WORLDWIDE | B57: 11499 | C57: 2619 | D57: KIA | E57: Kia/Digital/Upfront/Entertainment/UF 2025/26 - 1-3Q26 | F57: 252314 | G57: KIA - LFV - RON Ent - ROS - Pre/Mid - DT/MB/CTV/VOD - Package - 3Q'26 | H57: 537026 | I57: KIA - LFV - RON Ent - Pre/Mid - ROS - DT/MB/CTV/STB - A2554 - 3Q'26 | J57: 88777089 | K57: RON - Ent | L57: CPM | M57: 33.57 | N57: 3P CoView Imps | O57: 0 | P57: 0 | S57: =IF(ISBLANK(R57)," ",ROUND(R57*(IF(ISBLANK(Q57),(M57/1000),(Q57/1000))),2)) | T57: =IF(IF(COUNTIF(H$2:$H57,H57)=1,1,"")=1,SUMIF($H$2:$H$7997,H57,$S$2:$S$7997),"") -> 0 | V57: Show Only Net | W57: 0 | X57: 0 | Y57: 0 | Z57: 0 | AA57: 1 | AB57: 0 | AC57: 0 | AD57: 0 | AE57: Bill on Actuals - 3rd Party Performance | AF57: 0 | AG57: 7447126 | AH57: 250000.02 | AI57: Kia/Digital/Upfront/Entertainment/UF 2025/26 - 1-3Q26 | AJ57: 252314 | AK57: P25-54 | AL57: O-D2FCJC9 | AN57: Allison Klein | AO57: Guaranteed | AP57: LFV - RON Ent - Pre/Mid - ROS - DT/MB/CTV/STB | AQ57: 96341 | AR57: 46203 | AS57: 46202 | AT57: 46292 | AU57: Direct LFV | AW57: 46208.537
A58: CANVAS WORLDWIDE | B58: 11499 | C58: 889 | D58: ZILLOW.COM | E58: Zillow 2026 MWC Digital Plan | F58: 260564 | G58: Zillow - DIO - SOC - FS - MWC - Social Package | H58: 558520 | I58: Zillow - DIO - SOC - FOX Sports - Facebook/Instagram - MWC | J58: 558521 | K58: FOX Sports - FB-Inst | L58: Flat Rate | M58: 1000000 | N58: Bill on Contract | O58: 0 | P58: 265486.73 | S58: =IF(ISBLANK(R58)," ",ROUND(R58*(IF(ISBLANK(Q58),(M58/1000),(Q58/1000))),2)) | T58: =IF(IF(COUNTIF(H$2:$H58,H58)=1,1,"")=1,SUMIF($H$2:$H$7997,H58,$S$2:$S$7997),"") -> 0 | V58: Show Only Net; NONE | W58: 0 | X58: 0 | Y58: 0 | Z58: 0 | AA58: 1 | AB58: 0 | AC58: 0 | AD58: 0 | AE58: Bill on Contract - Pro-rated | AF58: 265486.73 | AG58: 1 | AH58: 1000000 | AI58: Zillow 2026 MWC Digital Plan | AJ58: 260564 | AK58: P2+ | AL58: 1 | AN58: Dylan Giordano | AO58: Guaranteed | AP58: DIO - SOC - FOX Sports - Facebook/Instagram - MWC | AQ58: 109945 | AR58: 46203 | AS58: 46082 | AT58: 46225 | AU58: Social Facebook/Instagram | AW58: 46208.537
A59: CANVAS WORLDWIDE | B59: 11499 | C59: 889 | D59: ZILLOW.COM | E59: Zillow 2026 MWC Digital Plan | F59: 260564 | G59: Zillow - DIO - SOC - FS - MWC - Social Package | H59: 558520 | I59: Zillow - DIO - SOC - FOX Sports - TikTok - MWC | J59: 558524 | K59: FOX Sports - TikTok | L59: Flat Rate | M59: 1000000 | N59: Bill on Contract | O59: 0 | P59: 265486.73 | S59: =IF(ISBLANK(R59)," ",ROUND(R59*(IF(ISBLANK(Q59),(M59/1000),(Q59/1000))),2)) | T59: =IF(IF(COUNTIF(H$2:$H59,H59)=1,1,"")=1,SUMIF($H$2:$H$7997,H59,$S$2:$S$7997),"") | W59: 0 | X59: 0 | Y59: 0 | Z59: 0 | AA59: 1 | AB59: 0 | AC59: 0 | AD59: 0 | AE59: Bill on Contract - Pro-rated | AF59: 265486.73 | AG59: 1 | AH59: 1000000 | AI59: Zillow 2026 MWC Digital Plan | AJ59: 260564 | AK59: P2+ | AL59: 1 | AN59: Dylan Giordano | AO59: Guaranteed | AP59: DIO - SOC - FOX Sports - TikTok - MWC | AQ59: 109945 | AR59: 46203 | AS59: 46082 | AT59: 46225 | AU59: Social TikTok | AW59: 46208.537
A60: CANVAS WORLDWIDE | B60: 11499 | C60: 889 | D60: ZILLOW.COM | E60: Zillow 2026 MWC Digital Plan | F60: 260564 | G60: Zillow - DIO - SOC - FS - MWC - Social Package | H60: 558520 | I60: Zillow - DIO - SOC - FOX Sports - X - MWC | J60: 558522 | K60: FOX Sports - Twitter | L60: Flat Rate | M60: 1000000 | N60: Bill on Contract | O60: 0 | P60: 265486.73 | S60: =IF(ISBLANK(R60)," ",ROUND(R60*(IF(ISBLANK(Q60),(M60/1000),(Q60/1000))),2)) | T60: =IF(IF(COUNTIF(H$2:$H60,H60)=1,1,"")=1,SUMIF($H$2:$H$7997,H60,$S$2:$S$7997),"") | W60: 0 | X60: 0 | Y60: 0 | Z60: 0 | AA60: 1 | AB60: 0 | AC60: 0 | AD60: 0 | AE60: Bill on Contract - Pro-rated | AF60: 265486.73 | AG60: 1 | AH60: 1000000 | AI60: Zillow 2026 MWC Digital Plan | AJ60: 260564 | AK60: P2+ | AL60: 1 | AN60: Dylan Giordano | AO60: Guaranteed | AP60: DIO - SOC - FOX Sports - X - MWC | AQ60: 109945 | AR60: 46203 | AS60: 46082 | AT60: 46225 | AU60: Social X | AW60: 46208.537
A61: CANVAS WORLDWIDE | B61: 11499 | C61: 889 | D61: ZILLOW.COM | E61: Zillow 2026 MWC Digital Plan | F61: 260564 | G61: Zillow - DIO - SOC - FS - MWC - Social Package | H61: 558520 | I61: Zillow - DIO - SOC - FOX Sports - Youtube - Custom Content - MWC | J61: 558523 | K61: FOX Sports | L61: Flat Rate | M61: 1000000 | N61: Bill on Contract | O61: 0 | P61: 265486.73 | S61: =IF(ISBLANK(R61)," ",ROUND(R61*(IF(ISBLANK(Q61),(M61/1000),(Q61/1000))),2)) | T61: =IF(IF(COUNTIF(H$2:$H61,H61)=1,1,"")=1,SUMIF($H$2:$H$7997,H61,$S$2:$S$7997),"") | W61: 0 | X61: 0 | Y61: 0 | Z61: 0 | AA61: 1 | AB61: 0 | AC61: 0 | AD61: 0 | AE61: Bill on Contract - Pro-rated | AF61: 265486.73 | AG61: 1 | AH61: 1000000 | AI61: Zillow 2026 MWC Digital Plan | AJ61: 260564 | AK61: P2+ | AL61: 1 | AN61: Dylan Giordano | AO61: Guaranteed | AP61: DIO - SOC - FOX Sports - Youtube - Custom Content - MWC | AQ61: 109945 | AR61: 46203 | AS61: 46082 | AT61: 46225 | AU61: Social | AW61: 46208.537
A62: CARAT - NY | B62: 10993 | C62: 8984 | D62: GENERAL MOTORS | E62: GM/Digital/Upfront/MG/AllFox/2Q26/Makegood | F62: 271227 | G62: GM- Cadillac - Run of AllFOX Video - AAT - 2Q26 Makegood | H62: 593675 | I62: GM - Cadillac - DIO - ROV - 1F - SEN - Pre/Mid - ROS - DT/MB/CTV - AAT - 2Q26 MG - SXD | J62: 94781419 | K62: OneFOX | L62: CPM | M62: 17.35 | N62: 3P Audience Target | O62: 811249 | P62: 0 | S62: =IF(ISBLANK(R62)," ",ROUND(R62*(IF(ISBLANK(Q62),(M62/1000),(Q62/1000))),2)) | T62: =IF(IF(COUNTIF(H$2:$H62,H62)=1,1,"")=1,SUMIF($H$2:$H$7997,H62,$S$2:$S$7997),"") -> 0 | W62: 811249 | X62: 811249 | Y62: 0 | Z62: 0 | AA62: 1 | AB62: 0 | AC62: 0 | AD62: 0 | AE62: Bill on Actuals - 3rd Party Performance | AF62: 0 | AG62: 3370816 | AH62: 0 | AI62: GM/Digital/Upfront/MG/AllFox/2Q26/Makegood | AJ62: 94777313 | AK62: Audience Target | AL62: O-D324VR0 | AN62: Allison Klein | AO62: Guaranteed | AP62: DIO - ROV - 1F - SEN - Pre/Mid - ROS - DT/MB/CTV - SXD | AQ62: 131313 | AR62: 46203 | AS62: 46188 | AT62: 46222 | AU62: Direct ROV | AW62: 46208.537
A63: CARAT - NY | B63: 10993 | C63: 5032 | D63: MICROSOFT | E63: Microsoft/Digital/Scatter/Sports/1QUD/2Q'26 | F63: 267640 | G63: Microsoft - Run of FOX Sports Video - Package - 2Q26 | H63: 584536 | I63: Microsoft - DIO - ROV - FS - Pre/Mid - ROS - DT/MB/CTV - 1Q PMP UD - 2Q26 | J63: 93472729 | K63: FOX Sports | L63: CPM | M63: 21.5 | N63: 3P CoView Imps | O63: 466856 | P63: 10037.4 | S63: =IF(ISBLANK(R63)," ",ROUND(R63*(IF(ISBLANK(Q63),(M63/1000),(Q63/1000))),2)) | T63: =IF(IF(COUNTIF(H$2:$H63,H63)=1,1,"")=1,SUMIF($H$2:$H$7997,H63,$S$2:$S$7997),"") -> 0 | W63: 244806 | X63: 399097 | Y63: 286369 | Z63: 466856 | AA63: 1 | AB63: 1.1697816 | AC63: 0 | AD63: 0 | AE63: Bill on Actuals - 3rd Party Performance | AF63: 3604.4 | AG63: 1234432 | AH63: 26540.29 | AI63: Microsoft/Digital/Scatter/Sports/1QUD/2Q'26 | AJ63: 93472719 | AK63: P2+ | AL63: O-D2RRUDA-R0 | AN63: Mike Maresca | AO63: Guaranteed | AP63: DIO - ROV - FS - Pre/Mid - ROS - DT/MB/CTV | AQ63: 126158 | AR63: 46203 | AS63: 46132 | AT63: 46203 | AU63: Direct ROV | AW63: 46208.537
A64: CARAT - NY | B64: 10993 | C64: 5032 | D64: MICROSOFT | E64: Microsoft/Digital/Scatter/World Cup/25-26 | F64: 270359 | G64: Microsoft - Run of World Cup Video - Package | H64: 591380 | I64: Microsoft - DIO - LFV - TUB - Pre/Mid - MWC - DT/MB/CTV | J64: 94461204 | K64: Fox Sold Tubi | L64: CPM | M64: 44 | N64: 3P Imps | O64: 2453680 | P64: 105000.02 | S64: =IF(ISBLANK(R64)," ",ROUND(R64*(IF(ISBLANK(Q64),(M64/1000),(Q64/1000))),2)) | T64: =IF(IF(COUNTIF(H$2:$H64,H64)=1,1,"")=1,SUMIF($H$2:$H$7997,H64,$S$2:$S$7997),"") -> 0 | W64: 2453680 | X64: 2453680 | Y64: 0 | Z64: 0 | AA64: 1 | AB64: 0 | AC64: 0 | AD64: 0 | AE64: Bill on Actuals - 3rd Party Performance | AF64: 52500.01 | AG64: 2386364 | AH64: 105000.02 | AI64: Microsoft/Digital/Scatter/World Cup/25-26 | AJ64: 94461190 | AK64: P2+ | AL64: O-D30TP6Q | AN64: Mike Maresca | AO64: Guaranteed | AP64: DIO - LFV - TUB - Pre/Mid - MWC - DT/MB/CTV | AQ64: 130320 | AR64: 46203 | AS64: 46178 | AT64: 46203 | AU64: Direct LFV | AW64: 46208.537
A65: CARAT - NY | B65: 10993 | C65: 5032 | D65: MICROSOFT | E65: Microsoft/Digital/Scatter/World Cup/25-26 | F65: 270359 | G65: Microsoft - Run of World Cup Video - Package | H65: 591380 | I65: Microsoft - DIO - ROV - FS - Pre/Mid - MWC - DT/MB/CTV | J65: 94461193 | K65: FOX Sports | L65: CPM | M65: 44 | N65: 3P Imps | O65: 1052146 | P65: 44999.99 | S65: =IF(ISBLANK(R65)," ",ROUND(R65*(IF(ISBLANK(Q65),(M65/1000),(Q65/1000))),2)) | T65: =IF(IF(COUNTIF(H$2:$H65,H65)=1,1,"")=1,SUMIF($H$2:$H$7997,H65,$S$2:$S$7997),"") | W65: 1052146 | X65: 1052146 | Y65: 0 | Z65: 0 | AA65: 1 | AB65: 0 | AC65: 0 | AD65: 0 | AE65: Bill on Actuals - 3rd Party Performance | AF65: 22500 | AG65: 1022727 | AH65: 44999.99 | AI65: Microsoft/Digital/Scatter/World Cup/25-26 | AJ65: 94461190 | AK65: P2+ | AL65: O-D30TP6Q | AN65: Mike Maresca | AO65: Guaranteed | AP65: DIO - ROV - FS - Pre/Mid - MWC - DT/MB/CTV | AQ65: 130320 | AR65: 46203 | AS65: 46178 | AT65: 46203 | AU65: Direct ROV | AW65: 46208.537
A66: CARAT - NY | B66: 10993 | C66: 5032 | D66: MICROSOFT | E66: Microsoft/Digital/Scatter/World Cup/25-26 | F66: 270359 | G66: Microsoft - Run of AllFOX Video - Package - AAT 'Soccer Fan' | H66: 591381 | I66: Microsoft - DIO - LFV - 1F - Tubi - Pre/Mid - ROS - DT/MB/CTV - FW - SXD - AAT 'Soccer Fan' | J66: 94461197 | K66: Fox Sold Tubi | L66: CPM | M66: 20 | N66: 3P Audience Target | O66: 2316225 | P66: 45000 | S66: =IF(ISBLANK(R66)," ",ROUND(R66*(IF(ISBLANK(Q66),(M66/1000),(Q66/1000))),2)) | T66: =IF(IF(COUNTIF(H$2:$H66,H66)=1,1,"")=1,SUMIF($H$2:$H$7997,H66,$S$2:$S$7997),"") -> 0 | W66: 2316225 | X66: 2316225 | Y66: 0 | Z66: 0 | AA66: 1 | AB66: 0 | AC66: 0 | AD66: 0 | AE66: Bill on Actuals - 3rd Party Performance | AF66: 22500 | AG66: 2250000 | AH66: 45000 | AI66: Microsoft/Digital/Scatter/World Cup/25-26 | AJ66: 94461190 | AK66: Audience Target | AL66: O-D30TP6Q | AN66: Mike Maresca | AO66: Guaranteed | AP66: DIO - LFV - 1F - Tubi - Pre/Mid - ROS - DT/MB/CTV - FW - SXD | AQ66: 130320 | AR66: 46203 | AS66: 46178 | AT66: 46203 | AU66: Direct LFV | AW66: 46208.537
A67: CARAT - NY | B67: 10993 | C67: 5032 | D67: MICROSOFT | E67: Microsoft/Digital/Scatter/World Cup/25-26 | F67: 270359 | G67: Microsoft - Run of AllFOX Video - Package - AAT 'Soccer Fan' | H67: 591381 | I67: Microsoft - DIO - ROV - 1F - SEN - Pre/Mid - ROS - DT/MB/CTV - SXD - AAT 'Soccer Fan' | J67: 94461200 | K67: OneFOX | L67: CPM | M67: 20 | N67: 3P Audience Target | O67: 5378876 | P67: 105000 | S67: =IF(ISBLANK(R67)," ",ROUND(R67*(IF(ISBLANK(Q67),(M67/1000),(Q67/1000))),2)) | T67: =IF(IF(COUNTIF(H$2:$H67,H67)=1,1,"")=1,SUMIF($H$2:$H$7997,H67,$S$2:$S$7997),"") | W67: 5378876 | X67: 5378876 | Y67: 0 | Z67: 0 | AA67: 1 | AB67: 0 | AC67: 0 | AD67: 0 | AE67: Bill on Actuals - 3rd Party Performance | AF67: 52500 | AG67: 5250000 | AH67: 105000 | AI67: Microsoft/Digital/Scatter/World Cup/25-26 | AJ67: 94461190 | AK67: Audience Target | AL67: O-D30TP6Q | AN67: Mike Maresca | AO67: Guaranteed | AP67: DIO - ROV - 1F - SEN - Pre/Mid - ROS - DT/MB/CTV - SXD | AQ67: 130320 | AR67: 46203 | AS67: 46178 | AT67: 46203 | AU67: Direct ROV | AW67: 46208.537
A68: COMFLUENCE LLC | B68: 20269 | C68: 9975 | D68: AMAZON XCM | E68: Amazon XCM/Digital/Direct/Upfront/Entertainment/25-26/UPFTRES | F68: 250528 | G68: Amazon XCM - LFV - RON Entertainment - ROS - Pre/Mid - DT/MB/CTV/VOD - A1849 AAT - Package - 3Q'26 UPFTRES | H68: 538245 | I68: Amazon XCM - LFV - RON Entertainment - ROS - Pre/Mid - DT/MB/CTV/STB - A1849 AAT - 3Q'26 UPFTRES | J68: 88560497 | K68: RON - Ent | L68: CPM | M68: 19 | N68: 3P Audience Target | O68: 0 | P68: 0 | S68: =IF(ISBLANK(R68)," ",ROUND(R68*(IF(ISBLANK(Q68),(M68/1000),(Q68/1000))),2)) | T68: =IF(IF(COUNTIF(H$2:$H68,H68)=1,1,"")=1,SUMIF($H$2:$H$7997,H68,$S$2:$S$7997),"") -> 0 | W68: 0 | X68: 0 | Y68: 0 | Z68: 0 | AA68: 1 | AB68: 0 | AC68: 0 | AD68: 0 | AE68: Bill on Actuals - 3rd Party Performance | AF68: 0 | AG68: 39470842 | AH68: 749946 | AI68: Amazon XCM/Digital/Direct/Upfront/Entertainment/25-26/UPFTRES | AJ68: 250528 | AK68: Audience Target | AL68: UPFTRES2526 | AN68: Matthew DiToro | AO68: Guaranteed | AP68: LFV - RON Ent - Pre/Mid - ROS - DT/MB/CTV/STB | AQ68: 95194 | AR68: 46203 | AS68: 46202 | AT68: 46292 | AU68: Direct LFV | AW68: 46208.537
A69: COMFLUENCE LLC | B69: 20269 | C69: 9975 | D69: AMAZON XCM | E69: Amazon XCM/Digital/Direct/Upfront/Sports/25-26/UPFTRES | F69: 253612 | G69: Amazon XCM - LFV - FSLS - Pre/Mid - ROS - DT/MB/CTV - P2+ - 3Q'26 UPFTRES | H69: 539342 | I69: Amazon XCM - LFV - FSLS - Pre/Mid - ROS - DT/MB/CTV - P2+ - 3Q'26 UPFTRES | J69: 90749646 | K69: FOX Sports Streaming | L69: CPM | M69: 22.65 | N69: 3P CoView Imps | O69: 0 | P69: 0 | S69: =IF(ISBLANK(R69)," ",ROUND(R69*(IF(ISBLANK(Q69),(M69/1000),(Q69/1000))),2)) | T69: =IF(IF(COUNTIF(H$2:$H69,H69)=1,1,"")=1,SUMIF($H$2:$H$7997,H69,$S$2:$S$7997),"") -> 0 | W69: 0 | X69: 0 | Y69: 0 | Z69: 0 | AA69: 1 | AB69: 0 | AC69: 0 | AD69: 0 | AE69: Bill on Actuals - 3rd Party Performance | AF69: 0 | AG69: 9683047 | AH69: 219321.01 | AI69: Amazon XCM/Digital/Direct/Upfront/Sports/25-26/UPFTRES | AJ69: 253612 | AK69: P2+ | AL69: UPFTRES2526 | AN69: Nicole Gamache | AO69: Guaranteed | AP69: LFV - FSLS - Pre/Mid - ROS - DT/MB/CTV | AQ69: 96038 | AR69: 46203 | AS69: 46202 | AT69: 46292 | AU69: Direct LFV | AW69: 46208.537
A70: CONNECT AT PUBLICIS MEDIA | B70: 10788 | C70: 3025 | D70: KEURIG DR PEPPER | E70: KDP/DIGITAL/UPFRONT 2025/2026/SPORTS/FLEX FUND/1Q'26-2Q'26 | F70: 260800 | G70: KDP - FLEX FUND - ROV - FS - Pre/Mid - ROS - DT/MB/CTV - P2+ - 2Q'26 Package | H70: 559447 | I70: KDP - FLEX FUND - P2+ - DIO - SFV - FSEN - Pre - ROS - DT/MB/CTV - non-CoV - 2Q'26 June | J70: 95039608 | K70: FSEN | L70: CPM | M70: 21.79 | N70: 3P Imps | O70: 343633 | P70: 7487.76 | S70: =IF(ISBLANK(R70)," ",ROUND(R70*(IF(ISBLANK(Q70),(M70/1000),(Q70/1000))),2)) | T70: =IF(IF(COUNTIF(H$2:$H70,H70)=1,1,"")=1,SUMIF($H$2:$H$7997,H70,$S$2:$S$7997),"") -> 0 | W70: 343633 | X70: 343633 | Y70: 0 | Z70: 0 | AA70: 1 | AB70: 0 | AC70: 0 | AD70: 0 | AE70: Bill on Actuals - 3rd Party Performance | AF70: 1862.92 | AG70: 344196 | AH70: 7500.03 | AI70: KDP/DIGITAL/UPFRONT 2025/2026/SPORTS/FLEX FUND/1Q'26-2Q'26 | AJ70: 90689056 | AK70: P2+ | AL70: O-D2H1JLS-R1 | AN70: Janna Goldstein | AO70: Guaranteed | AP70: DIO - SFV - FSEN - Pre - ROS - DT/MB/CTV - non-CoV | AQ70: 111730 | AR70: 46203 | AS70: 46111 | AT70: 46201 | AU70: Direct SFV | AW70: 46208.537
A71: CONNECT AT PUBLICIS MEDIA | B71: 10788 | C71: 3025 | D71: KEURIG DR PEPPER | E71: KDP/DIGITAL/UPFRONT 2025/2026/SPORTS/FLEX FUND/1Q'26-2Q'26 | F71: 260800 | G71: KDP - FLEX FUND - ROV - FS - Pre/Mid - ROS - DT/MB/CTV - P2+ - 2Q'26 Package | H71: 559447 | I71: KDP - FLEX FUND - P2+ - ROV - FS - Pre/Mid - ROS - DT/MB/CTV - 2Q'26 - June | J71: 93501078 | K71: FOX Sports | L71: CPM | M71: 21.79 | N71: 3P CoView Imps | O71: 108269 | P71: 1942.14 | S71: =IF(ISBLANK(R71)," ",ROUND(R71*(IF(ISBLANK(Q71),(M71/1000),(Q71/1000))),2)) | T71: =IF(IF(COUNTIF(H$2:$H71,H71)=1,1,"")=1,SUMIF($H$2:$H$7997,H71,$S$2:$S$7997),"") | V71: Show Only Net; NONE | W71: 90288 | X71: 90288 | Y71: 108269 | Z71: 108269 | AA71: 1 | AB71: 1.1991612 | AC71: 0 | AD71: 0 | AE71: Bill on Actuals - 3rd Party Performance | AF71: 482.4 | AG71: 89130 | AH71: 1942.14 | AI71: KDP/DIGITAL/UPFRONT 2025/2026/SPORTS/FLEX FUND/1Q'26-2Q'26 | AJ71: 90689056 | AK71: P2+ | AL71: O-D2H1JLS-R1 | AN71: Janna Goldstein | AO71: Guaranteed | AP71: ROV - FS - Pre/Mid - ROS - DT/MB/CTV | AQ71: 111730 | AR71: 46203 | AS71: 46111 | AT71: 46201 | AU71: Direct ROV | AW71: 46208.537
A72: CONNECT AT PUBLICIS MEDIA | B72: 10788 | C72: 8800 | D72: MILLERCOORS | E72: Coors Light/Digital/Scatter/Men's World Cup/Q2-Q3'26 | F72: 259315 | G72: Coors Light - World Cup Social Sponsorship Content - Package - X | H72: 582132 | I72: Coors Light - DIO - SOC - FOX Sports - X - MWC | J72: 582134 | K72: FOX Sports - Twitter | L72: Flat Rate | M72: 250000 | N72: Bill on Contract | O72: 0 | P72: 64102.56 | S72: =IF(ISBLANK(R72)," ",ROUND(R72*(IF(ISBLANK(Q72),(M72/1000),(Q72/1000))),2)) | T72: =IF(IF(COUNTIF(H$2:$H72,H72)=1,1,"")=1,SUMIF($H$2:$H$7997,H72,$S$2:$S$7997),"") -> 0 | W72: 0 | X72: 0 | Y72: 0 | Z72: 0 | AA72: 1 | AB72: 0 | AC72: 0 | AD72: 0 | AE72: Bill on Contract - Pro-rated | AF72: 64102.56 | AG72: 1 | AH72: 250000 | AI72: Coors Light/Digital/Scatter/Men's World Cup/Q2-Q3'26 | AJ72: 259315 | AK72: P2+ | AL72: O-D2UC9I1 | AN72: Matt Frey | AO72: Guaranteed | AP72: DIO - SOC - FOX Sports - X - MWC | AQ72: 129350 | AR72: 46203 | AS72: 46184 | AT72: 46222 | AU72: Social X | AW72: 46208.537
A73: CONNECT AT PUBLICIS MEDIA | B73: 10788 | C73: 8800 | D73: MILLERCOORS | E73: Coors Light/Digital/Scatter/Men's World Cup/Q2-Q3'26 | F73: 259315 | G73: Coors Light - Run of World Cup Video - Package | H73: 582142 | I73: Coors Light - DIO - LFV - TUB - Pre/Mid - MWC - DT/MB/CTV | J73: 94268018 | K73: Fox Sold Tubi | L73: CPM | M73: 40 | N73: 3P Imps | O73: 4064074 | P73: 162562.96 | S73: =IF(ISBLANK(R73)," ",ROUND(R73*(IF(ISBLANK(Q73),(M73/1000),(Q73/1000))),2)) | T73: =IF(IF(COUNTIF(H$2:$H73,H73)=1,1,"")=1,SUMIF($H$2:$H$7997,H73,$S$2:$S$7997),"") -> 0 | W73: 4064074 | X73: 4064074 | Y73: 0 | Z73: 0 | AA73: 1 | AB73: 0 | AC73: 0 | AD73: 0 | AE73: Bill on Actuals - 3rd Party Performance | AF73: 81983.87 | AG73: 6125000 | AH73: 245000 | AI73: Coors Light/Digital/Scatter/Men's World Cup/Q2-Q3'26 | AJ73: 94268011 | AK73: P2+ | AL73: O-D2UC9I1 | AN73: Matt Frey | AO73: Guaranteed | AP73: DIO - LFV - TUB - Pre/Mid - MWC - DT/MB/CTV | AQ73: 129350 | AR73: 46203 | AS73: 46174 | AT73: 46222 | AU73: Direct LFV | AW73: 46208.537
A74: CONNECT AT PUBLICIS MEDIA | B74: 10788 | C74: 8800 | D74: MILLERCOORS | E74: Coors Light/Digital/Scatter/Men's World Cup/Q2-Q3'26 | F74: 259315 | G74: Coors Light - Run of World Cup Video - Package | H74: 582142 | I74: Coors Light - DIO - ROV - FS - Pre/Mid - MWC - DT/MB/CTV | J74: 94268014 | K74: FOX Sports | L74: CPM | M74: 40 | N74: 3P Imps | O74: 1780679 | P74: 71227.16 | S74: =IF(ISBLANK(R74)," ",ROUND(R74*(IF(ISBLANK(Q74),(M74/1000),(Q74/1000))),2)) | T74: =IF(IF(COUNTIF(H$2:$H74,H74)=1,1,"")=1,SUMIF($H$2:$H$7997,H74,$S$2:$S$7997),"") | W74: 1780679 | X74: 1780679 | Y74: 0 | Z74: 0 | AA74: 1 | AB74: 0 | AC74: 0 | AD74: 0 | AE74: Bill on Actuals - 3rd Party Performance | AF74: 35135.95 | AG74: 2625000 | AH74: 105000 | AI74: Coors Light/Digital/Scatter/Men's World Cup/Q2-Q3'26 | AJ74: 94268011 | AK74: P2+ | AL74: O-D2UC9I1 | AN74: Matt Frey | AO74: Guaranteed | AP74: DIO - ROV - FS - Pre/Mid - MWC - DT/MB/CTV | AQ74: 129350 | AR74: 46203 | AS74: 46174 | AT74: 46222 | AU74: Direct ROV | AW74: 46208.537
A75: CONNECT AT PUBLICIS MEDIA | B75: 10788 | C75: 8800 | D75: MILLERCOORS | E75: Miller Coors/Digital/Scatter/Men's World Cup/Q2-Q3'26 | F75: 269662 | G75: Miller Lite - World Cup Social Sponsorship Content - Package - X | H75: 588871 | I75: Miller Lite - DIO - SOC - FOX Sports - X - MWC | J75: 588872 | K75: FOX Sports - Twitter | L75: Flat Rate | M75: 250000 | N75: Bill on Contract | O75: 0 | P75: 64102.56 | S75: =IF(ISBLANK(R75)," ",ROUND(R75*(IF(ISBLANK(Q75),(M75/1000),(Q75/1000))),2)) | T75: =IF(IF(COUNTIF(H$2:$H75,H75)=1,1,"")=1,SUMIF($H$2:$H$7997,H75,$S$2:$S$7997),"") -> 0 | W75: 0 | X75: 0 | Y75: 0 | Z75: 0 | AA75: 1 | AB75: 0 | AC75: 0 | AD75: 0 | AE75: Bill on Contract - Pro-rated | AF75: 64102.56 | AG75: 1 | AH75: 250000 | AI75: Miller Coors/Digital/Scatter/Men's World Cup/Q2-Q3'26 | AJ75: 269662 | AK75: P2+ | AL75: O-D2UC9I1 | AN75: Matt Frey | AO75: Guaranteed | AP75: DIO - SOC - FOX Sports - X - MWC | AQ75: 129388 | AR75: 46203 | AS75: 46184 | AT75: 46222 | AU75: Social X | AW75: 46208.537
A76: CONNECT AT PUBLICIS MEDIA | B76: 10788 | C76: 8800 | D76: MILLERCOORS | E76: Miller Coors/Digital/Scatter/Men's World Cup/Q2-Q3'26 | F76: 269662 | G76: Miller Lite - Run of World Cup Video - Package | H76: 588876 | I76: Miller Lite - DIO - ROV - FS - Pre/Mid - MWC - DT/MB/CTV | J76: 94269070 | K76: FOX Sports | L76: CPM | M76: 40 | N76: 3P Imps | O76: 765347 | P76: 30613.88 | S76: =IF(ISBLANK(R76)," ",ROUND(R76*(IF(ISBLANK(Q76),(M76/1000),(Q76/1000))),2)) | T76: =IF(IF(COUNTIF(H$2:$H76,H76)=1,1,"")=1,SUMIF($H$2:$H$7997,H76,$S$2:$S$7997),"") -> 0 | W76: 765347 | X76: 765347 | Y76: 0 | Z76: 0 | AA76: 1 | AB76: 0 | AC76: 0 | AD76: 0 | AE76: Bill on Actuals - 3rd Party Performance | AF76: 15094.37 | AG76: 1125000 | AH76: 45000 | AI76: Miller Coors/Digital/Scatter/Men's World Cup/Q2-Q3'26 | AJ76: 94269064 | AK76: P2+ | AL76: O-D2UC9I1 | AN76: Matt Frey | AO76: Guaranteed | AP76: DIO - ROV - FS - Pre/Mid - MWC - DT/MB/CTV | AQ76: 129388 | AR76: 46203 | AS76: 46174 | AT76: 46222 | AU76: Direct ROV | AW76: 46208.537
A77: CONNECT AT PUBLICIS MEDIA | B77: 10788 | C77: 8800 | D77: MILLERCOORS | E77: Miller Coors/Digital/Scatter/Men's World Cup/Q2-Q3'26 | F77: 269662 | G77: Miller Lite - Run of World Cup Video - Package | H77: 588876 | I77: Miller Lite - LFV - TUB - Pre/Mid - MWC - DT/MB/CTV | J77: 94269067 | K77: Fox Sold Tubi | L77: CPM | M77: 40 | N77: 3P Imps | O77: 1743195 | P77: 69727.8 | S77: =IF(ISBLANK(R77)," ",ROUND(R77*(IF(ISBLANK(Q77),(M77/1000),(Q77/1000))),2)) | T77: =IF(IF(COUNTIF(H$2:$H77,H77)=1,1,"")=1,SUMIF($H$2:$H$7997,H77,$S$2:$S$7997),"") | W77: 1743195 | X77: 1743195 | Y77: 0 | Z77: 0 | AA77: 1 | AB77: 0 | AC77: 0 | AD77: 0 | AE77: Bill on Actuals - 3rd Party Performance | AF77: 35220.19 | AG77: 2625000 | AH77: 105000 | AI77: Miller Coors/Digital/Scatter/Men's World Cup/Q2-Q3'26 | AJ77: 94269064 | AK77: P2+ | AL77: O-D2UC9I1 | AN77: Matt Frey | AO77: Guaranteed | AP77: DIO - LFV - TUB - Pre/Mid - MWC - DT/MB/CTV | AQ77: 129388 | AR77: 46203 | AS77: 46174 | AT77: 46222 | AU77: Direct LFV | AW77: 46208.537
A78: CONNECT AT PUBLICIS MEDIA | B78: 10788 | C78: 7080 | D78: SIGNET | E78: Signet Kay/25-26/Digital/Upfront/Entertainment/UF 2025/26/2Q | F78: 265809 | G78: Signet Kay DIO - LFV - Entertainment ROS - Package Bridal 2Q | H78: 576868 | I78: Signet Kay LFV - RON Ent - Pre/Mid - ROS - DT/MB/CTV/STB Bridal June 2Q | J78: 92878662 | K78: RON - Ent | L78: CPM | M78: 17 | N78: 3P CoView Imps | O78: 296071 | P78: 4842.35 | S78: =IF(ISBLANK(R78)," ",ROUND(R78*(IF(ISBLANK(Q78),(M78/1000),(Q78/1000))),2)) | T78: =IF(IF(COUNTIF(H$2:$H78,H78)=1,1,"")=1,SUMIF($H$2:$H$7997,H78,$S$2:$S$7997),"") -> 0 | V78: Show Only Net; NONE | W78: 234331 | X78: 234331 | Y78: 296071 | Z78: 296071 | AA78: 1 | AB78: 1.2634759 | AC78: 0 | AD78: 0 | AE78: Bill on Actuals - 3rd Party Performance | AF78: 4809.06 | AG78: 284844 | AH78: 4842.35 | AI78: Signet Kay/25-26/Digital/Upfront/Entertainment/UF 2025/26/2Q | AJ78: 92878643 | AK78: P2+ | AL78: O-D2OO844 | AN78: Carly Sartwell | AO78: Guaranteed | AP78: LFV - RON Ent - Pre/Mid - ROS - DT/MB/CTV/STB | AQ78: 122614 | AR78: 46203 | AS78: 46113 | AT78: 46203 | AU78: Direct LFV | AW78: 46208.537
A79: CONNECT AT PUBLICIS MEDIA | B79: 10788 | C79: 7080 | D79: SIGNET | E79: Signet Kay/25-26/Digital/Upfront/Entertainment/UF 2025/26/2Q | F79: 265809 | G79: Signet Kay DIO - LFV - Entertainment ROS - Package Gifting 2Q | H79: 576879 | I79: Signet Kay LFV - RON Ent - Pre/Mid - ROS - DT/MB/CTV/STB Gifting June 2Q | J79: 92878649 | K79: RON - Ent | L79: CPM | M79: 17 | N79: 3P CoView Imps | O79: 448130 | P79: 7263.51 | S79: =IF(ISBLANK(R79)," ",ROUND(R79*(IF(ISBLANK(Q79),(M79/1000),(Q79/1000))),2)) | T79: =IF(IF(COUNTIF(H$2:$H79,H79)=1,1,"")=1,SUMIF($H$2:$H$7997,H79,$S$2:$S$7997),"") -> 0 | W79: 353305 | X79: 353305 | Y79: 448130 | Z79: 448130 | AA79: 1 | AB79: 1.2683961 | AC79: 0 | AD79: 0 | AE79: Bill on Actuals - 3rd Party Performance | AF79: 7263.51 | AG79: 427265 | AH79: 7263.51 | AI79: Signet Kay/25-26/Digital/Upfront/Entertainment/UF 2025/26/2Q | AJ79: 92878643 | AK79: P2+ | AL79: O-D2OO844 | AN79: Carly Sartwell | AO79: Guaranteed | AP79: LFV - RON Ent - Pre/Mid - ROS - DT/MB/CTV/STB | AQ79: 122614 | AR79: 46203 | AS79: 46113 | AT79: 46203 | AU79: Direct LFV | AW79: 46208.537
A80: CRITICAL MASS | B80: 18610 | C80: 1665 | D80: BMW | E80: BMW / SCATTER / DIGITAL / SPORTS / FY Q4 25-26 / World Cup | F80: 266966 | G80: BMW - Run of World Cup Display - Men's World Cup 26' - 300x250, 320x50, 728x90 | H80: 581635 | I80: BMW - DIS - FS - Display Unit - MWC - 300x250, 320x50, 728x90 | J80: 7310447455 | K80: FOX Sports | L80: CPM | M80: 6 | N80: 3P Imps | O80: 0 | P80: 0 | S80: =IF(ISBLANK(R80)," ",ROUND(R80*(IF(ISBLANK(Q80),(M80/1000),(Q80/1000))),2)) | T80: =IF(IF(COUNTIF(H$2:$H80,H80)=1,1,"")=1,SUMIF($H$2:$H$7997,H80,$S$2:$S$7997),"") -> 0 | W80: 0 | X80: 0 | Y80: 0 | Z80: 0 | AA80: 1 | AB80: 0 | AC80: 0 | AD80: 0 | AE80: Bill on Actuals - 3rd Party Performance | AF80: 14047.12 | AG80: 13333333 | AH80: 80000 | AI80: BMW / SCATTER / DIGITAL / SPORTS / FY Q4 25-26 / World Cup | AJ80: 266966 | AK80: P2+ | AL80: O-D2TS2G5-R6 | AN80: Adam Chardavoyne | AO80: Guaranteed | AP80: DIS - FS - Display Unit - MWC | AQ80: 128177 | AR80: 46203 | AS80: 46184 | AT80: 46222 | AU80: Direct Display | AW80: 46208.537
A81: CRITICAL MASS | B81: 18610 | C81: 1665 | D81: BMW | E81: BMW / SCATTER / DIGITAL / SPORTS / FY Q4 25-26 / World Cup | F81: 266966 | G81: BMW - World Cup Social Sponsorship Content - Men's World Cup | H81: 581649 | I81: BMW - DIO - SOC - FOX Sports - Facebook/Instagram - MWC | J81: 581650 | K81: FOX Sports - FB-Inst | L81: Flat Rate | M81: 0.15 | N81: Bill on Contract | O81: 341880267 | P81: 51282.04 | S81: =IF(ISBLANK(R81)," ",ROUND(R81*(IF(ISBLANK(Q81),(M81/1000),(Q81/1000))),2)) | T81: =IF(IF(COUNTIF(H$2:$H81,H81)=1,1,"")=1,SUMIF($H$2:$H$7997,H81,$S$2:$S$7997),"") -> 0 | W81: 0 | X81: 0 | Y81: 0 | Z81: 0 | AA81: 1 | AB81: 0 | AC81: 0 | AD81: 0 | AE81: Bill on Contract - Pro-rated | AF81: 51282.04 | AG81: 1333333 | AH81: 199999.95 | AI81: BMW / SCATTER / DIGITAL / SPORTS / FY Q4 25-26 / World Cup | AJ81: 266966 | AK81: P2+ | AL81: O-D2TS2G5-R6 | AN81: Adam Chardavoyne | AO81: Guaranteed | AP81: DIO - SOC - FOX Sports - Facebook/Instagram - MWC | AQ81: 128177 | AR81: 46203 | AS81: 46184 | AT81: 46222 | AU81: Social Facebook/Instagram | AW81: 46208.537
A82: CRITICAL MASS | B82: 18610 | C82: 1665 | D82: BMW | E82: BMW / SCATTER / DIGITAL / SPORTS / FY Q4 25-26 / World Cup | F82: 266966 | G82: BMW - World Cup Social Sponsorship Content - Men's World Cup | H82: 581649 | I82: BMW - DIO - SOC - FOX Sports - TikTok - MWC | J82: 581653 | K82: FOX Sports - TikTok | L82: Flat Rate | M82: 0.15 | N82: Bill on Contract | O82: 341880533 | P82: 51282.08 | S82: =IF(ISBLANK(R82)," ",ROUND(R82*(IF(ISBLANK(Q82),(M82/1000),(Q82/1000))),2)) | T82: =IF(IF(COUNTIF(H$2:$H82,H82)=1,1,"")=1,SUMIF($H$2:$H$7997,H82,$S$2:$S$7997),"") | W82: 0 | X82: 0 | Y82: 0 | Z82: 0 | AA82: 1 | AB82: 0 | AC82: 0 | AD82: 0 | AE82: Bill on Contract - Pro-rated | AF82: 51282.08 | AG82: 1333334 | AH82: 200000.1 | AI82: BMW / SCATTER / DIGITAL / SPORTS / FY Q4 25-26 / World Cup | AJ82: 266966 | AK82: P2+ | AL82: O-D2TS2G5-R6 | AN82: Adam Chardavoyne | AO82: Guaranteed | AP82: DIO - SOC - FOX Sports - TikTok - MWC | AQ82: 128177 | AR82: 46203 | AS82: 46184 | AT82: 46222 | AU82: Social TikTok | AW82: 46208.537
A83: CRITICAL MASS | B83: 18610 | C83: 1665 | D83: BMW | E83: BMW / SCATTER / DIGITAL / SPORTS / FY Q4 25-26 / World Cup | F83: 266966 | G83: BMW - World Cup Social Sponsorship Content - Men's World Cup | H83: 581649 | I83: BMW - DIO - SOC - FOX Sports - Youtube - Custom Content - MWC | J83: 581652 | K83: FOX Sports | L83: Flat Rate | M83: 0.15 | N83: Bill on Contract | O83: 341880267 | P83: 51282.04 | S83: =IF(ISBLANK(R83)," ",ROUND(R83*(IF(ISBLANK(Q83),(M83/1000),(Q83/1000))),2)) | T83: =IF(IF(COUNTIF(H$2:$H83,H83)=1,1,"")=1,SUMIF($H$2:$H$7997,H83,$S$2:$S$7997),"") | W83: 0 | X83: 0 | Y83: 0 | Z83: 0 | AA83: 1 | AB83: 0 | AC83: 0 | AD83: 0 | AE83: Bill on Contract - Pro-rated | AF83: 51282.04 | AG83: 1333333 | AH83: 199999.95 | AI83: BMW / SCATTER / DIGITAL / SPORTS / FY Q4 25-26 / World Cup | AJ83: 266966 | AK83: P2+ | AL83: O-D2TS2G5-R6 | AN83: Adam Chardavoyne | AO83: Guaranteed | AP83: DIO - SOC - FOX Sports - Youtube - Custom Content - MWC | AQ83: 128177 | AR83: 46203 | AS83: 46184 | AT83: 46222 | AU83: Social | AW83: 46208.537
A84: CRITICAL MASS | B84: 18610 | C84: 1665 | D84: BMW | E84: BMW / SCATTER / DIGITAL / SPORTS / FY Q4 25-26 / World Cup | F84: 266966 | G84: BMW - World Cup FOX Sports Site & App Takeover - Non - OMP 6/20/2026 | H84: 587742 | I84: BMW - DIS - FS - Blank - ROS - Sponsorship - Non - OMP 6/20/2026 | J84: 7307921013 | K84: FOX Sports | L84: Flat Rate | M84: 0 | N84: Bill on Contract | O84: 0 | P84: 0 | S84: =IF(ISBLANK(R84)," ",ROUND(R84*(IF(ISBLANK(Q84),(M84/1000),(Q84/1000))),2)) | T84: =IF(IF(COUNTIF(H$2:$H84,H84)=1,1,"")=1,SUMIF($H$2:$H$7997,H84,$S$2:$S$7997),"") -> 0 | W84: 0 | X84: 0 | Y84: 0 | Z84: 0 | AA84: 1 | AB84: 0 | AC84: 0 | AD84: 0 | AE84: Bill on Contract - Pro-rated | AF84: 0 | AG84: 1 | AH84: 0 | AI84: BMW / SCATTER / DIGITAL / SPORTS / FY Q4 25-26 / World Cup | AJ84: 266966 | AK84: P2+ | AL84: O-D2TS2G5-R6 | AN84: Adam Chardavoyne | AO84: Guaranteed | AP84: DIS - FS - Blank - ROS - Sponsorship | AQ84: 128177 | AR84: 46203 | AS84: 46193 | AT84: 46193 | AU84: Direct Display | AW84: 46208.537
A85: CRITICAL MASS | B85: 18610 | C85: 1665 | D85: BMW | E85: BMW / SCATTER / DIGITAL / SPORTS / FY Q4 25-26 / World Cup | F85: 266966 | G85: BMW - World Cup FOX Sports Site & App Takeover - Non - OMP 6/20/2026 | H85: 587742 | I85: BMW - DIS - FS - Display Unit - ROS - Sponsorship - 300 x 250 - 6/20/2026 | J85: 7307919777 | K85: FOX Sports | L85: Flat Rate | M85: 50000 | N85: Bill on Contract | O85: 500 | P85: 25000 | S85: =IF(ISBLANK(R85)," ",ROUND(R85*(IF(ISBLANK(Q85),(M85/1000),(Q85/1000))),2)) | T85: =IF(IF(COUNTIF(H$2:$H85,H85)=1,1,"")=1,SUMIF($H$2:$H$7997,H85,$S$2:$S$7997),"") | W85: 0 | X85: 0 | Y85: 0 | Z85: 0 | AA85: 1 | AB85: 0 | AC85: 0 | AD85: 0 | AE85: Bill on Contract - Pro-rated | AF85: 25000 | AG85: 1 | AH85: 50000 | AI85: BMW / SCATTER / DIGITAL / SPORTS / FY Q4 25-26 / World Cup | AJ85: 266966 | AK85: P2+ | AL85: O-D2TS2G5-R6 | AN85: Adam Chardavoyne | AO85: Guaranteed | AP85: DIS - FS - Display Unit - ROS - Sponsorship | AQ85: 128177 | AR85: 46203 | AS85: 46193 | AT85: 46193 | AU85: Direct Display | AW85: 46208.537
A86: CRITICAL MASS | B86: 18610 | C86: 1665 | D86: BMW | E86: BMW / SCATTER / DIGITAL / SPORTS / FY Q4 25-26 / World Cup | F86: 266966 | G86: BMW - World Cup FOX Sports Site & App Takeover - Non - OMP 6/20/2026 | H86: 587742 | I86: BMW - DIS - FS - Display Unit - ROS - Sponsorship - 300 x 600 - 6/20/2026 | J86: 7312079423 | K86: FOX Sports | L86: Flat Rate | M86: 50000 | N86: Bill on Contract | O86: 500 | P86: 25000 | S86: =IF(ISBLANK(R86)," ",ROUND(R86*(IF(ISBLANK(Q86),(M86/1000),(Q86/1000))),2)) | T86: =IF(IF(COUNTIF(H$2:$H86,H86)=1,1,"")=1,SUMIF($H$2:$H$7997,H86,$S$2:$S$7997),"") | W86: 0 | X86: 0 | Y86: 0 | Z86: 0 | AA86: 1 | AB86: 0 | AC86: 0 | AD86: 0 | AE86: Bill on Contract - Pro-rated | AF86: 25000 | AG86: 1 | AH86: 50000 | AI86: BMW / SCATTER / DIGITAL / SPORTS / FY Q4 25-26 / World Cup | AJ86: 266966 | AK86: P2+ | AL86: O-D2TS2G5-R6 | AN86: Adam Chardavoyne | AO86: Guaranteed | AP86: DIS - FS - Display Unit - ROS - Sponsorship | AQ86: 128177 | AR86: 46203 | AS86: 46193 | AT86: 46193 | AU86: Direct Display | AW86: 46208.537
A87: CRITICAL MASS | B87: 18610 | C87: 1665 | D87: BMW | E87: BMW / SCATTER / DIGITAL / SPORTS / FY Q4 25-26 / World Cup | F87: 266966 | G87: BMW - World Cup FOX Sports Site & App Takeover - Non - OMP 6/20/2026 | H87: 587742 | I87: BMW - DIS - FS - Display Unit - ROS - Sponsorship - 320 x 50 - 6/20/2026 | J87: 7307919765 | K87: FOX Sports | L87: Flat Rate | M87: 50000 | N87: Bill on Contract | O87: 500 | P87: 25000 | S87: =IF(ISBLANK(R87)," ",ROUND(R87*(IF(ISBLANK(Q87),(M87/1000),(Q87/1000))),2)) | T87: =IF(IF(COUNTIF(H$2:$H87,H87)=1,1,"")=1,SUMIF($H$2:$H$7997,H87,$S$2:$S$7997),"") | W87: 0 | X87: 0 | Y87: 0 | Z87: 0 | AA87: 1 | AB87: 0 | AC87: 0 | AD87: 0 | AE87: Bill on Contract - Pro-rated | AF87: 25000 | AG87: 1 | AH87: 50000 | AI87: BMW / SCATTER / DIGITAL / SPORTS / FY Q4 25-26 / World Cup | AJ87: 266966 | AK87: P2+ | AL87: O-D2TS2G5-R6 | AN87: Adam Chardavoyne | AO87: Guaranteed | AP87: DIS - FS - Display Unit - ROS - Sponsorship | AQ87: 128177 | AR87: 46203 | AS87: 46193 | AT87: 46193 | AU87: Direct Display | AW87: 46208.537
A88: CRITICAL MASS | B88: 18610 | C88: 1665 | D88: BMW | E88: BMW / SCATTER / DIGITAL / SPORTS / FY Q4 25-26 / World Cup | F88: 266966 | G88: BMW - World Cup FOX Sports Site & App Takeover - Non - OMP 6/20/2026 | H88: 587742 | I88: BMW - DIS - FS - Display Unit - ROS - Sponsorship - 728 x 90 - 6/20/2026 | J88: 7307920440 | K88: FOX Sports | L88: Flat Rate | M88: 50000 | N88: Bill on Contract | O88: 500 | P88: 25000 | S88: =IF(ISBLANK(R88)," ",ROUND(R88*(IF(ISBLANK(Q88),(M88/1000),(Q88/1000))),2)) | T88: =IF(IF(COUNTIF(H$2:$H88,H88)=1,1,"")=1,SUMIF($H$2:$H$7997,H88,$S$2:$S$7997),"") | W88: 0 | X88: 0 | Y88: 0 | Z88: 0 | AA88: 1 | AB88: 0 | AC88: 0 | AD88: 0 | AE88: Bill on Contract - Pro-rated | AF88: 25000 | AG88: 1 | AH88: 50000 | AI88: BMW / SCATTER / DIGITAL / SPORTS / FY Q4 25-26 / World Cup | AJ88: 266966 | AK88: P2+ | AL88: O-D2TS2G5-R6 | AN88: Adam Chardavoyne | AO88: Guaranteed | AP88: DIS - FS - Display Unit - ROS - Sponsorship | AQ88: 128177 | AR88: 46203 | AS88: 46193 | AT88: 46193 | AU88: Direct Display | AW88: 46208.537
A89: CRITICAL MASS | B89: 18610 | C89: 1665 | D89: BMW | E89: BMW / SCATTER / DIGITAL / SPORTS / FY Q4 25-26 / World Cup | F89: 266966 | G89: BMW - World Cup FOX Sports Site & App Takeover - Non - OMP 6/20/2026 | H89: 587742 | I89: BMW - DIS - FS - High Impact - ROS - Sponsorship - Non - OMP 6/20/2026 | J89: 7307912787 | K89: FOX Sports | L89: Flat Rate | M89: 50000 | N89: Bill on Contract | O89: 500 | P89: 25000 | S89: =IF(ISBLANK(R89)," ",ROUND(R89*(IF(ISBLANK(Q89),(M89/1000),(Q89/1000))),2)) | T89: =IF(IF(COUNTIF(H$2:$H89,H89)=1,1,"")=1,SUMIF($H$2:$H$7997,H89,$S$2:$S$7997),"") | W89: 0 | X89: 0 | Y89: 0 | Z89: 0 | AA89: 1 | AB89: 0 | AC89: 0 | AD89: 0 | AE89: Bill on Contract - Pro-rated | AF89: 25000 | AG89: 1 | AH89: 50000 | AI89: BMW / SCATTER / DIGITAL / SPORTS / FY Q4 25-26 / World Cup | AJ89: 266966 | AK89: P2+ | AL89: O-D2TS2G5-R6 | AN89: Adam Chardavoyne | AO89: Guaranteed | AP89: DIS - FS - High Impact - ROS - Sponsorship | AQ89: 128177 | AR89: 46203 | AS89: 46193 | AT89: 46193 | AU89: Direct Display | AW89: 46208.537
A90: DENTSU INC | B90: 11515 | C90: 4694 | D90: HILTON HOTELS | E90: Hilton/Digital/Upfront/Streaming/25-26 -3Q26 | F90: 272050 | G90: Hilton - DIO - ROV - FS - Pre/Mid - ROS - DT/MB/CTV - Package - 3Q26 | H90: 595758 | I90: Hilton - DIO - ROV - FS - Pre/Mid - ROS - DT/MB/CTV - 3Q26 | J90: 95091062 | K90: FOX Sports | L90: CPM | M90: 20 | N90: 3P CoView Imps | O90: 1418 | P90: 28.36 | S90: =IF(ISBLANK(R90)," ",ROUND(R90*(IF(ISBLANK(Q90),(M90/1000),(Q90/1000))),2)) | T90: =IF(IF(COUNTIF(H$2:$H90,H90)=1,1,"")=1,SUMIF($H$2:$H$7997,H90,$S$2:$S$7997),"") -> 0 | W90: 1192 | X90: 1192 | Y90: 1418 | Z90: 1418 | AA90: 1 | AB90: 1.1899999 | AC90: 0 | AD90: 0 | AE90: Bill on Actuals - 3rd Party Performance | AF90: 14.17 | AG90: 5000000 | AH90: 100000 | AI90: Hilton/Digital/Upfront/Streaming/25-26 -3Q26 | AJ90: 95091055 | AK90: P2+ | AL90: O-D33NEM8 | AN90: Mike Maresca | AO90: Guaranteed | AP90: DIO - ROV - FS - Pre/Mid - ROS - DT/MB/CTV | AQ90: 133681 | AR90: 46203 | AS90: 46202 | AT90: 46292 | AU90: Direct ROV | AW90: 46208.537
... A92: DENTSU INC | B92: 11515 | C92: 4694 | D92: HILTON HOTELS | E92: Hilton/Digital/Upfront/Streaming/25-26/DIO/2Q'26 | F92: 264956 | G92: Hilton - DIO - ROV - FS - Pre/Mid - ROS - DT/MB/CTV - Package | H92: 573888 | I92: Hilton - DIO - SFV - FSEN - Pre - ROS - DT/MB/CTV - non-CoV - 2Q26 | J92: 94909490 | K92: FSEN | L92: Flat Rate | M92: 20 | N92: Bill on Contract | O92: 418342 | P92: 8366.83 | S92: =IF(ISBLANK(R92)," ",ROUND(R92*(IF(ISBLANK(Q92),(M92/1000),(Q92/1000))),2)) | T92: =IF(IF(COUNTIF(H$2:$H92,H92)=1,1,"")=1,SUMIF($H$2:$H$7997,H92,$S$2:$S$7997),"") | W92: 1950158 | X92: 1950158 | Y92: 0 | Z92: 0 | AA92: 1 | AB92: 0 | AC92: 0 | AD92: 0 | AE92: Bill on Contract - Straightline | AF92: 8366.83 | AG92: 1897860 | AH92: 37957.2 | AI92: Hilton/Digital/Upfront/Streaming/25-26/DIO/2Q'26 | AJ92: 92909732 | AK92: P2+ | AL92: O-D2O8AIT-R1 | AN92: Mike Maresca | AO92: Guaranteed | AP92: DIO - SFV - FSEN - Pre - ROS - DT/MB/CTV - non-CoV | AQ92: 121426 | AR92: 46203 | AS92: 46112 | AT92: 46201 | AU92: Direct SFV | AW92: 46208.537
A93: DIGITAS - NY | B93: 11691 | C93: 5988 | D93: EXACT SCIENCES | E93: Cologuard/Digital/Upfront/ONE FOX/UF 2025.26/Direct/2Q26 | F93: 264810 | G93: Cologuard - OneFox - 25/26 - Pre/Mid - ROS - AAT - SXD - A45+ - 2Q'26 | H93: 573336 | I93: Cologuard - DIO - ROV - 1F - SEN - Pre/Mid - ROS - DT/MB/CTV - SXD - 2Q'26 - A45+ | J93: 92911180 | K93: OneFOX | L93: CPM | M93: 17.46 | N93: 3P Audience Target | O93: 2564410 | P93: 44774.6 | S93: =IF(ISBLANK(R93)," ",ROUND(R93*(IF(ISBLANK(Q93),(M93/1000),(Q93/1000))),2)) | T93: =IF(IF(COUNTIF(H$2:$H93,H93)=1,1,"")=1,SUMIF($H$2:$H$7997,H93,$S$2:$S$7997),"") -> 0 | V93: Show Only Net; NONE | W93: 1803031 | X93: 2564410 | Y93: 0 | Z93: 0 | AA93: 1 | AB93: 0 | AC93: 0 | AD93: 0 | AE93: Bill on Actuals - 3rd Party Performance | AF93: 29198.32 | AG93: 7159221 | AH93: 125000 | AI93: Cologuard/Digital/Upfront/ONE FOX/UF 2025.26/Direct/2Q26 | AJ93: 92911177 | AK93: Audience Target | AL93: O-D2PJPKE-R2 | AN93: Jon Renz | AO93: Guaranteed | AP93: DIO - ROV - 1F - SEN - Pre/Mid - ROS - DT/MB/CTV - SXD | AQ93: 122756 | AR93: 46203 | AS93: 46113 | AT93: 46201 | AU93: Direct ROV | AW93: 46208.537
A94: ESSENCE GLOBAL LLC | B94: 11737 | C94: 5954 | D94: AIRBNB | E94: Airbnb/MWC/Digital/SCT/25-26 | F94: 257222 | G94: OMP - Airbnb - Run of World Cup Video - Package | H94: 583535 | I94: OMP - Airbnb - DIO - LFV - TUB - Pre/Mid - MWC - DT/MB/CTV | J94: 93796299 | K94: Fox Sold Tubi | L94: CPM | M94: 40 | N94: 3P Imps | O94: 4897238 | P94: 195889.52 | S94: =IF(ISBLANK(R94)," ",ROUND(R94*(IF(ISBLANK(Q94),(M94/1000),(Q94/1000))),2)) | T94: =IF(IF(COUNTIF(H$2:$H94,H94)=1,1,"")=1,SUMIF($H$2:$H$7997,H94,$S$2:$S$7997),"") -> 0 | W94: 4897238 | X94: 4897238 | Y94: 0 | Z94: 0 | AA94: 1 | AB94: 0 | AC94: 0 | AD94: 0 | AE94: Bill on Actuals - 3rd Party Performance | AF94: 99241.53 | AG94: 7437500 | AH94: 297500 | AI94: Airbnb/MWC/Digital/SCT/25-26 | AJ94: 93796293 | AK94: P2+ | AL94: O-D2TN2MQ-R1 | AN94: Nicole Joscelyn | AO94: Guaranteed | AP94: DIO - LFV - TUB - Pre/Mid - MWC - DT/MB/CTV | AQ94: 127516 | AR94: 46203 | AS94: 46184 | AT94: 46222 | AU94: Direct LFV | AW94: 46208.537
A95: ESSENCE GLOBAL LLC | B95: 11737 | C95: 5954 | D95: AIRBNB | E95: Airbnb/MWC/Digital/SCT/25-26 | F95: 257222 | G95: OMP - Airbnb - Run of World Cup Video - Package | H95: 583535 | I95: OMP - Airbnb - DIO - ROV - FS - Pre/Mid - MWC - DT/MB/CTV | J95: 93796296 | K95: FOX Sports | L95: CPM | M95: 40 | N95: 3P Imps | O95: 8877808 | P95: 355112.32 | S95: =IF(ISBLANK(R95)," ",ROUND(R95*(IF(ISBLANK(Q95),(M95/1000),(Q95/1000))),2)) | T95: =IF(IF(COUNTIF(H$2:$H95,H95)=1,1,"")=1,SUMIF($H$2:$H$7997,H95,$S$2:$S$7997),"") | W95: 8877808 | X95: 8877808 | Y95: 0 | Z95: 0 | AA95: 1 | AB95: 0 | AC95: 0 | AD95: 0 | AE95: Bill on Actuals - 3rd Party Performance | AF95: 175966.07 | AG95: 13187500 | AH95: 527500 | AI95: Airbnb/MWC/Digital/SCT/25-26 | AJ95: 93796293 | AK95: P2+ | AL95: O-D2TN2MQ-R1 | AN95: Nicole Joscelyn | AO95: Guaranteed | AP95: DIO - ROV - FS - Pre/Mid - MWC - DT/MB/CTV | AQ95: 127516 | AR95: 46203 | AS95: 46184 | AT95: 46222 | AU95: Direct ROV | AW95: 46208.537
A96: ESSENCE GLOBAL LLC | B96: 11737 | C96: 5954 | D96: AIRBNB | E96: Airbnb/MWC/Digital/SCT/25-26 | F96: 257222 | G96: OMP - Airbnb - Run of World Cup Display - Package | H96: 583538 | I96: OMP - Airbnb - DIS - FS - Display Unit - MWC -728x90/300x250/320x50 | J96: 7303325458 | K96: FOX Sports | L96: CPM | M96: 6 | N96: 3P Imps | O96: 0 | P96: 0 | S96: =IF(ISBLANK(R96)," ",ROUND(R96*(IF(ISBLANK(Q96),(M96/1000),(Q96/1000))),2)) | T96: =IF(IF(COUNTIF(H$2:$H96,H96)=1,1,"")=1,SUMIF($H$2:$H$7997,H96,$S$2:$S$7997),"") -> 0 | W96: 0 | X96: 0 | Y96: 0 | Z96: 0 | AA96: 1 | AB96: 0 | AC96: 0 | AD96: 0 | AE96: Bill on Actuals - 3rd Party Performance | AF96: 28405.97 | AG96: 16666667 | AH96: 100000 | AI96: Airbnb/MWC/Digital/SCT/25-26 | AJ96: 257222 | AK96: P2+ | AL96: O-D2TN2MQ-R1 | AN96: Nicole Joscelyn | AO96: Guaranteed | AP96: DIS - FS - Display Unit - MWC | AQ96: 127516 | AR96: 46203 | AS96: 46184 | AT96: 46222 | AU96: Direct Display | AW96: 46208.537
A97: ESSENCE GLOBAL LLC | B97: 11737 | C97: 5954 | D97: AIRBNB | E97: Airbnb/MWC/Digital/SCT/25-26 | F97: 257222 | G97: OMP - Airbnb - Run of FOX Sports Video - Package | H97: 583540 | I97: OMP - Airbnb - DIO - ROV - FS - Pre/Mid - ROS - DT/MB/CTV | J97: 93796302 | K97: FOX Sports | L97: CPM | M97: 20 | N97: 3P CoView Imps | O97: 3048999 | P97: 60979.98 | S97: =IF(ISBLANK(R97)," ",ROUND(R97*(IF(ISBLANK(Q97),(M97/1000),(Q97/1000))),2)) | T97: =IF(IF(COUNTIF(H$2:$H97,H97)=1,1,"")=1,SUMIF($H$2:$H$7997,H97,$S$2:$S$7997),"") -> 0 | W97: 2743851 | X97: 2743851 | Y97: 3048999 | Z97: 3048999 | AA97: 1 | AB97: 1.1112118 | AC97: 0 | AD97: 0 | AE97: Bill on Actuals - 3rd Party Performance | AF97: 19926.4 | AG97: 6541900 | AH97: 130838 | AI97: Airbnb/MWC/Digital/SCT/25-26 | AJ97: 93796293 | AK97: P2+ | AL97: O-D2TN2MQ-R1 | AN97: Nicole Joscelyn | AO97: Guaranteed | AP97: DIO - ROV - FS - Pre/Mid - ROS - DT/MB/CTV | AQ97: 127516 | AR97: 46203 | AS97: 46184 | AT97: 46222 | AU97: Direct ROV | AW97: 46208.537
A98: ESSENCE GLOBAL LLC | B98: 11737 | C98: 5954 | D98: AIRBNB | E98: Airbnb/MWC/Digital/SCT/25-26 | F98: 257222 | G98: OMP - Airbnb - Run of FOX Sports Video - Package | H98: 583540 | I98: OMP - Airbnb - DIO - SFV - FSEN - Pre - ROS - DT/MB/CTV - non-CoV | J98: 94961195 | K98: FSEN | L98: CPM | M98: 20 | N98: 3P Imps | O98: 1032574 | P98: 20651.48 | S98: =IF(ISBLANK(R98)," ",ROUND(R98*(IF(ISBLANK(Q98),(M98/1000),(Q98/1000))),2)) | T98: =IF(IF(COUNTIF(H$2:$H98,H98)=1,1,"")=1,SUMIF($H$2:$H$7997,H98,$S$2:$S$7997),"") | W98: 1032574 | X98: 1032574 | Y98: 0 | Z98: 0 | AA98: 1 | AB98: 0 | AC98: 0 | AD98: 0 | AE98: Bill on Actuals - 3rd Party Performance | AF98: 10533.25 | AG98: 3458100 | AH98: 69162 | AI98: Airbnb/MWC/Digital/SCT/25-26 | AJ98: 93796293 | AK98: P2+ | AL98: O-D2TN2MQ-R1 | AN98: Nicole Joscelyn | AO98: Guaranteed | AP98: DIO - SFV - FSEN - Pre - ROS - DT/MB/CTV - non-CoV | AQ98: 127516 | AR98: 46203 | AS98: 46184 | AT98: 46222 | AU98: Direct SFV | AW98: 46208.537
A99: ESSENCE GLOBAL LLC | B99: 11737 | C99: 8942 | D99: FOCUS FEATURES | E99: FocusFeatures/Digital/25-26/SCT | F99: 264794 | G99: FocusFeatures/Digital/Sports/Scatter/2Q'26/Pressure - EXTENDED | H99: 592162 | I99: FocusFeatures//Sports/Scatter/ROV - FSEN/2Q'26/Pressure - FSEN | J99: 94436556 | K99: FSEN | L99: CPM | M99: 25 | N99: 3P Imps | O99: 114384 | P99: 2795.23 | S99: =IF(ISBLANK(R99)," ",ROUND(R99*(IF(ISBLANK(Q99),(M99/1000),(Q99/1000))),2)) | T99: =IF(IF(COUNTIF(H$2:$H99,H99)=1,1,"")=1,SUMIF($H$2:$H$7997,H99,$S$2:$S$7997),"") -> 0 | W99: 114384 | X99: 114384 | Y99: 0 | Z99: 0 | AA99: 1 | AB99: 0.99224483 | AC99: 0 | AD99: 0 | AE99: Bill on Actuals - 3rd Party Performance | AF99: 1394.04 | AG99: 111809 | AH99: 2795.23 | AI99: FocusFeatures/Digital/25-26/SCT | AJ99: 93775179 | AK99: P2+ | AL99: O-D2TA0O2-R0 | AN99: Nicole Joscelyn | AO99: Guaranteed | AP99: DIO - SFV - FSEN - Pre - ROS - DT/MB/CTV - non-CoV | AQ99: 130141 | AR99: 46203 | AS99: 46176 | AT99: 46180 | AU99: Direct SFV | AW99: 46208.537
A100: ESSENCE GLOBAL LLC | B100: 11737 | C100: 8981 | D100: UNIVERSAL PICTURES | E100: Universal Pictures/Digital/Scatter/Sports/MWC 2026/Disclosure Day | F100: 261965 | G100: Universal- Run of World Cup Video - Package (Disclosure Day) | H100: 581358 | I100: Universal- DIO - LFV - TUB - Pre/Mid - MWC - DT/MB/CTV (Disclosure Day) | J100: 94399507 | K100: Fox Sold Tubi | L100: CPM | M100: 40 | N100: 3P Imps | O100: 425670 | P100: 15100 | S100: =IF(ISBLANK(R100)," ",ROUND(R100*(IF(ISBLANK(Q100),(M100/1000),(Q100/1000))),2)) | T100: =IF(IF(COUNTIF(H$2:$H100,H100)=1,1,"")=1,SUMIF($H$2:$H$7997,H100,$S$2:$S$7997),"") -> 0 | W100: 425670 | X100: 425670 | Y100: 0 | Z100: 0 | AA100: 1 | AB100: 0 | AC100: 0 | AD100: 0 | AE100: Bill on Actuals - 3rd Party Performance | AF100: 7548.84 | AG100: 377500 | AH100: 15100 | AI100: Universal Pictures/Digital/Scatter/Sports/MWC 2026/Disclosure Day | AJ100: 94399500 | AK100: P2+ | AL100: O-D302AVD-R2 | AN100: Gina Rodarte | AO100: Guaranteed | AP100: DIO - LFV - TUB - Pre/Mid - MWC - DT/MB/CTV | AQ100: 130009 | AR100: 46203 | AS100: 46184 | AT100: 46192 | AU100: Direct LFV | AW100: 46208.537
A101: ESSENCE GLOBAL LLC | B101: 11737 | C101: 8981 | D101: UNIVERSAL PICTURES | E101: Universal Pictures/Digital/Scatter/Sports/MWC 2026/Disclosure Day | F101: 261965 | G101: Universal- Run of World Cup Video - Package (Disclosure Day) | H101: 581358 | I101: Universal- DIO - ROV - FS - Pre/Mid - MWC - DT/MB/CTV (Disclosure Day) | J101: 94399524 | K101: FOX Sports | L101: CPM | M101: 40 | N101: 3P Imps | O101: 112967 | P101: 4518.68 | S101: =IF(ISBLANK(R101)," ",ROUND(R101*(IF(ISBLANK(Q101),(M101/1000),(Q101/1000))),2)) | T101: =IF(IF(COUNTIF(H$2:$H101,H101)=1,1,"")=1,SUMIF($H$2:$H$7997,H101,$S$2:$S$7997),"") | W101: 112967 | X101: 112967 | Y101: 0 | Z101: 0 | AA101: 1 | AB101: 0 | AC101: 0 | AD101: 0 | AE101: Bill on Actuals - 3rd Party Performance | AF101: 3235 | AG101: 161775 | AH101: 6471 | AI101: Universal Pictures/Digital/Scatter/Sports/MWC 2026/Disclosure Day | AJ101: 94399500 | AK101: P2+ | AL101: O-D302AVD-R2 | AN101: Gina Rodarte | AO101: Guaranteed | AP101: DIO - ROV - FS - Pre/Mid - MWC - DT/MB/CTV | AQ101: 130009 | AR101: 46203 | AS101: 46184 | AT101: 46192 | AU101: Direct ROV | AW101: 46208.537
A102: ESSENCE GLOBAL LLC | B102: 11737 | C102: 8981 | D102: UNIVERSAL PICTURES | E102: Universal Pictures/Digital/Scatter/Sports/MWC 2026/Forgotten Island | F102: 270643 | G102: Universal- Run of World Cup Video - Package (Forgotten Island) | H102: 592113 | I102: Universal- DIO - LFV - TUB - Pre/Mid - MWC - DT/MB/CTV (Forgotten Island) | J102: 94438329 | K102: Fox Sold Tubi | L102: CPM | M102: 40 | N102: 3P Imps | O102: 970130 | P102: 38805.2 | S102: =IF(ISBLANK(R102)," ",ROUND(R102*(IF(ISBLANK(Q102),(M102/1000),(Q102/1000))),2)) | T102: =IF(IF(COUNTIF(H$2:$H102,H102)=1,1,"")=1,SUMIF($H$2:$H$7997,H102,$S$2:$S$7997),"") -> 0 | W102: 970130 | X102: 970130 | Y102: 0 | Z102: 0 | AA102: 1 | AB102: 0 | AC102: 0 | AD102: 0 | AE102: Bill on Actuals - 3rd Party Performance | AF102: 19435.09 | AG102: 1949500 | AH102: 77980 | AI102: Universal Pictures/Digital/Scatter/Sports/MWC 2026/Forgotten Island | AJ102: 94438322 | AK102: P2+ | AL102: O-D302834-R3 | AN102: Gina Rodarte | AO102: Guaranteed | AP102: DIO - LFV - TUB - Pre/Mid - MWC - DT/MB/CTV | AQ102: 130239 | AR102: 46203 | AS102: 46200 | AT102: 46222 | AU102: Direct LFV | AW102: 46208.537
A103: ESSENCE GLOBAL LLC | B103: 11737 | C103: 8981 | D103: UNIVERSAL PICTURES | E103: Universal Pictures/Digital/Scatter/Sports/MWC 2026/Forgotten Island | F103: 270643 | G103: Universal- Run of World Cup Video - Package (Forgotten Island) | H103: 592113 | I103: Universal- DIO - ROV - FS - Pre/Mid - MWC - DT/MB/CTV (Forgotten Island) | J103: 94438325 | K103: FOX Sports | L103: CPM | M103: 40 | N103: 3P Imps | O103: 417923 | P103: 16716.92 | S103: =IF(ISBLANK(R103)," ",ROUND(R103*(IF(ISBLANK(Q103),(M103/1000),(Q103/1000))),2)) | T103: =IF(IF(COUNTIF(H$2:$H103,H103)=1,1,"")=1,SUMIF($H$2:$H$7997,H103,$S$2:$S$7997),"") | W103: 417923 | X103: 417923 | Y103: 0 | Z103: 0 | AA103: 1 | AB103: 0 | AC103: 0 | AD103: 0 | AE103: Bill on Actuals - 3rd Party Performance | AF103: 8329.33 | AG103: 835500 | AH103: 33420 | AI103: Universal Pictures/Digital/Scatter/Sports/MWC 2026/Forgotten Island | AJ103: 94438322 | AK103: P2+ | AL103: O-D302834-R3 | AN103: Gina Rodarte | AO103: Guaranteed | AP103: DIO - ROV - FS - Pre/Mid - MWC - DT/MB/CTV | AQ103: 130239 | AR103: 46203 | AS103: 46200 | AT103: 46222 | AU103: Direct ROV | AW103: 46208.537
A104: ESSENCE GLOBAL LLC | B104: 11737 | C104: 8981 | D104: UNIVERSAL PICTURES | E104: Universal Pictures/Digital/Scatter/Sports/MWC 2026/Monsters and Minions | F104: 270734 | G104: Universal- Run of World Cup Video - Package (Monsters and Minions) | H104: 592345 | I104: Universal- DIO - LFV - TUB - Pre/Mid - MWC - DT/MB/CTV (Monsters and Minions) | J104: 94483741 | K104: Fox Sold Tubi | L104: CPM | M104: 40 | N104: 3P Imps | O104: 1700168 | P104: 68006.72 | S104: =IF(ISBLANK(R104)," ",ROUND(R104*(IF(ISBLANK(Q104),(M104/1000),(Q104/1000))),2)) | T104: =IF(IF(COUNTIF(H$2:$H104,H104)=1,1,"")=1,SUMIF($H$2:$H$7997,H104,$S$2:$S$7997),"") -> 0 | W104: 1700168 | X104: 1700168 | Y104: 0 | Z104: 0 | AA104: 1 | AB104: 0 | AC104: 0 | AD104: 0 | AE104: Bill on Actuals - 3rd Party Performance | AF104: 34672.51 | AG104: 1788650 | AH104: 71546 | AI104: Universal Pictures/Digital/Scatter/Sports/MWC 2026/Monsters and Minions | AJ104: 94483738 | AK104: P2+ | AL104: O-D302386-R7 | AN104: Gina Rodarte | AO104: Guaranteed | AP104: DIO - LFV - TUB - Pre/Mid - MWC - DT/MB/CTV | AQ104: 130393 | AR104: 46203 | AS104: 46184 | AT104: 46207 | AU104: Direct LFV | AW104: 46208.537
A105: ESSENCE GLOBAL LLC | B105: 11737 | C105: 8981 | D105: UNIVERSAL PICTURES | E105: Universal Pictures/Digital/Scatter/Sports/MWC 2026/Monsters and Minions | F105: 270734 | G105: Universal- Run of World Cup Video - Package (Monsters and Minions) | H105: 592345 | I105: Universal- DIO - ROV - FS - Pre/Mid - MWC - DT/MB/CTV (Monsters and Minions) | J105: 94484068 | K105: FOX Sports | L105: CPM | M105: 40 | N105: 3P Imps | O105: 775286 | P105: 30663 | S105: =IF(ISBLANK(R105)," ",ROUND(R105*(IF(ISBLANK(Q105),(M105/1000),(Q105/1000))),2)) | T105: =IF(IF(COUNTIF(H$2:$H105,H105)=1,1,"")=1,SUMIF($H$2:$H$7997,H105,$S$2:$S$7997),"") | W105: 775286 | X105: 775286 | Y105: 0 | Z105: 0 | AA105: 1 | AB105: 0 | AC105: 0 | AD105: 0 | AE105: Bill on Actuals - 3rd Party Performance | AF105: 14859.85 | AG105: 766575 | AH105: 30663 | AI105: Universal Pictures/Digital/Scatter/Sports/MWC 2026/Monsters and Minions | AJ105: 94483738 | AK105: P2+ | AL105: O-D302386-R7 | AN105: Gina Rodarte | AO105: Guaranteed | AP105: DIO - ROV - FS - Pre/Mid - MWC - DT/MB/CTV | AQ105: 130393 | AR105: 46203 | AS105: 46184 | AT105: 46207 | AU105: Direct ROV | AW105: 46208.537
... A110: ESSENCE GLOBAL LLC | B110: 11737 | C110: 8981 | D110: UNIVERSAL PICTURES | E110: Universal Pictures/Digital/Scatter/Sports/MWC 2026/The Odyssey | F110: 270547 | G110: Universal- Run of World Cup Video - Package (The Odyssey) | H110: 591934 | I110: Universal- DIO - ROV - FS - Pre/Mid - MWC - DT/MB/CTV (The Odyssey) | J110: 94438093 | K110: FOX Sports | L110: CPM | M110: 40 | N110: 3P Imps | O110: 1497475 | P110: 59899 | S110: =IF(ISBLANK(R110)," ",ROUND(R110*(IF(ISBLANK(Q110),(M110/1000),(Q110/1000))),2)) | T110: =IF(IF(COUNTIF(H$2:$H110,H110)=1,1,"")=1,SUMIF($H$2:$H$7997,H110,$S$2:$S$7997),"") | W110: 1497475 | X110: 1497475 | Y110: 0 | Z110: 0 | AA110: 1 | AB110: 0 | AC110: 0 | AD110: 0 | AE110: Bill on Actuals - 3rd Party Performance | AF110: 32128.82 | AG110: 2181550 | AH110: 87262 | AI110: Universal Pictures/Digital/Scatter/Sports/MWC 2026/The Odyssey | AJ110: 94438060 | AK110: P2+ | AL110: O-D302867-R6 | AN110: Gina Rodarte | AO110: Guaranteed | AP110: DIO - ROV - FS - Pre/Mid - MWC - DT/MB/CTV | AQ110: 130243 | AR110: 46203 | AS110: 46184 | AT110: 46222 | AU110: Direct ROV | AW110: 46208.537
A111: ESSENCE GLOBAL LLC | B111: 11737 | C111: 8981 | D111: UNIVERSAL PICTURES | E111: Universal Pictures/Digital/Scatter/Sports/MWC 2026/The Odyssey | F111: 270547 | G111: Universal- DIO - SOC - FOX Sports - META VAP - MWC (The Odyssey) | H111: 594851 | I111: Universal- DIO - SOC - FOX Sports - META VAP - MWC (The Odyssey) | J111: 594851 | K111: FOX Sports - FB-Inst | L111: Flat Rate | M111: 0 | N111: 1P Imps | O111: 0 | P111: 0 | S111: =IF(ISBLANK(R111)," ",ROUND(R111*(IF(ISBLANK(Q111),(M111/1000),(Q111/1000))),2)) | T111: =IF(IF(COUNTIF(H$2:$H111,H111)=1,1,"")=1,SUMIF($H$2:$H$7997,H111,$S$2:$S$7997),"") -> 0 | W111: 0 | X111: 0 | Y111: 0 | Z111: 0 | AA111: 1 | AB111: 0 | AC111: 0 | AD111: 0 | AE111: Bill on Actuals - 3rd Party Performance | AF111: 0 | AG111: 0 | AH111: 0 | AI111: Universal Pictures/Digital/Scatter/Sports/MWC 2026/The Odyssey | AJ111: 270547 | AK111: P2+ | AL111: O-D302867-R6 | AN111: Gina Rodarte | AO111: Guaranteed | AP111: DIO - SOC - FOX Sports - META VAP - MWC | AR111: 46203 | AS111: 46203 | AT111: 46203 | AU111: Social Facebook/Instagram | AW111: 46208.537
A112: ESSENCE GLOBAL LLC | B112: 11737 | C112: 8981 | D112: UNIVERSAL PICTURES | E112: Universal Pictures/Digital/Scatter/Sports/MWC 2026/The Odyssey | F112: 270547 | G112: Universal- DIO - SOC - FOX Sports - META VAP - MWC (The Odyssey) | H112: 598428 | I112: Universal- DIO - SOC - FOX Sports - META VAP - MWC (The Odyssey) | J112: 598428 | K112: FOX Sports - FB-Inst | L112: CPM | M112: 30 | N112: 1P Imps | O112: 0 | P112: 0 | S112: =IF(ISBLANK(R112)," ",ROUND(R112*(IF(ISBLANK(Q112),(M112/1000),(Q112/1000))),2)) | T112: =IF(IF(COUNTIF(H$2:$H112,H112)=1,1,"")=1,SUMIF($H$2:$H$7997,H112,$S$2:$S$7997),"") -> 0 | W112: 0 | X112: 0 | Y112: 0 | Z112: 0 | AA112: 1 | AB112: 0 | AC112: 0 | AD112: 0 | AE112: Bill on Actuals - 3rd Party Performance | AF112: 0 | AG112: 3333334 | AH112: 100000.02 | AI112: Universal Pictures/Digital/Scatter/Sports/MWC 2026/The Odyssey | AJ112: 270547 | AK112: P2+ | AL112: O-D302867-R6 | AN112: Gina Rodarte | AO112: Guaranteed | AP112: DIO - SOC - FOX Sports - META VAP - MWC | AQ112: 130243 | AR112: 46203 | AS112: 46195 | AT112: 46222 | AU112: Social Facebook/Instagram | AW112: 46208.537
A113: ESSENCE GLOBAL LLC | B113: 11737 | C113: 8981 | D113: UNIVERSAL PICTURES | E113: UNIVERSAL PICTURES/Digital/Upfront/Entertainment/UF 2025/26 - Disclosure Day | F113: 269710 | G113: Disclosure Day- UP- DIO - LFV - Entertainment - Package - Sci-Fi/Thriller Fans or Moviegoers Showmix | H113: 589034 | I113: Disclosure Day- UP- DIO - LFV - RON Ent - Pre/Mid - DT/MB/CTV/STB - FOH - Sci-Fi/Thriller Fans or Moviegoers Showmix | J113: 94010279 | K113: RON - Ent | L113: CPM | M113: 19 | N113: 3P CoView Imps | O113: 1543719 | P113: 29330.66 | S113: =IF(ISBLANK(R113)," ",ROUND(R113*(IF(ISBLANK(Q113),(M113/1000),(Q113/1000))),2)) | T113: =IF(IF(COUNTIF(H$2:$H113,H113)=1,1,"")=1,SUMIF($H$2:$H$7997,H113,$S$2:$S$7997),"") -> 0 | W113: 492695 | X113: 1295567 | Y113: 587065 | Z113: 1543719 | AA113: 1 | AB113: 1.19154 | AC113: 0 | AD113: 0 | AE113: Bill on Actuals - 3rd Party Performance | AF113: 10651.52 | AG113: 2131579 | AH113: 40500 | AI113: UNIVERSAL PICTURES/Digital/Upfront/Entertainment/UF 2025/26 - Disclosure Day | AJ113: 94010107 | AK113: P2+ | AL113: O-D2L6GLR-R0 | AN113: Gina Rodarte | AO113: Guaranteed | AP113: DIO - LFV - RON Ent - Pre/Mid - ROS - DT/MB/CTV/STB | AQ113: 128406 | AR113: 46203 | AS113: 46160 | AT113: 46187 | AU113: Direct LFV | AW113: 46208.537
A114: ESSENCE GLOBAL LLC | B114: 11737 | C114: 8981 | D114: UNIVERSAL PICTURES | E114: UNIVERSAL PICTURES/Digital/Upfront/Entertainment/UF 2025/26 - Disclosure Day | F114: 269710 | G114: Disclosure Day- UP- DIO - LFV - Entertainment - Package - Sci-Fi/Thriller Fans or Moviegoers Showmix | H114: 589034 | I114: Disclosure Day- UP- DIO - LFV - RON Ent - Pre/Mid - DT/MB/CTV/STB - FOT - Sci-Fi/Thriller Fans or Moviegoers Showmix | J114: 94010269 | K114: RON - Ent | L114: CPM | M114: 19 | N114: 3P CoView Imps | O114: 190306 | P114: 3615.81 | S114: =IF(ISBLANK(R114)," ",ROUND(R114*(IF(ISBLANK(Q114),(M114/1000),(Q114/1000))),2)) | T114: =IF(IF(COUNTIF(H$2:$H114,H114)=1,1,"")=1,SUMIF($H$2:$H$7997,H114,$S$2:$S$7997),"") | W114: 60780 | X114: 153178 | Y114: 75512 | Z114: 190306 | AA114: 1 | AB114: 1.2423899 | AC114: 0 | AD114: 0 | AE114: Bill on Actuals - 3rd Party Performance | AF114: 1315 | AG114: 263158 | AH114: 5000 | AI114: UNIVERSAL PICTURES/Digital/Upfront/Entertainment/UF 2025/26 - Disclosure Day | AJ114: 94010107 | AK114: P2+ | AL114: O-D2L6GLR-R0 | AN114: Gina Rodarte | AO114: Guaranteed | AP114: DIO - LFV - RON Ent - Pre/Mid - ROS - DT/MB/CTV/STB | AQ114: 128406 | AR114: 46203 | AS114: 46160 | AT114: 46187 | AU114: Direct LFV | AW114: 46208.537
A115: ESSENCE GLOBAL LLC | B115: 11737 | C115: 8981 | D115: UNIVERSAL PICTURES | E115: UNIVERSAL PICTURES/Digital/Upfront/Entertainment/UF 2025/26 - Disclosure Day | F115: 269710 | G115: Disclosure Day- UP- DIO - LFV - Entertainment - Package - Sci-Fi/Thriller Fans or Moviegoers Showmix | H115: 589034 | I115: Disclosure Day- UP- DIO - LFV - RON Ent - Pre/Mid - DT/MB/CTV/STB - FOX - Sci-Fi/Thriller Fans or Moviegoers Showmix | J115: 94010113 | K115: RON - Ent | L115: CPM | M115: 19 | N115: 3P CoView Imps | O115: 61369 | P115: 1166.01 | S115: =IF(ISBLANK(R115)," ",ROUND(R115*(IF(ISBLANK(Q115),(M115/1000),(Q115/1000))),2)) | T115: =IF(IF(COUNTIF(H$2:$H115,H115)=1,1,"")=1,SUMIF($H$2:$H$7997,H115,$S$2:$S$7997),"") | V115: Show Only Net; NONE | W115: 33386 | X115: 47628 | Y115: 43018 | Z115: 61369 | AA115: 1 | AB115: 1.2885099 | AC115: 0 | AD115: 0 | AE115: Bill on Actuals - 3rd Party Performance | AF115: 526 | AG115: 105263 | AH115: 2000 | AI115: UNIVERSAL PICTURES/Digital/Upfront/Entertainment/UF 2025/26 - Disclosure Day | AJ115: 94010107 | AK115: P2+ | AL115: O-D2L6GLR-R0 | AN115: Gina Rodarte | AO115: Guaranteed | AP115: DIO - LFV - RON Ent - Pre/Mid - ROS - DT/MB/CTV/STB | AQ115: 128406 | AR115: 46203 | AS115: 46160 | AT115: 46187 | AU115: Direct LFV | AW115: 46208.537
A116: ESSENCE GLOBAL LLC | B116: 11737 | C116: 8981 | D116: UNIVERSAL PICTURES | E116: UNIVERSAL PICTURES/Digital/Upfront/Entertainment/UF 2025/26 - Disclosure Day | F116: 269710 | G116: Disclosure Day- UP- DIO - LFV - Entertainment - Package - Sci-Fi/Thriller Fans or Moviegoers Showmix | H116: 589034 | I116: Disclosure Day- UP- DIO - LFV - RON Ent - Pre/Mid - DT/MB/CTV/STB - FOX STB VOD - Sci-Fi/Thriller Fans or Moviegoers Showmix | J116: 94010276 | K116: RON - Ent | L116: CPM | M116: 19 | N116: 3P CoView Imps | O116: 80118 | P116: 1522.24 | S116: =IF(ISBLANK(R116)," ",ROUND(R116*(IF(ISBLANK(Q116),(M116/1000),(Q116/1000))),2)) | T116: =IF(IF(COUNTIF(H$2:$H116,H116)=1,1,"")=1,SUMIF($H$2:$H$7997,H116,$S$2:$S$7997),"") | W116: 45355 | X116: 66765 | Y116: 54426 | Z116: 80118 | AA116: 1 | AB116: 1.2000018 | AC116: 0 | AD116: 0 | AE116: Bill on Actuals - 3rd Party Performance | AF116: 657.5 | AG116: 131579 | AH116: 2500 | AI116: UNIVERSAL PICTURES/Digital/Upfront/Entertainment/UF 2025/26 - Disclosure Day | AJ116: 94010107 | AK116: P2+ | AL116: O-D2L6GLR-R0 | AN116: Gina Rodarte | AO116: Guaranteed | AP116: DIO - LFV - RON Ent - Pre/Mid - ROS - DT/MB/CTV/STB | AQ116: 128406 | AR116: 46203 | AS116: 46160 | AT116: 46187 | AU116: Direct LFV | AW116: 46208.537
A117: ESSENCE GLOBAL LLC | B117: 11737 | C117: 8981 | D117: UNIVERSAL PICTURES | E117: UNIVERSAL PICTURES/Digital/Upfront/Entertainment/UF 2025/26 - Minions 3 | F117: 267764 | G117: Minions & Monsters_UP_DIO - LFV - Entertainment - Package - Animation + Families w/ Children Showmix | H117: 584846 | I117: Minions & Monsters_UP_DIO - LFV - RON Ent - Pre/Mid - DT/MB/CTV/STB - FOH - Animation + Families w/ Children Showmix | J117: 93827526 | K117: RON - Ent | L117: CPM | M117: 19 | N117: 3P CoView Imps | O117: 1038545 | P117: 19732.35 | S117: =IF(ISBLANK(R117)," ",ROUND(R117*(IF(ISBLANK(Q117),(M117/1000),(Q117/1000))),2)) | T117: =IF(IF(COUNTIF(H$2:$H117,H117)=1,1,"")=1,SUMIF($H$2:$H$7997,H117,$S$2:$S$7997),"") -> 0 | W117: 973067 | X117: 973067 | Y117: 1038545 | Z117: 1038545 | AA117: 1 | AB117: 1.0672907 | AC117: 0 | AD117: 0 | AE117: Bill on Actuals - 3rd Party Performance | AF117: 26394.7 | AG117: 1705263 | AH117: 32400 | AI117: UNIVERSAL PICTURES/Digital/Upfront/Entertainment/UF 2025/26 - Minions 3 | AJ117: 93827506 | AK117: P2+ | AL117: O-D2SBLKA-R0 | AN117: Gina Rodarte | AO117: Guaranteed | AP117: DIO - LFV - RON Ent - Pre/Mid - ROS - DT/MB/CTV/STB | AQ117: 127605 | AR117: 46203 | AS117: 46188 | AT117: 46204 | AU117: Direct LFV | AW117: 46208.537
...

Sheet AOS Pivot
A3: Row Labels | B3: Sum of Net Invoice Amount
A4: 250383 | B4: 0
A5: 250390 | B5: 0
A6: 250528 | B6: 0
A7: 251184 | B7: 0
A8: 251751 | B8: 0
A9: 251886 | B9: 6741.12
A10: 252064 | B10: 0
A11: 252135 | B11: 0
A12: 252293 | B12: 0
A13: 252314 | B13: 0
A14: 252340 | B14: 30427.135
A15: 252528 | B15: 0
... A231: 272782 | B231: 0
A232: Grand Total | B232: 56204191

Sheet AOS Pre
A1: Agency MDM ID | B1: Primary Advertiser Name | C1: Advertiser MDM ID | D1: Deal Name | E1: Deal ID | F1: Package Name | G1: Package ID | H1: Line Item ID | I1: Line Item Name | J1: Line Item Start Date | K1: Line Item End Date | L1: Billable Third Party Server | M1: Line Item Cost Method | N1: Net Line Item Unit Cost | O1: Line Item Quantity | P1: Net Line Item Cost | Q1: Unit Type | R1: Invoice Schedule - Suggested Amount Terms | S1: Invoice Schedule - Suggested Invoice Units | T1: Invoice Schedule - Suggested Invoice Amount | U1: Actual Invoice Units Term Used | V1: Adjusted Invoice Units | W1: Actual Net Invoice Amount Term Source | X1: Adjusted Net Invoice Amount | Y1: Net Invoice Amount | Z1: Gross Invoice Amount | AA1: Primary Performance | AB1: Third Party Performance | AC1: Order Start Date | AD1: Order End Date | AE1: Account Manager | AF1: Invoice Status | AG1: Billing Period Name | AH1: Net Order Cost | AI1: Invoice ID | AJ1: Primary Salesperson
A2: AGC005226 | B2: AMAZON XCM | C2: ADV011498 | D2: Amazon XCM/Digital/Direct/Upfront/Entertainment/25-26/UPFTRES | E2: 250528 | F2: LFV - RON Ent - ROS - Pre/Mid - DT/MB/CTV/VOD - Package | G2: 3535 | H2: 538245 | I2: Amazon XCM - LFV - RON Entertainment - ROS - Pre/Mid - DT/MB/CTV/VOD - A1849 AAT - Package - 3Q'26 UPFTRES | J2: 46202 | K2: 46292 | L2: FOX DCM | M2: CPM | N2: 19 | O2: 39470842 | P2: 749946 | Q2: Impressions | R2: performance | S2: 0 | T2: 0 | U2: performance | V2: 0 | W2: invoice_schedule | X2: 0 | Y2: 0 | Z2: 0 | AC2: 46202 | AD2: 46292 | AE2: Erin Travers | AF2: None | AG2: JUN'26 | AH2: 749946 | AI2: 95194 | AJ2: Matthew DiToro
A3: AGC002601 | B3: WARNER BROS | C3: ADV006261 | D3: Warner Brothers/Digital/Direct/Upfront/Entertainment/25-26/UPFTRES | E3: 251184 | F3: LFV - RON Ent - ROS - Pre/Mid - DT/MB/CTV/VOD - Package | G3: 3535 | H3: 537460 | I3: CANCELLED - Warner Brothers - LFV - RON Entertainment - ROS - Pre/Mid - DT/MB/CTV/VOD - P2+ No CoV - Package - 2Q'26 UPFTRES | J3: 46149 | K3: 46201 | L3: FOX DCM | M3: CPM | N3: 0 | O3: 0 | P3: 0 | Q3: Impressions | R3: performance | S3: 0 | T3: 0 | U3: performance | V3: 0 | W3: invoice_schedule | X3: 0 | Y3: 0 | Z3: 0 | AC3: 46149 | AD3: 46201 | AE3: Kailey McGinn | AF3: None | AG3: JUN'26 | AH3: 0 | AI3: 101604 | AJ3: Matthew DiToro
A4: AGC001913 | B4: CONSTELLATION BRANDS | C4: ADV001091 | D4: Constellation/Modelo/25-26/Upfront/Digital/Sports/Streaming | E4: 251886 | F4: Generic Flighted Bottom Up Package | G4: 1 | H4: 534730 | I4: MODELO/UF/SPORTS/D/25-26/P2+/2Q'26 | J4: 46113 | K4: 46203 | M4: CPM | N4: 25 | O4: 4135880 | P4: 103397.01 | R4: performance | S4: 0 | T4: 0 | U4: performance | V4: 269644 | W4: invoice_schedule | X4: 6741.12 | Y4: 6741.12 | Z4: 6741.12 | AA4: 615694 | AB4: 0 | AC4: 46113 | AD4: 46203 | AE4: John Hertman | AF4: None | AG4: JUN'26 | AH4: 200000.03 | AI4: 96408 | AJ4: Colleen Cahill
A5: AGC002070 | B5: NATIONAL VISION INC | C5: ADV006329 | D5: National Vision/Digital/Upfront/ONEFOX/UF 2025/26 | E5: 252293 | F5: Generic Flighted Bottom Up Package | G5: 1 | H5: 537073 | I5: CANCELLED - National Vision - OneFOX - A25-54 - 3Q'26 Package - UPFT RES | J5: 46202 | K5: 46292 | L5: FOX DCM | M5: CPM | N5: 0 | O5: 0 | P5: 0 | Q5: Impressions | R5: performance | S5: 0 | T5: 0 | U5: performance | V5: 0 | W5: invoice_schedule | X5: 0 | Y5: 0 | Z5: 0 | AC5: 46202 | AD5: 46292 | AE5: Katie Johnson | AF5: None | AG5: JUN'26 | AH5: 0 | AI5: 95920 | AJ5: Tim Wodzisz
A6: AGC001318 | B6: KIA | C6: ADV004496 | D6: Kia/Digital/Upfront/Entertainment/UF 2025/26 - 1-3Q26 | E6: 252314 | F6: LFV - RON Ent - ROS - Pre/Mid - DT/MB/CTV/VOD - Package | G6: 3535 | H6: 537026 | I6: KIA - LFV - RON Ent - ROS - Pre/Mid - DT/MB/CTV/VOD - Package - 3Q'26 | J6: 46202 | K6: 46292 | L6: FOX DCM | M6: CPM | N6: 33.57 | O6: 7447126 | P6: 250000.02 | Q6: CoV Impressions | R6: performance | S6: 0 | T6: 0 | U6: performance | V6: 0 | W6: invoice_schedule | X6: 0 | Y6: 0 | Z6: 0 | AC6: 46202 | AD6: 46292 | AE6: Jessica Lang | AF6: None | AG6: JUN'26 | AH6: 830000.67 | AI6: 96341 | AJ6: Allison Klein
A7: AGC001035 | B7: AUDI | C7: ADV006306 | D7: Audi/Digital/Upfront/Sports/MLS/2026 | E7: 253348 | H7: 538224 | I7: Audi - LFV - FSLS - Pre - MLS - DT/MB/CTV - 100% SOV Sponsorship - 2026 | J7: 46074 | K7: 46387 | L7: FOX DCM | M7: SOV-Flat Rate | N7: 75000 | O7: 1 | P7: 75000 | Q7: n/a | R7: prorated | S7: 0 | T7: 7165.6051 | U7: prorated | V7: 0 | W7: invoice_schedule | X7: 6768.0042 | Y7: 6768.0042 | Z7: 6768.0042 | AC7: 46074 | AD7: 46387 | AE7: Kailey McGinn | AF7: None | AG7: JUN'26 | AH7: 85000.05 | AI7: 101619 | AJ7: Nicole Gamache
A8: AGC001035 | B8: AUDI | C8: ADV006306 | D8: Audi/Digital/Upfront/Sports/MLS/2026 | E8: 253348 | F8: Generic Flighted Bottom Up Package | G8: 1 | H8: 538226 | I8: Audi - LFV - ROV - FS - Pre/Mid - MLS/Soccer - DT/MB/TB/CTV - CoV - P2+ - Package - 2026 | J8: 46074 | K8: 46387 | L8: FOX DCM | M8: CPM | N8: 25.7 | O8: 389106 | P8: 10000.02 | Q8: CoV Impressions | R8: performance | S8: 0 | T8: 0 | U8: performance | V8: 16417 | W8: invoice_schedule | X8: 421.9169 | Y8: 421.9169 | Z8: 421.9169 | AA8: 17205 | AB8: 16417 | AC8: 46074 | AD8: 46387 | AE8: Kailey McGinn | AF8: None | AG8: JUN'26 | AH8: 85000.05 | AI8: 101619 | AJ8: Nicole Gamache
A9: AGC001249 | B9: US ARMY | C9: ADV000193 | D9: Army / UPFRONT / DIGITAL / SPORTS 2025/26 | E9: 254371 | F9: DIO - ROV - FS - Pre/Mid - ROS - DT/MB/CTV - Package | G9: 7968 | H9: 585268 | I9: ARMY - DIO - ROV - FS - Pre/Mid - ROS - DT/MB/CTV - 2Q'26 AAT A1849 | J9: 46136 | K9: 46201 | M9: CPM | N9: 27.97 | O9: 3166932 | P9: 88579.09 | Q9: Impressions | R9: performance | S9: 0 | T9: 0 | U9: performance | V9: 310672 | W9: invoice_schedule | X9: 8689.4958 | Y9: 8689.4958 | Z9: 8689.4958 | AA9: 327357 | AB9: 310672 | AC9: 46136 | AD9: 46201 | AE9: Anthony Gizzo | AF9: None | AG9: JUN'26 | AH9: 199999.99 | AI9: 109200 | AJ9: Adam Chardavoyne
A10: AGC001913 | B10: EGGLANDS FOOD COMPANY | C10: ADV006280 | D10: Eggland's Best/Digital/Scatter/Entertainment/2Q-3Q26 | E10: 257492 | F10: DIO - LFV - Entertainment ROS - Package | G10: 2789 | H10: 549546 | I10: EGGLAND'S BEST/D/ENT/SCATTER/RON/2-3Q'26 | J10: 46125 | K10: 46295 | L10: FOX DCM | M10: CPM | N10: 20.1 | O10: 9950249 | P10: 200000 | Q10: CoV Impressions | R10: performance | S10: 0 | T10: 0 | U10: performance | V10: 488055 | W10: invoice_schedule | X10: 9809.9055 | Y10: 9809.9055 | Z10: 9809.9055 | AA10: 502244 | AB10: 488055 | AC10: 46125 | AD10: 46295 | AE10: John Hertman | AF10: None | AG10: JUN'26 | AH10: 300000.01 | AI10: 105784 | AJ10: Jeanne Feeley
A11: AGC001913 | B11: EGGLANDS FOOD COMPANY | C11: ADV006280 | D11: Eggland's Best/Digital/Scatter/Entertainment/2Q-3Q26 | E11: 257492 | F11: DIO - LFV - Entertainment ROS - Package | G11: 2789 | H11: 549549 | I11: EGGLAND'S BEST/LFV/Amplified Absolute A Show Mix /P2+/2-3Q'26 | J11: 46162 | K11: 46177 | L11: FOX 1st Party | M11: CPM | N11: 34 | O11: 1470589 | P11: 50000.03 | Q11: CoV Impressions | R11: performance | S11: 0 | T11: 0 | U11: performance | V11: 221142 | W11: invoice_schedule | X11: 7518.83 | Y11: 7518.83 | Z11: 7518.83 | AA11: 264775 | AB11: 0 | AC11: 46162 | AD11: 46177 | AE11: John Hertman | AF11: None | AG11: JUN'26 | AH11: 300000.01 | AI11: 105784 | AJ11: Jeanne Feeley
A12: AGC001913 | B12: EGGLANDS FOOD COMPANY | C12: ADV006280 | D12: Eggland's Best/Digital/Scatter/Entertainment/2Q-3Q26 | E12: 257492 | H12: 549554 | I12: EGGLAND'S BEST/D/ENT/SCATTER/SOCIAL/@Foodclubfox | J12: 46160 | K12: 46181 | L12: FOX 1st Party | M12: SOV-Flat Rate | N12: 50000 | O12: 1 | P12: 50000 | Q12: Impressions | R12: prorated | S12: 0 | T12: 18181.818 | U12: prorated | V12: 0 | W12: invoice_schedule | X12: 18181.818 | Y12: 18181.818 | Z12: 18181.818 | AC12: 46160 | AD12: 46181 | AE12: John Hertman | AF12: None | AG12: JUN'26 | AH12: 300000.01 | AI12: 105784 | AJ12: Jeanne Feeley
A13: AGC001913 | B13: CARNIVAL CRUISE LINES | C13: ADV004004 | D13: Carnival/2026/Scatter/Digital/MWC | E13: 257594 | F13: Run of World Cup Video - Package | G13: 8005 | H13: 580820 | I13: CARNIVAL/S/SPORTS/25-26/MWC/Run of WC Video | J13: 46174 | K13: 46222 | L13: FOX DCM | M13: CPM | N13: 35 | O13: 5400000 | P13: 189000 | Q13: Impressions | R13: performance | S13: 0 | T13: 0 | U13: performance | V13: 2428121 | W13: invoice_schedule | X13: 84984.235 | Y13: 84984.235 | Z13: 84984.235 | AA13: 2429157 | AB13: 2428121 | AC13: 46174 | AD13: 46222 | AE13: John Hertman | AF13: None | AG13: JUN'26 | AH13: 600000.03 | AI13: 127378 | AJ13: Colleen Cahill
A14: AGC001913 | B14: CARNIVAL CRUISE LINES | C14: ADV004004 | D14: Carnival/2026/Scatter/Digital/MWC | E14: 257594 | F14: Run of FOX Sports Video - Package | G14: 8002 | H14: 580823 | I14: CARNIVAL/S/SPORTS/25-26/MWC/Run of FS Video | J14: 46174 | K14: 46222 | L14: FOX DCM | M14: CPM | N14: 25 | O14: 1000000 | P14: 25000 | Q14: Impressions | R14: performance | S14: 0 | T14: 0 | U14: performance | V14: 415842 | W14: invoice_schedule | X14: 10396.05 | Y14: 10396.05 | Z14: 10396.05 | AA14: 425246 | AB14: 415842 | AC14: 46174 | AD14: 46222 | AE14: John Hertman | AF14: None | AG14: JUN'26 | AH14: 600000.03 | AI14: 127378 | AJ14: Colleen Cahill
A15: AGC001913 | B15: CARNIVAL CRUISE LINES | C15: ADV004004 | D15: Carnival/2026/Scatter/Digital/MWC | E15: 257594 | F15: Run of World Cup Display - Package | G15: 8004 | H15: 580825 | I15: CARNIVAL/S/SPORTS/25-26/MWC/Run of WC Display | J15: 46174 | K15: 46222 | L15: FOX DCM | M15: CPM | N15: 6 | O15: 8333333 | P15: 50000 | Q15: Impressions | R15: performance | S15: 0 | T15: 0 | U15: performance | V15: 6061028 | W15: invoice_schedule | X15: 36366.168 | Y15: 36366.168 | Z15: 36366.168 | AA15: 6062382 | AB15: 6061028 | AC15: 46174 | AD15: 46222 | AE15: John Hertman | AF15: None | AG15: JUN'26 | AH15: 600000.03 | AI15: 127378 | AJ15: Colleen Cahill
A16: AGC001913 | B16: CARNIVAL CRUISE LINES | C16: ADV004004 | D16: Carnival/2026/Scatter/Digital/MWC | E16: 257594 | F16: World Cup Social Sponsorship Content - Package | G16: 8000 | H16: 580840 | I16: CARNIVAL/S/SPORTS/25-26/MWC/SOCIAL | J16: 46174 | K16: 46222 | L16: FOX 1st Party | M16: SOV-Flat Rate | N16: 180000 | O16: 3 | P16: 180000 | Q16: n/a | R16: prorated | S16: 2 | T16: 110204.08 | U16: prorated | V16: 2 | W16: invoice_schedule | X16: 110204.08 | Y16: 110204.08 | Z16: 110204.08 | AC16: 46174 | AD16: 46222 | AE16: John Hertman | AF16: None | AG16: JUN'26 | AH16: 600000.03 | AI16: 127378 | AJ16: Colleen Cahill
A17: AGC001913 | B17: CARNIVAL CRUISE LINES | C17: ADV004004 | D17: Carnival/2026/Scatter/Digital/MWC | E17: 257594 | F17: Run of AllFOX Video - Package | G17: 7998 | H17: 582660 | I17: CARNIVAL/S/SPORTS/25-26/ALLFOX/AAT | J17: 46174 | K17: 46222 | L17: FOX DCM | M17: CPM | N17: 21 | O17: 7380953 | P17: 155000.01 | Q17: Impressions | R17: performance | S17: 0 | T17: 0 | U17: performance | V17: 4889067 | W17: invoice_schedule | X17: 102670.41 | Y17: 102670.41 | Z17: 102670.41 | AA17: 4881622 | AB17: 4889067 | AC17: 46174 | AD17: 46222 | AE17: John Hertman | AF17: None | AG17: JUN'26 | AH17: 600000.03 | AI17: 127378 | AJ17: Colleen Cahill
A18: AGC001913 | B18: CARNIVAL CRUISE LINES | C18: ADV004004 | D18: Carnival/2026/Scatter/Digital/MWC | E18: 257594 | F18: Run of FOX Sports Display - Package | G18: 8001 | H18: 587925 | I18: CARNIVAL/S/SPORTS/25-26/Run of FOX Sports Display | J18: 46174 | K18: 46222 | L18: FOX DCM | M18: CPM | N18: 6 | O18: 166667 | P18: 1000 | Q18: Impressions | R18: performance | S18: 0 | T18: 0 | U18: performance | V18: 36331 | W18: invoice_schedule | X18: 217.986 | Y18: 217.986 | Z18: 217.986 | AA18: 36336 | AB18: 36331 | AC18: 46174 | AD18: 46222 | AE18: John Hertman | AF18: None | AG18: JUN'26 | AH18: 600000.03 | AI18: 127378 | AJ18: Colleen Cahill
A19: AGC002070 | B19: STARBUCKS | C19: ADV005074 | D19: THE STARBUCKS COMPANY/DIGITAL/SCATTER/SPORTS/MWC/2Q'26 | E19: 259125 | F19: World Cup Social Sponsorship Content - Package | G19: 8000 | H19: 582320 | I19: Starbucks - World Cup Social Sponsorship Content - 2026 MWC Package | J19: 46174 | K19: 46201 | L19: FOX 1st Party | M19: SOV-Flat Rate | N19: 99700 | O19: 3 | P19: 99700 | Q19: n/a | R19: prorated | S19: 3 | T19: 99700 | U19: prorated | V19: 3 | W19: invoice_schedule | X19: 99700 | Y19: 99700 | Z19: 99700 | AC19: 46174 | AD19: 46201 | AE19: Matthew Vellardito | AF19: None | AG19: JUN'26 | AH19: 598482 | AI19: 129149 | AJ19: Janna Goldstein
A20: AGC002070 | B20: STARBUCKS | C20: ADV005074 | D20: THE STARBUCKS COMPANY/DIGITAL/SCATTER/SPORTS/MWC/2Q'26 | E20: 259125 | F20: Run of World Cup Video - Package | G20: 8005 | H20: 582328 | I20: Starbucks - Run of World Cup Video - 2026 MWC Package | J20: 46174 | K20: 46201 | L20: FOX Innovid | M20: CPM | N20: 40 | O20: 7500000 | P20: 300000 | Q20: Impressions | R20: performance | S20: 0 | T20: 0 | U20: performance | V20: 7500000 | W20: invoice_schedule | X20: 300000 | Y20: 300000 | Z20: 300000 | AA20: 7707810 | AB20: 7723698 | AC20: 46174 | AD20: 46201 | AE20: Matthew Vellardito | AF20: None | AG20: JUN'26 | AH20: 598482 | AI20: 129149 | AJ20: Janna Goldstein
A21: AGC002070 | B21: STARBUCKS | C21: ADV005074 | D21: THE STARBUCKS COMPANY/DIGITAL/SCATTER/SPORTS/MWC/2Q'26 | E21: 259125 | F21: Run of FOX Sports Video - Package | G21: 8002 | H21: 582346 | I21: Starbucks - Run of FOX Sports Video - 2026 MWC Package | J21: 46174 | K21: 46201 | L21: FOX Innovid | M21: CPM | N21: 25 | O21: 7951280 | P21: 198782 | R21: performance | S21: 0 | T21: 0 | U21: performance | V21: 5424817 | W21: invoice_schedule | X21: 135620.42 | Y21: 135620.42 | Z21: 135620.42 | AA21: 5380998 | AB21: 5424817 | AC21: 46174 | AD21: 46201 | AE21: Matthew Vellardito | AF21: None | AG21: JUN'26 | AH21: 598482 | AI21: 129149 | AJ21: Janna Goldstein
A22: AGC002408 | B22: FCA NORTH AMERICA HOLDINGS | C22: ADV001639 | D22: FCA(Stellantis)/DIGITAL/SCATTER/SPORTS/MWC | E22: 259149 | F22: Run of World Cup Video - Package | G22: 8005 | H22: 582769 | I22: Stellantis - Run of World Cup Video + Tubi - Package 2026 | J22: 46174 | K22: 46222 | L22: FOX Innovid | M22: CPM | N22: 40 | O22: 17500000 | P22: 700000 | Q22: Impressions | R22: performance | S22: 0 | T22: 0 | U22: performance | V22: 11628821 | W22: invoice_schedule | X22: 465152.84 | Y22: 465152.84 | Z22: 465152.84 | AA22: 11607293 | AB22: 11628821 | AC22: 46174 | AD22: 46222 | AE22: Megan Sileo | AF22: None | AG22: JUN'26 | AH22: 1275000 | AI22: 126262 | AJ22: Janna Goldstein
A23: AGC002408 | B23: FCA NORTH AMERICA HOLDINGS | C23: ADV001639 | D23: FCA(Stellantis)/DIGITAL/SCATTER/SPORTS/MWC | E23: 259149 | F23: Run of AllFOX Video - Package | G23: 7998 | H23: 582772 | I23: Stellantis - Run of AllFOX Video - Package -AAT- 2026 | J23: 46174 | K23: 46222 | L23: FOX Innovid | M23: CPM | N23: 18.25 | O23: 17808220 | P23: 325000.02 | Q23: Impressions | R23: performance | S23: 0 | T23: 0 | U23: performance | V23: 12109273 | W23: invoice_schedule | X23: 220994.23 | Y23: 220994.23 | Z23: 220994.23 | AA23: 12124261 | AB23: 12109273 | AC23: 46174 | AD23: 46222 | AE23: Megan Sileo | AF23: None | AG23: JUN'26 | AH23: 1275000 | AI23: 126262 | AJ23: Janna Goldstein
A24: AGC002408 | B24: FCA NORTH AMERICA HOLDINGS | C24: ADV001639 | D24: FCA(Stellantis)/DIGITAL/SCATTER/SPORTS/MWC | E24: 259149 | F24: World Cup Social Sponsorship Content - Package | G24: 8000 | H24: 582785 | I24: Stellantis - World Cup Social Sponsorship Content - X Amplify - Package - 2026 | J24: 46174 | K24: 46222 | L24: FOX 1st Party | M24: SOV-Flat Rate | N24: 250000 | O24: 1 | P24: 250000 | Q24: n/a | R24: prorated | S24: 1 | T24: 153061.22 | U24: prorated | V24: 1 | W24: invoice_schedule | X24: 153061.22 | Y24: 153061.22 | Z24: 153061.22 | AC24: 46174 | AD24: 46222 | AE24: Megan Sileo | AF24: None | AG24: JUN'26 | AH24: 1275000 | AI24: 126262 | AJ24: Janna Goldstein
A25: AGC002408 | B25: VISA | C25: ADV006353 | D25: VISA/DIGITAL/SCATTER/SPORTS/MWC/WellsFargo | E25: 259155 | F25: World Cup Social Sponsorship Content - Package | G25: 8000 | H25: 581608 | I25: VISA - Wells Fargo - OMP - World Cup Social Sponsorship Content - Package - 2026 | J25: 46174 | K25: 46222 | L25: FOX 1st Party | M25: SOV-Flat Rate | N25: 1000000 | O25: 3 | P25: 1000000 | Q25: n/a | R25: prorated | S25: 2 | T25: 612244.9 | U25: prorated | V25: 2 | W25: invoice_schedule | X25: 612244.9 | Y25: 612244.9 | Z25: 612244.9 | AC25: 46174 | AD25: 46222 | AE25: Megan Sileo | AF25: None | AG25: JUN'26 | AH25: 1000000 | AI25: 127440 | AJ25: Janna Goldstein
A26: AGC002330 | B26: JOHNSONVILLE | C26: ADV000112 | D26: Johnsonville/Digital/Upfront/Entertainment - UF 2025/26 | E26: 259248 | F26: DIO - LFV - Entertainment ROS - Package | G26: 2789 | H26: 554207 | I26: Johnsonville - DIO - LFV - Entertainment ROS - Package | J26: 46083 | K26: 46387 | M26: CPM | N26: 24.9 | O26: 6024097 | P26: 150000.02 | Q26: CoV Impressions | R26: performance | S26: 0 | T26: 0 | U26: performance | V26: 0 | W26: invoice_schedule | X26: 0 | Y26: 0 | Z26: 0 | AC26: 46083 | AD26: 46387 | AE26: JohnMichael Bogusz | AF26: None | AG26: JUN'26 | AH26: 150000.03 | AI26: 119053 | AJ26: Tierney Flynn
A27: AGC002408 | B27: ANHEUSER BUSCH | C27: ADV001839 | D27: AB/DIGITAL/SCATTER/SPORTS/MWC | E27: 259270 | F27: World Cup Social Sponsorship Content - Package | G27: 8000 | H27: 581380 | I27: Anheuser-Busch - OMP - World Cup Social Sponsorship Content - Player of the Match - 2026 Package | J27: 46174 | K27: 46222 | L27: FOX 1st Party | M27: SOV-Flat Rate | N27: 1454124 | O27: 3 | P27: 1454124 | Q27: n/a | R27: prorated | S27: 2 | T27: 890280 | U27: prorated | V27: 2 | W27: invoice_schedule | X27: 890280 | Y27: 890280 | Z27: 890280 | AC27: 46174 | AD27: 46222 | AE27: Megan Sileo | AF27: None | AG27: JUN'26 | AH27: 1454124 | AI27: 128025 | AJ27: Janna Goldstein
A28: AGC001122 | B28: HOMES.COM | C28: ADV012887 | D28: Homes.com/Digital/Upfront/Entertainment/Targeted/UF 2025/26 - 1Q-3Q'26 | E28: 259271 | F28: LFV - RON Ent - ROS - Pre/Mid - DT/MB/CTV/VOD - Package | G28: 3535 | H28: 554320 | I28: CANCELLED_Homes.com_AAT_LFV - RON Ent - ROS - Pre/Mid - DT/MB/CTV - Package - 2Q'26 - A25-54 & HHI $75K+ | J28: 46113 | K28: 46203 | L28: FOX Innovid | M28: CPM | N28: 0 | O28: 0 | P28: 0 | Q28: Impressions | R28: performance | S28: 0 | T28: 0 | U28: performance | V28: 0 | W28: invoice_schedule | X28: 0 | Y28: 0 | Z28: 0 | AC28: 46113 | AD28: 46203 | AE28: Creighton Hendrix | AF28: None | AG28: JUN'26 | AH28: 192951.5 | AI28: 111881 | AJ28: Nathan Cortez
A29: AGC002070 | B29: LOWE'S HOME CENTERS | C29: ADV003680 | D29: LOWE'S/DIGITAL/SCATTER/SPORTS/MWC/25-26 | E29: 259384 | F29: Run of World Cup Display - Package | G29: 8004 | H29: 582844 | I29: Lowe's - Run of World Cup Display - 2026 MWC Package | J29: 46174 | K29: 46222 | L29: FOX DCM | M29: CPM | N29: 6 | O29: 41666667 | P29: 250000 | Q29: Impressions | R29: prorated | S29: 25510205 | T29: 153061.22 | U29: prorated | V29: 25510205 | W29: invoice_schedule | X29: 153061.22 | Y29: 153061.22 | Z29: 153061.22 | AA29: 14689500 | AB29: 14687116 | AC29: 46174 | AD29: 46222 | AE29: Matthew Vellardito | AF29: None | AG29: JUN'26 | AH29: 1733100 | AI29: 129141 | AJ29: Janna Goldstein
A30: AGC002070 | B30: LOWE'S HOME CENTERS | C30: ADV003680 | D30: LOWE'S/DIGITAL/SCATTER/SPORTS/MWC/25-26 | E30: 259384 | F30: Run of World Cup Video - Package | G30: 8005 | H30: 582848 | I30: Lowe's - Run of World Cup Video - 2026 MWC Package | J30: 46174 | K30: 46222 | L30: FOX 1st Party | M30: CPM | N30: 40 | O30: 15625000 | P30: 625000 | Q30: Impressions | R30: prorated | S30: 9566327 | T30: 382653.06 | U30: prorated | V30: 9566327 | W30: invoice_schedule | X30: 382653.06 | Y30: 382653.06 | Z30: 382653.06 | AA30: 10361861 | AB30: 0 | AC30: 46174 | AD30: 46222 | AE30: Matthew Vellardito | AF30: None | AG30: JUN'26 | AH30: 1733100 | AI30: 129141 | AJ30: Janna Goldstein
A31: AGC002070 | B31: LOWE'S HOME CENTERS | C31: ADV003680 | D31: LOWE'S/DIGITAL/SCATTER/SPORTS/MWC/25-26 | E31: 259384 | F31: World Cup FOX Sports Site & App Takeover - Package | G31: 8003 | H31: 582860 | I31: Lowe's - World Cup FOX Sports Site & App Takeover - 6/16 Argentina vs. Algeria - 2026 MWC Package | J31: 46189 | K31: 46189 | L31: FOX DCM | M31: Cost Per Day | N31: 50000 | O31: 6 | P31: 300000 | Q31: Days | R31: prorated | S31: 6 | T31: 300000 | U31: prorated | V31: 6 | W31: invoice_schedule | X31: 300000 | Y31: 300000 | Z31: 300000 | AA31: 0 | AB31: 0 | AC31: 46189 | AD31: 46189 | AE31: Matthew Vellardito | AF31: None | AG31: JUN'26 | AH31: 1733100 | AI31: 129141 | AJ31: Janna Goldstein
A32: AGC002070 | B32: LOWE'S HOME CENTERS | C32: ADV003680 | D32: LOWE'S/DIGITAL/SCATTER/SPORTS/MWC/25-26 | E32: 259384 | F32: Run of FOX Sports Video - Package | G32: 8002 | H32: 582873 | I32: Lowe's - Run of FOX Sports Video - 2026 MWC Package | J32: 46174 | K32: 46222 | L32: FOX 1st Party | M32: CPM | N32: 25 | O32: 2200000 | P32: 55000 | R32: prorated | S32: 1346939 | T32: 33673.469 | U32: prorated | V32: 1346939 | W32: invoice_schedule | X32: 33673.469 | Y32: 33673.469 | Z32: 33673.469 | AA32: 892237 | AB32: 0 | AC32: 46174 | AD32: 46222 | AE32: Matthew Vellardito | AF32: None | AG32: JUN'26 | AH32: 1733100 | AI32: 129141 | AJ32: Janna Goldstein
A33: AGC002070 | B33: LOWE'S HOME CENTERS | C33: ADV003680 | D33: LOWE'S/DIGITAL/SCATTER/SPORTS/MWC/25-26 | E33: 259384 | F33: Run of AllFOX Video - Package | G33: 7998 | H33: 582880 | I33: Lowe's - Run of AllFOX Video - 2026 MWC Package | J33: 46174 | K33: 46222 | L33: FOX 1st Party | M33: CPM | N33: 20 | O33: 12655000 | P33: 253100 | Q33: Impressions | R33: prorated | S33: 7747960 | T33: 154959.18 | U33: prorated | V33: 7747960 | W33: invoice_schedule | X33: 154959.18 | Y33: 154959.18 | Z33: 154959.18 | AA33: 8596683 | AB33: 0 | AC33: 46174 | AD33: 46222 | AE33: Matthew Vellardito | AF33: None | AG33: JUN'26 | AH33: 1733100 | AI33: 129141 | AJ33: Janna Goldstein
A34: AGC002070 | B34: LOWE'S HOME CENTERS | C34: ADV003680 | D34: LOWE'S/DIGITAL/SCATTER/SPORTS/MWC/25-26 | E34: 259384 | F34: World Cup Social Sponsorship Content - Package | G34: 8000 | H34: 582957 | I34: Lowe's World Cup Social Sponsorship Content - X - 2026 MWC Package | J34: 46174 | K34: 46222 | L34: FOX 1st Party | M34: SOV-Flat Rate | N34: 250000 | O34: 1 | P34: 250000 | Q34: n/a | R34: prorated | S34: 1 | T34: 153061.22 | U34: prorated | V34: 1 | W34: invoice_schedule | X34: 153061.22 | Y34: 153061.22 | Z34: 153061.22 | AC34: 46174 | AD34: 46222 | AE34: Matthew Vellardito | AF34: None | AG34: JUN'26 | AH34: 1733100 | AI34: 129141 | AJ34: Janna Goldstein
A35: AGC001386 | B35: BRISTOL MYERS SQUIBB | C35: ADV003845 | D35: BMS/25-26/Upfront/Digital/ENT/CAMZYOS | E35: 259418 | F35: DIO - LFV - Entertainment ROS - Package | G35: 2789 | H35: 556247 | I35: BMS/UF/RON/25-26/AAT/2Q'26/CAMZYOS | J35: 46113 | K35: 46203 | L35: FOX Flashtalking | M35: CPM | N35: 42.4 | O35: 1768868 | P35: 75000 | Q35: Impressions | R35: performance | S35: 0 | T35: 0 | U35: performance | V35: 230619 | W35: invoice_schedule | X35: 9778.2456 | Y35: 9778.2456 | Z35: 9778.2456 | AA35: 216609 | AB35: 230619 | AC35: 46113 | AD35: 46203 | AE35: John Hertman | AF35: None | AG35: JUN'26 | AH35: 150000.04 | AI35: 108708 | AJ35: Jeanne Feeley
A36: AGC001386 | B36: BRISTOL MYERS SQUIBB | C36: ADV003845 | D36: BMS/25-26/Upfront/Digital/Sports/COBENFY | E36: 259424 | F36: DIO - LFV - FSLS - Pre/Mid - ROS - DT/MB/CTV - Package | G36: 3534 | H36: 556649 | I36: BMS/UF/SPORTS/D/25-26/LFV/AAT/2Q'26/COBENFY | J36: 46113 | K36: 46191 | L36: FOX Flashtalking | M36: CPM | N36: 59 | O36: 81017 | P36: 4780 | Q36: Impressions | R36: performance | S36: 0 | T36: 0 | U36: performance | V36: 60162 | W36: invoice_schedule | X36: 3549.558 | Y36: 3549.558 | Z36: 3549.558 | AA36: 61060 | AB36: 60162 | AC36: 46113 | AD36: 46191 | AE36: John Hertman | AF36: None | AG36: JUN'26 | AH36: 119707.91 | AI36: 109443 | AJ36: Colleen Cahill
A37: AGC003164 | B37: ADIDAS | C37: ADV002210 | D37: adidas/2026/Scatter/Digital/MWC | E37: 259461 | F37: Run of World Cup Video - Package | G37: 8005 | H37: 582793 | I37: Adidas - Run of World Cup Video - Package | J37: 46177 | K37: 46222 | L37: FOX DCM | M37: CPM | N37: 40 | O37: 18750000 | P37: 750000 | Q37: Impressions | R37: performance | S37: 0 | T37: 0 | U37: performance | V37: 12524712 | W37: invoice_schedule | X37: 500988.48 | Y37: 500988.48 | Z37: 500988.48 | AA37: 12681744 | AB37: 12524712 | AC37: 46177 | AD37: 46222 | AE37: Kelsey Brahms | AF37: None | AG37: JUN'26 | AH37: 3000000 | AI37: 130306 | AJ37: Colleen Cahill
A38: AGC003164 | B38: ADIDAS | C38: ADV002210 | D38: adidas/2026/Scatter/Digital/MWC | E38: 259461 | F38: World Cup Social Sponsorship Content - Package | G38: 8000 | H38: 582794 | I38: Adidas - World Cup Social- Highlights/WC Coverage | J38: 46174 | K38: 46222 | M38: SOV-Flat Rate | N38: 1250000 | O38: 3 | P38: 1250000 | Q38: n/a | R38: prorated | S38: 2 | T38: 765306.12 | U38: prorated | V38: 2 | W38: invoice_schedule | X38: 765306.12 | Y38: 765306.12 | Z38: 765306.12 | AC38: 46174 | AD38: 46222 | AE38: Kelsey Brahms | AF38: None | AG38: JUN'26 | AH38: 3000000 | AI38: 130306 | AJ38: Colleen Cahill
A39: AGC003164 | B39: ADIDAS | C39: ADV002210 | D39: adidas/2026/Scatter/Digital/MWC | E39: 259461 | F39: World Cup Social Sponsorship Content - Package | G39: 8000 | H39: 593458 | I39: Adidas - World Cup Social- Custom 8 | J39: 46184 | K39: 46222 | M39: SOV-Flat Rate | N39: 1000000 | O39: 3 | P39: 1000000 | Q39: n/a | R39: prorated | S39: 2 | T39: 512820.51 | U39: prorated | V39: 2 | W39: invoice_schedule | X39: 512820.51 | Y39: 512820.51 | Z39: 512820.51 | AC39: 46184 | AD39: 46222 | AE39: Kelsey Brahms | AF39: None | AG39: JUN'26 | AH39: 3000000 | AI39: 130306 | AJ39: Colleen Cahill
A40: AGC000913 | B40: TACO BELL | C40: ADV000233 | D40: TACO BELL/DIGITAL/UPFRONT/FOXSPORTS/UF 2025/26/MWC | E40: 259734 | F40: Run of World Cup Video - Package | G40: 8005 | H40: 582242 | I40: Taco Bell - Run of World Cup Video - Package | J40: 46174 | K40: 46222 | L40: FOX Extreme Reach | M40: CPM | N40: 40 | O40: 8906250 | P40: 356250 | Q40: Impressions | R40: performance | S40: 0 | T40: 0 | U40: performance | V40: 5694888 | W40: invoice_schedule | X40: 227795.52 | Y40: 227795.52 | Z40: 227795.52 | AA40: 5919640 | AB40: 5694888 | AC40: 46174 | AD40: 46222 | AE40: Katie Johnson | AF40: None | AG40: JUN'26 | AH40: 712500.03 | AI40: 129262 | AJ40: Tim Wodzisz
A41: AGC000913 | B41: TACO BELL | C41: ADV000233 | D41: TACO BELL/DIGITAL/UPFRONT/FOXSPORTS/UF 2025/26/MWC | E41: 259734 | F41: World Cup Social Sponsorship Content - Package | G41: 8000 | H41: 582245 | I41: Taco Bell - World Cup Social Sponsorship Content - Package | J41: 46174 | K41: 46222 | L41: FOX Extreme Reach | M41: SOV-Flat Rate | N41: 356250 | O41: 3 | P41: 356250 | Q41: n/a | R41: prorated | S41: 2 | T41: 218112.24 | U41: prorated | V41: 2 | W41: invoice_schedule | X41: 218112.24 | Y41: 218112.24 | Z41: 218112.24 | AC41: 46174 | AD41: 46222 | AE41: Katie Johnson | AF41: None | AG41: JUN'26 | AH41: 712500.03 | AI41: 129262 | AJ41: Tim Wodzisz
A42: AGC002371 | B42: NUTRAFOL | C42: ADV008819 | D42: Nutrafol/25-26/2Q26/Digital/Sports/DR | E42: 259968 | F42: Generic Flighted Bottom Up Package | G42: 1 | H42: 556835 | I42: Tatari/Nutrafol/25-26/Digital/Sports/ROS/Preempt -3Q26 | J42: 46181 | K42: 46203 | L42: FOX Extreme Reach | M42: CPM | N42: 15 | O42: 2083394 | P42: 31250.92 | Q42: Impressions | R42: performance | S42: 0 | T42: 0 | U42: performance | V42: 36 | W42: invoice_schedule | X42: 0.54 | Y42: 0.54 | Z42: 0.54 | AA42: 368 | AB42: 36 | AC42: 46181 | AD42: 46203 | AE42: Jessica Lang | AF42: None | AG42: JUN'26 | AH42: 31250.92 | AI42: 121116 | AJ42: Nunzio Belfiore
A43: AGC002175 | B43: KEURIG DR PEPPER | C43: ADV000835 | D43: KDP/DIGITAL/UPFRONT 2025/2026/SPORTS/FLEX FUND/1Q'26-2Q'26 | E43: 260800 | F43: Generic Flighted Bottom Up Package | G43: 1 | H43: 559447 | I43: KDP - FLEX FUND - ROV - FS - Pre/Mid - ROS - DT/MB/CTV - P2+ - 2Q'26 Package | J43: 46111 | K43: 46201 | L43: FOX DCM | M43: CPM | N43: 21.79 | O43: 2914182 | P43: 63500.02 | R43: performance | S43: 0 | T43: 0 | U43: performance | V43: 107633 | W43: invoice_schedule | X43: 2345.3231 | Y43: 2345.3231 | Z43: 2345.3231 | AA43: 108257 | AB43: 107633 | AC43: 46111 | AD43: 46201 | AE43: Matthew Vellardito | AF43: None | AG43: JUN'26 | AH43: 127500.01 | AI43: 111730 | AJ43: Janna Goldstein
A44: AGC001810 | B44: WALMART | C44: ADV006265 | D44: Walmart/2026 MWC/Digital/Scatter | E44: 261764 | F44: Run of World Cup Video - Package | G44: 8005 | H44: 581693 | I44: Walmart - BTX2 - Run of World Cup Video - Package - 2026 | J44: 46195 | K44: 46203 | L44: FOX Innovid | M44: CPM | N44: 40 | O44: 1675000 | P44: 67000 | Q44: Impressions | R44: performance | S44: 0 | T44: 0 | U44: performance | V44: 1675000 | W44: invoice_schedule | X44: 67000 | Y44: 67000 | Z44: 67000 | AA44: 1697860 | AB44: 1706824 | AC44: 46195 | AD44: 46203 | AE44: Megan Sileo | AF44: None | AG44: JUN'26 | AH44: 1870000 | AI44: 130574 | AJ44: Tom Cecil
A45: AGC001810 | B45: WALMART | C45: ADV006265 | D45: Walmart/2026 MWC/Digital/Scatter | E45: 261764 | F45: Run of World Cup Display - Package | G45: 8004 | H45: 581709 | I45: Walmart - EX2- Run of World Cup Display - Package - 2026 | J45: 46181 | K45: 46222 | L45: FOX DCM | M45: CPM | N45: 6 | O45: 60000000 | P45: 360000 | Q45: Impressions | R45: performance | S45: 0 | T45: 0 | U45: performance | V45: 14985805 | W45: invoice_schedule | X45: 89914.83 | Y45: 89914.83 | Z45: 89914.83 | AA45: 15269308 | AB45: 14985805 | AC45: 46181 | AD45: 46222 | AE45: Megan Sileo | AF45: None | AG45: JUN'26 | AH45: 1870000 | AI45: 130574 | AJ45: Tom Cecil
A46: AGC001810 | B46: WALMART | C46: ADV006265 | D46: Walmart/2026 MWC/Digital/Scatter | E46: 261764 | F46: Run of AllFOX Video - Package | G46: 7998 | H46: 581823 | I46: Walmart - BTX2 - Run of AllFOX Video - Package - 2026 - AAT | J46: 46195 | K46: 46234 | L46: FOX Innovid | M46: CPM | N46: 20 | O46: 625000 | P46: 12500 | Q46: Impressions | R46: performance | S46: 0 | T46: 0 | U46: performance | V46: 192625 | W46: invoice_schedule | X46: 3852.5 | Y46: 3852.5 | Z46: 3852.5 | AA46: 187137 | AB46: 192625 | AC46: 46195 | AD46: 46234 | AE46: Megan Sileo | AF46: None | AG46: JUN'26 | AH46: 1870000 | AI46: 130574 | AJ46: Tom Cecil
A47: AGC001810 | B47: WALMART | C47: ADV006265 | D47: Walmart/2026 MWC/Digital/Scatter | E47: 261764 | F47: World Cup Social Sponsorship Content - Package | G47: 8000 | H47: 581826 | I47: Walmart - BTX2 - World Cup Social Sponsorship Content - Package - 2026 | J47: 46195 | K47: 46222 | M47: SOV-Flat Rate | N47: 50000 | O47: 3 | P47: 50000 | Q47: n/a | R47: prorated | S47: 0 | T47: 16071.428 | U47: prorated | V47: 0 | W47: invoice_schedule | X47: 16071.428 | Y47: 16071.428 | Z47: 16071.428 | AC47: 46195 | AD47: 46222 | AE47: Megan Sileo | AF47: None | AG47: JUN'26 | AH47: 1870000 | AI47: 130574 | AJ47: Tom Cecil
A48: AGC001810 | B48: WALMART | C48: ADV006265 | D48: Walmart/2026 MWC/Digital/Scatter | E48: 261764 | F48: Run of World Cup Video - Package | G48: 8005 | H48: 592687 | I48: Walmart - EX2 - Run of World Cup Video - Package - 2026 | J48: 46181 | K48: 46222 | L48: FOX Innovid | M48: CPM | N48: 40 | O48: 2675000 | P48: 107000 | Q48: Impressions | R48: performance | S48: 0 | T48: 0 | U48: performance | V48: 1796691 | W48: invoice_schedule | X48: 71867.64 | Y48: 71867.64 | Z48: 71867.64 | AA48: 1787936 | AB48: 1796691 | AC48: 46181 | AD48: 46222 | AE48: Megan Sileo | AF48: None | AG48: JUN'26 | AH48: 1870000 | AI48: 130574 | AJ48: Tom Cecil
A49: AGC001810 | B49: WALMART | C49: ADV006265 | D49: Walmart/2026 MWC/Digital/Scatter | E49: 261764 | F49: Run of AllFOX Video - Package | G49: 7998 | H49: 592690 | I49: Walmart - EX2 - Run of AllFOX Video - Package - 2026 - AAT | J49: 46181 | K49: 46222 | L49: FOX Innovid | M49: CPM | N49: 20 | O49: 1594423 | P49: 31888.46 | Q49: Impressions | R49: performance | S49: 0 | T49: 0 | U49: performance | V49: 1072448 | W49: invoice_schedule | X49: 21448.96 | Y49: 21448.96 | Z49: 21448.96 | AA49: 1060856 | AB49: 1072448 | AC49: 46181 | AD49: 46222 | AE49: Megan Sileo | AF49: None | AG49: JUN'26 | AH49: 1870000 | AI49: 130574 | AJ49: Tom Cecil
A50: AGC001810 | B50: WALMART | C50: ADV006265 | D50: Walmart/2026 MWC/Digital/Scatter | E50: 261764 | F50: World Cup Social Sponsorship Content - Package | G50: 8000 | H50: 592693 | I50: Walmart - EX2 - World Cup Social Sponsorship Content - Package - 2026 | J50: 46174 | K50: 46222 | M50: SOV-Flat Rate | N50: 300000 | O50: 3 | P50: 300000 | Q50: n/a | R50: prorated | S50: 2 | T50: 183673.47 | U50: prorated | V50: 2 | W50: invoice_schedule | X50: 183673.47 | Y50: 183673.47 | Z50: 183673.47 | AC50: 46174 | AD50: 46222 | AE50: Megan Sileo | AF50: None | AG50: JUN'26 | AH50: 1870000 | AI50: 130574 | AJ50: Tom Cecil
A51: AGC001810 | B51: WALMART | C51: ADV006265 | D51: Walmart/2026 MWC/Digital/Scatter | E51: 261764 | F51: Run of World Cup Video - Package | G51: 8005 | H51: 592716 | I51: Walmart - WAL2 - Run of World Cup Video - Package - 2026 | J51: 46181 | K51: 46222 | L51: FOX Innovid | M51: CPM | N51: 40 | O51: 4650000 | P51: 186000 | Q51: Impressions | R51: performance | S51: 0 | T51: 0 | U51: performance | V51: 3114636 | W51: invoice_schedule | X51: 124585.44 | Y51: 124585.44 | Z51: 124585.44 | AA51: 3108177 | AB51: 3114636 | AC51: 46181 | AD51: 46222 | AE51: Megan Sileo | AF51: None | AG51: JUN'26 | AH51: 1870000 | AI51: 130574 | AJ51: Tom Cecil
A52: AGC001810 | B52: WALMART | C52: ADV006265 | D52: Walmart/2026 MWC/Digital/Scatter | E52: 261764 | F52: Run of AllFOX Video - Package | G52: 7998 | H52: 592720 | I52: Walmart - WAL2 - Run of AllFOX Video - Package - 2026 - AAT | J52: 46181 | K52: 46234 | L52: FOX Innovid | M52: CPM | N52: 20 | O52: 1398367 | P52: 27967.34 | Q52: Impressions | R52: performance | S52: 0 | T52: 0 | U52: performance | V52: 938457 | W52: invoice_schedule | X52: 18769.14 | Y52: 18769.14 | Z52: 18769.14 | AA52: 932078 | AB52: 938457 | AC52: 46181 | AD52: 46234 | AE52: Megan Sileo | AF52: None | AG52: JUN'26 | AH52: 1870000 | AI52: 130574 | AJ52: Tom Cecil
A53: AGC001810 | B53: WALMART | C53: ADV006265 | D53: Walmart/2026 MWC/Digital/Scatter | E53: 261764 | F53: World Cup Social Sponsorship Content - Package | G53: 8000 | H53: 592724 | I53: Walmart - WAL2 - World Cup Social Sponsorship Content - Package - 2026 | J53: 46174 | K53: 46222 | M53: SOV-Flat Rate | N53: 210000 | O53: 3 | P53: 210000 | Q53: n/a | R53: prorated | S53: 2 | T53: 128571.43 | U53: prorated | V53: 2 | W53: invoice_schedule | X53: 128571.43 | Y53: 128571.43 | Z53: 128571.43 | AC53: 46174 | AD53: 46222 | AE53: Megan Sileo | AF53: None | AG53: JUN'26 | AH53: 1870000 | AI53: 130574 | AJ53: Tom Cecil
A54: AGC001318 | B54: HYUNDAI | C54: ADV003876 | D54: Hyundai/Digital/Scatter/Sports/MWC/25-26 | E54: 261946 | F54: Run of World Cup Display - Package | G54: 8004 | H54: 581295 | I54: Hyundai - Run of World Cup Display - Package - 728x90, 300x250,320x50 - OMP | J54: 46174 | K54: 46222 | L54: FOX DCM | M54: CPM | N54: 10 | O54: 5000000 | P54: 50000 | Q54: Impressions | R54: performance | S54: 0 | T54: 0 | U54: performance | V54: 3671918 | W54: invoice_schedule | X54: 36719.18 | Y54: 36719.18 | Z54: 36719.18 | AA54: 4194623 | AB54: 3671918 | AC54: 46174 | AD54: 46222 | AE54: Jessica Lang | AF54: None | AG54: JUN'26 | AH54: 850000.32 | AI54: 126577 | AJ54: Dylan Giordano
A55: AGC001318 | B55: HYUNDAI | C55: ADV003876 | D55: Hyundai/Digital/Scatter/Sports/MWC/25-26 | E55: 261946 | F55: World Cup Social Sponsorship Content - Package | G55: 8000 | H55: 582460 | I55: Hyundai - World Cup Social Sponsorship Content - Package | J55: 46174 | K55: 46222 | M55: Cost Per Unit | N55: 0.15 | O55: 1000002 | P55: 150000.3 | Q55: Placements | R55: straightline | S55: 500001 | T55: 75000.15 | U55: straightline | V55: 500001 | W55: invoice_schedule | X55: 75000.15 | Y55: 75000.15 | Z55: 75000.15 | AC55: 46174 | AD55: 46222 | AE55: Jessica Lang | AF55: None | AG55: JUN'26 | AH55: 850000.32 | AI55: 126577 | AJ55: Dylan Giordano
A56: AGC001318 | B56: HYUNDAI | C56: ADV003876 | D56: Hyundai/Digital/Scatter/Sports/MWC/25-26 | E56: 261946 | F56: Run of World Cup Video - Package | G56: 8005 | H56: 582466 | I56: Hyundai - Run of World Cup Video - Package - OMP | J56: 46174 | K56: 46222 | L56: FOX DCM | M56: CPM | N56: 40 | O56: 10000000 | P56: 400000 | Q56: Impressions | R56: performance | S56: 0 | T56: 0 | U56: performance | V56: 3777132 | W56: invoice_schedule | X56: 151085.28 | Y56: 151085.28 | Z56: 151085.28 | AA56: 3765120 | AB56: 1152277 | AC56: 46174 | AD56: 46222 | AE56: Jessica Lang | AF56: None | AG56: JUN'26 | AH56: 850000.32 | AI56: 126577 | AJ56: Dylan Giordano
A57: AGC001318 | B57: HYUNDAI | C57: ADV003876 | D57: Hyundai/Digital/Scatter/Sports/MWC/25-26 | E57: 261946 | F57: Run of FOX Sports Display - Package | G57: 8001 | H57: 582471 | I57: Hyundai - Run of FOX Sports Display - Package - 728x90, 300x250,320x50, 300x600 - OMP | J57: 46174 | K57: 46234 | L57: FOX DCM | M57: CPM | N57: 5 | O57: 20000000 | P57: 100000 | Q57: Impressions | R57: performance | S57: 0 | T57: 0 | U57: performance | V57: 13637077 | W57: invoice_schedule | X57: 68185.385 | Y57: 68185.385 | Z57: 68185.385 | AA57: 12836084 | AB57: 13637077 | AC57: 46174 | AD57: 46234 | AE57: Jessica Lang | AF57: None | AG57: JUN'26 | AH57: 850000.32 | AI57: 126577 | AJ57: Dylan Giordano
A58: AGC001318 | B58: HYUNDAI | C58: ADV003876 | D58: Hyundai/Digital/Scatter/Sports/MWC/25-26 | E58: 261946 | F58: Run of AllFOX Video - Package | G58: 7998 | H58: 582565 | I58: Hyundai - Run of AllFOX Video - Package | J58: 46174 | K58: 46222 | L58: FOX DCM | M58: CPM | N58: 23 | O58: 6521740 | P58: 150000.02 | Q58: Impressions | R58: performance | S58: 0 | T58: 0 | U58: performance | V58: 2415792 | W58: invoice_schedule | X58: 55563.216 | Y58: 55563.216 | Z58: 55563.216 | AA58: 2380338 | AB58: 2415792 | AC58: 46174 | AD58: 46222 | AE58: Jessica Lang | AF58: None | AG58: JUN'26 | AH58: 850000.32 | AI58: 126577 | AJ58: Dylan Giordano
A59: AGC000898 | B59: UNIVERSAL PICTURES | C59: ADV000562 | D59: Universal Pictures/Digital/Scatter/Sports/MWC 2026/Disclosure Day | E59: 261965 | F59: Run of World Cup Video - Package | G59: 8005 | H59: 581358 | I59: Universal- Run of World Cup Video - Package (Disclosure Day) | J59: 46184 | K59: 46192 | L59: FOX DCM | M59: CPM | N59: 40 | O59: 539275 | P59: 21571 | Q59: Impressions | R59: performance | S59: 0 | T59: 0 | U59: performance | V59: 539192 | W59: invoice_schedule | X59: 21567.68 | Y59: 21567.68 | Z59: 21567.68 | AA59: 538604 | AB59: 539192 | AC59: 46184 | AD59: 46192 | AE59: Marcela Miranda | AF59: None | AG59: JUN'26 | AH59: 21571 | AI59: 130009 | AJ59: Gina Rodarte
A60: AGC004676 | B60: COCA COLA | C60: ADV000868 | D60: POWERADE/DIGITAL/SCATTER/SPORTS/MWC | E60: 262032 | F60: World Cup Social Sponsorship Content - Package | G60: 8000 | H60: 582127 | I60: Powerade - OMP - World Cup Social Sponsorship Content - 2026 MWC Package | J60: 46174 | K60: 46222 | L60: FOX 1st Party | M60: SOV-Flat Rate | N60: 199000 | O60: 3 | P60: 199000 | Q60: n/a | R60: prorated | S60: 2 | T60: 121836.73 | U60: prorated | V60: 2 | W60: invoice_schedule | X60: 121836.73 | Y60: 121836.73 | Z60: 121836.73 | AC60: 46174 | AD60: 46222 | AE60: Matthew Vellardito | AF60: None | AG60: JUN'26 | AH60: 397600 | AI60: 128489 | AJ60: Janna Goldstein
A61: AGC004676 | B61: COCA COLA | C61: ADV000868 | D61: POWERADE/DIGITAL/SCATTER/SPORTS/MWC | E61: 262032 | F61: Run of World Cup Display - Package | G61: 8004 | H61: 582145 | I61: Powerade - OMP - Run of World Cup Display - 2026 MWC Package | J61: 46174 | K61: 46222 | L61: FOX DCM | M61: CPM | N61: 6 | O61: 5583333 | P61: 33500 | Q61: Impressions | R61: performance | S61: 0 | T61: 0 | U61: performance | V61: 4093433 | W61: invoice_schedule | X61: 24560.598 | Y61: 24560.598 | Z61: 24560.598 | AA61: 4078551 | AB61: 4093433 | AC61: 46174 | AD61: 46222 | AE61: Matthew Vellardito | AF61: None | AG61: JUN'26 | AH61: 397600 | AI61: 128489 | AJ61: Janna Goldstein
A62: AGC004676 | B62: COCA COLA | C62: ADV000868 | D62: POWERADE/DIGITAL/SCATTER/SPORTS/MWC | E62: 262032 | F62: Run of World Cup Video - Package | G62: 8005 | H62: 582166 | I62: Powerade - OMP - Run of World Cup Video - 2026 MWC Package | J62: 46174 | K62: 46222 | L62: FOX Extreme Reach | M62: CPM | N62: 40 | O62: 4127500 | P62: 165100 | Q62: Impressions | R62: performance | S62: 0 | T62: 0 | U62: performance | V62: 2644548 | W62: invoice_schedule | X62: 105781.92 | Y62: 105781.92 | Z62: 105781.92 | AA62: 2762569 | AB62: 2644548 | AC62: 46174 | AD62: 46222 | AE62: Matthew Vellardito | AF62: None | AG62: JUN'26 | AH62: 397600 | AI62: 128489 | AJ62: Janna Goldstein
A63: AGC004653 | B63: HEARTLAND FOOD PRODUCTS | C63: ADV001899 | D63: JavaHouse/SCT/Indy/Social/25-26 | E63: 262498 | F63: DIO - SOC - FOX Sports - Package | G63: 7993 | H63: 570374 | I63: Java House - Indy - DIO - SOC - FOX Sports - Package - FB/IG/TT | J63: 46082 | K63: 46278 | L63: FOX 1st Party | M63: Cost Per Unit | N63: 0.15 | O63: 666668 | P63: 100000.2 | Q63: Placements | R63: straightline | S63: 95238 | T63: 14285.743 | U63: straightline | V63: 95237 | W63: invoice_schedule | X63: 14285.55 | Y63: 14285.55 | Z63: 14285.55 | AC63: 46082 | AD63: 46278 | AE63: Kailey McGinn | AF63: None | AG63: JUN'26 | AH63: 100000.2 | AI63: 118690 | AJ63: Nicole Joscelyn
A64: AGC003039 | B64: BRIGHTHOUSE FINANCIAL | C64: ADV005685 | D64: Brighthouse Financial/AllFOX/2Q26/DIO | E64: 263735 | F64: DIO - ROV - 1F SEN - Pre/Mid - ROS - FW - SXD - Package | G64: 7950 | H64: 569809 | I64: Brighthouse Financial/AllFOX/2Q26/DIO | J64: 46118 | K64: 46203 | L64: FOX Flashtalking | M64: CPM | N64: 28 | O64: 1446429 | P64: 40500.01 | Q64: Impressions | R64: performance | S64: 0 | T64: 0 | U64: performance | V64: 456225 | W64: invoice_schedule | X64: 12774.3 | Y64: 12774.3 | Z64: 12774.3 | AA64: 454400 | AB64: 456225 | AC64: 46118 | AD64: 46203 | AE64: Kelsey Brahms | AF64: None | AG64: JUN'26 | AH64: 40500.01 | AI64: 120963 | AJ64: Bridgid Antoniello
A65: AGC002475 | B65: HEINEKEN | C65: ADV005498 | D65: HEINEKEN- Deportes - Digital - UF 2025/26- 2Q26 | E65: 264662 | F65: Generic Flighted Bottom Up Package | G65: 1 | H65: 572919 | I65: Heineken - Deportes - ROS - A21-54 - Upfront 25/26 - 2Q'26 | J65: 46113 | K65: 46203 | L65: FOX Innovid | M65: CPM | N65: 27.92 | O65: 179083 | P65: 5000 | R65: straightline | S65: 59694 | T65: 1666.6666 | U65: straightline | V65: 59671 | W65: invoice_schedule | X65: 1666 | Y65: 1666 | Z65: 1666 | AA65: 13114 | AB65: 13044 | AC65: 46113 | AD65: 46203 | AE65: Jessica Lang | AF65: None | AG65: JUN'26 | AH65: 5000 | AI65: 121258 | AJ65: Mike Maresca
A66: AGC001546 | B66: EXACT SCIENCES | C66: ADV006337 | D66: Cologuard/Digital/Upfront/ONE FOX/UF 2025.26/Direct/2Q26 | E66: 264810 | F66: Generic Flighted Bottom Up Package | G66: 1 | H66: 573336 | I66: Cologuard - OneFox - 25/26 - Pre/Mid - ROS - AAT - SXD - A45+ - 2Q'26 | J66: 46113 | K66: 46201 | L66: FOX DCM | M66: CPM | N66: 17.46 | O66: 7159221 | P66: 125000 | Q66: Impressions | R66: performance | S66: 0 | T66: 0 | U66: thirdparty_performance | V66: 1672298 | W66: invoice_schedule | X66: 29198.32 | Y66: 29198.32 | Z66: 29198.32 | AA66: 1790055 | AB66: 1793149 | AC66: 46113 | AD66: 46201 | AE66: Megan Sileo | AF66: None | AG66: JUN'26 | AH66: 125000 | AI66: 122756 | AJ66: Jon Renz
A67: AGC001914 | B67: CAPITAL ONE | C67: ADV004035 | D67: Capital One/Card/Digital/BYUF/Entertainment/UF2526_2Q'26 | E67: 264814 | F67: LFV - RON Ent - ROS - Pre/Mid - DT/MB/CTV/VOD - Package | G67: 3535 | H67: 573368 | I67: Capital One - Consumer Card - LFV - RON Ent - ROS - Pre/Mid - DT/MB/CTV/VOD - 1Q'26 | J67: 46125 | K67: 46201 | L67: FOX Innovid | M67: CPM | N67: 27.6 | O67: 9494131 | P67: 262038.02 | Q67: CoV Impressions | R67: straightline | S67: 3164710 | T67: 87346.007 | U67: straightline | V67: 3637362 | W67: invoice_schedule | X67: 100391.2 | Y67: 100391.2 | Z67: 100391.2 | AA67: 3326982 | AB67: 3179268 | AC67: 46125 | AD67: 46201 | AE67: Anthony Gizzo | AF67: None | AG67: JUN'26 | AH67: 262038.02 | AI67: 120477 | AJ67: Sydney Stipanovich
A68: AGC001914 | B68: CAPITAL ONE | C68: ADV004035 | D68: Capital One/BANK/25-26/Upfront/Digital/MLB/WS - UF 2025/26 | E68: 264953 | F68: DIO - LFV - FSLS - Pre/Mid - ROS - DT/MB/CTV - Package | G68: 3534 | H68: 574553 | I68: Capital One - BANK - DIO - LFV - FSLS - Pre/Mid - ROS - DT/MB/CTV - Regular Season | J68: 46106 | K68: 46292 | L68: FOX Innovid | M68: CPM | N68: 32.25 | O68: 241953 | P68: 7802.98 | Q68: CoV Impressions | R68: straightline | S68: 34565 | T68: 1114.7114 | U68: straightline | V68: 38374 | W68: invoice_schedule | X68: 1237.5575 | Y68: 1237.5575 | Z68: 1237.5575 | AA68: 246 | AB68: 223 | AC68: 46106 | AD68: 46292 | AE68: Anthony Gizzo | AF68: None | AG68: JUN'26 | AH68: 78030.02 | AI68: 121802 | AJ68: Dylan Giordano
A69: AGC000932 | B69: HILTON HOTELS | C69: ADV005857 | D69: Hilton/Digital/Upfront/Streaming/25-26/DIO/2Q'26 | E69: 264956 | F69: DIO - ROV - FS - Pre/Mid - ROS - DT/MB/CTV - Package | G69: 7968 | H69: 573888 | I69: Hilton - DIO - ROV - FS - Pre/Mid - ROS - DT/MB/CTV - Package | J69: 46112 | K69: 46201 | L69: FOX Innovid | M69: CPM | N69: 20 | O69: 5015000 | P69: 100300 | R69: straightline | S69: 1253750 | T69: 25075 | U69: straightline | V69: 1553076 | W69: invoice_schedule | X69: 30861.52 | Y69: 30861.52 | Z69: 30861.52 | AA69: 105988 | AB69: 103938 | AC69: 46112 | AD69: 46201 | AE69: Jessica Lang | AF69: None | AG69: JUN'26 | AH69: 100300 | AI69: 121426 | AJ69: Mike Maresca
A70: AGC002411 | B70: DIRECTV | C70: ADV001010 | D70: DTV/Digital/Deportes MLB/X Amplify/2526/Scatter | E70: 265056 | H70: 574125 | I70: CANCELLED - DTV DIO - SOC - FOX Sports - X - Deportes | J70: 46113 | K70: 46326 | M70: SOV-Flat Rate | N70: 0 | O70: 0 | P70: 0 | Q70: n/a | R70: prorated | S70: 0 | T70: 0 | U70: prorated | V70: 0 | W70: invoice_schedule | X70: 0 | Y70: 0 | Z70: 0 | AC70: 46113 | AD70: 46326 | AE70: Grace Stryker | AF70: None | AG70: JUN'26 | AH70: 250000.48 | AI70: 121539 | AJ70: Diana Montenegro
A71: AGC002411 | B71: DIRECTV | C71: ADV001010 | D71: DTV/Digital/Deportes MLB/X Amplify/2526/Scatter | E71: 265056 | H71: 587884 | I71: DTV - DIO - SOC - FOX Sports - X - FOXD | J71: 46113 | K71: 46326 | M71: SOV-Flat Rate | N71: 250000.5 | O71: 0 | P71: 250000.5 | Q71: n/a | R71: prorated | S71: 0 | T71: 35046.799 | U71: prorated | V71: 0 | W71: invoice_schedule | X71: 49019.706 | Y71: 49019.706 | Z71: 49019.706 | AC71: 46113 | AD71: 46326 | AE71: Grace Stryker | AF71: None | AG71: JUN'26 | AH71: 250000.48 | AI71: 121539 | AJ71: Diana Montenegro
A72: AGC002411 | B72: DIRECTV | C72: ADV001010 | D72: DIRECTV/DIGITAL SCATTER/25 26/MWC/X AMPLIFY - WC PORTAL | E72: 265069 | F72: World Cup Social Sponsorship Content - Package | G72: 8000 | H72: 583235 | I72: DTV World Cup Social Sponsorship Content - Package - X | J72: 46174 | K72: 46222 | M72: SOV-Flat Rate | N72: 500000 | O72: 1 | P72: 500000 | Q72: n/a | R72: prorated | S72: 1 | T72: 306122.45 | U72: prorated | V72: 1 | W72: invoice_schedule | X72: 306122.45 | Y72: 306122.45 | Z72: 306122.45 | AC72: 46174 | AD72: 46222 | AE72: Grace Stryker | AF72: None | AG72: JUN'26 | AH72: 500000 | AI72: 120776 | AJ72: Lisa Geraldson
A73: AGC004525 | B73: ADVERTISING COUNCIL | C73: ADV003096 | D73: Ad Council/2025/Dig/Pro-bono/2Q26/OneFox | E73: 265136 | F73: DIO - ROV - 1F SEN - Pre/Mid - ROS - FW - SXD - Package | G73: 7950 | H73: 574526 | I73: Ad Council - LFV - 1F - Pre/Mid - ROS - FW - SXD - Package- 2Q'26 - Pro-Bono | J73: 46113 | K73: 46203 | L73: FOX DCM | M73: CPM | N73: 25 | O73: 6000000 | P73: 0 | Q73: Impressions | R73: performance | S73: 0 | T73: 0 | U73: performance | V73: 1415163 | W73: invoice_schedule | X73: 0 | Y73: 0 | Z73: 0 | AA73: 1479260 | AB73: 1415163 | AC73: 46113 | AD73: 46203 | AE73: Kailey McGinn | AF73: None | AG73: JUN'26 | AH73: 0 | AI73: 121448 | AJ73: Nicholas Vara
A74: AGC001318 | B74: KIA | C74: ADV004496 | D74: Kia/Digital/Upfront/Entertainment/UF 2025/26 - 2Q26 | E74: 265152 | F74: LFV - RON Ent - ROS - Pre/Mid - DT/MB/CTV/VOD - Package | G74: 3535 | H74: 574706 | I74: KIA - LFV - RON Ent - ROS - Pre/Mid - DT/MB/CTV/VOD - Package - 2Q'26 | J74: 46113 | K74: 46203 | L74: FOX DCM | M74: CPM | N74: 33.57 | O74: 2468276 | P74: 82860.03 | Q74: CoV Impressions | R74: performance | S74: 0 | T74: 0 | U74: performance | V74: 0 | W74: invoice_schedule | X74: 0 | Y74: 0 | Z74: 0 | AC74: 46113 | AD74: 46203 | AE74: Jessica Lang | AF74: None | AG74: JUN'26 | AH74: 182860.03 | AI74: 121422 | AJ74: Allison Klein
A75: AGC001914 | B75: DISCOVER FINANCIAL SERVICES | C75: ADV001302 | D75: DISCOVER CARD/Digital/Upfront/Entertainment/ADDRESSABLE/UF 2Q'26 | E75: 265310 | F75: DIO - LFV - Entertainment ROS - Package | G75: 2789 | H75: 575165 | I75: Discover Card - DIO - LFV - Entertainment ROS - 2Q26 | J75: 46111 | K75: 46201 | L75: FOX Innovid | M75: CPM | N75: 17.87 | O75: 3357583 | P75: 60000.01 | Q75: Impressions | R75: performance | S75: 0 | T75: 0 | U75: performance | V75: 848471 | W75: invoice_schedule | X75: 15162.178 | Y75: 15162.178 | Z75: 15162.178 | AA75: 949348 | AB75: 956420 | AC75: 46111 | AD75: 46201 | AE75: Anthony Gizzo | AF75: None | AG75: JUN'26 | AH75: 60000 | AI75: 122543 | AJ75: Sydney Stipanovich
A76: AGC001318 | B76: KIA | C76: ADV004496 | D76: Kia/Upfront/Digital/Sports Streaming - UF 2025/26 - 2Q26 | E76: 265319 | F76: Generic Flighted Bottom Up Package | G76: 1 | H76: 575258 | I76: KIA/Upfront/Digital/Sports/Streaming/ROV/2025-2026 - 2Q26 | J76: 46113 | K76: 46203 | L76: FOX DCM | M76: CPM | N76: 34.96 | O76: 2742363 | P76: 95873.01 | R76: performance | S76: 0 | T76: 0 | U76: performance | V76: 0 | W76: invoice_schedule | X76: 0 | Y76: 0 | Z76: 0 | AC76: 46113 | AD76: 46203 | AE76: Jessica Lang | AF76: None | AG76: JUN'26 | AH76: 95873.01 | AI76: 122380 | AJ76: Dylan Giordano
A77: AGC000907 | B77: JOHNSON & JOHNSON | C77: ADV000102 | D77: J&J MWC'26/scatter/digital - Tremfya PsO | E77: 265595 | F77: Run of World Cup Video - Package | G77: 8005 | H77: 584732 | I77: J&J - MWC - TREMFYA PsO - Run of World Cup Video - Package - :60s | J77: 46174 | K77: 46222 | L77: FOX DCM | M77: CPM | N77: 80 | O77: 1875000 | P77: 150000 | Q77: Impressions | R77: performance | S77: 0 | T77: 0 | U77: performance | V77: 1357592 | W77: invoice_schedule | X77: 108607.36 | Y77: 108607.36 | Z77: 108607.36 | AA77: 1363014 | AB77: 1357592 | AC77: 46174 | AD77: 46222 | AE77: Mia Bonvissuto | AF77: None | AG77: JUN'26 | AH77: 150000 | AI77: 128214 | AJ77: Leslie Lowenthal
A78: AGC000386 | B78: AMERICAN EXPRESS | C78: ADV000681 | D78: 2026 FIFA MWC/AMEX/Digital | E78: 265747 | F78: Run of World Cup Video - Package | G78: 8005 | H78: 581680 | I78: AMEX - Run of World Cup Video - Package | J78: 46184 | K78: 46222 | M78: CPM | N78: 40 | O78: 16500000 | P78: 660000 | Q78: Impressions | R78: performance | S78: 0 | T78: 0 | U78: performance | V78: 10942300 | W78: invoice_schedule | X78: 437692 | Y78: 437692 | Z78: 437692 | AA78: 10942300 | AB78: 0 | AC78: 46184 | AD78: 46222 | AE78: JohnMichael Bogusz | AF78: None | AG78: JUN'26 | AH78: 2550000.1 | AI78: 128038 | AJ78: Meghan Courtney
A79: AGC000386 | B79: AMERICAN EXPRESS | C79: ADV000681 | D79: 2026 FIFA MWC/AMEX/Digital | E79: 265747 | F79: World Cup Social Sponsorship Content - Package | G79: 8000 | H79: 582833 | I79: AMEX - World Cup Social Sponsorship Content - Package - X | J79: 46184 | K79: 46222 | M79: SOV-Flat Rate | N79: 1000000 | O79: 0 | P79: 1000000 | Q79: n/a | R79: prorated | S79: 0 | T79: 512820.51 | U79: prorated | V79: 0 | W79: invoice_schedule | X79: 512820.51 | Y79: 512820.51 | Z79: 512820.51 | AC79: 46184 | AD79: 46222 | AE79: JohnMichael Bogusz | AF79: None | AG79: JUN'26 | AH79: 2550000.1 | AI79: 128038 | AJ79: Meghan Courtney
A80: AGC000386 | B80: AMERICAN EXPRESS | C80: ADV000681 | D80: 2026 FIFA MWC/AMEX/Digital | E80: 265747 | F80: World Cup Social Sponsorship Content - Package | G80: 8000 | H80: 582838 | I80: AMEX - World Cup Social Sponsorship Content - Package - FB/IG/TT/YT | J80: 46184 | K80: 46222 | M80: Cost Per Unit | N80: 0.15 | O80: 5933334 | P80: 890000.1 | Q80: Guaranteed Views | R80: prorated | S80: 3042736 | T80: 456410.31 | U80: prorated | V80: 3042736 | W80: invoice_schedule | X80: 456410.31 | Y80: 456410.31 | Z80: 456410.31 | AC80: 46184 | AD80: 46222 | AE80: JohnMichael Bogusz | AF80: None | AG80: JUN'26 | AH80: 2550000.1 | AI80: 128038 | AJ80: Meghan Courtney
A81: AGC002371 | B81: DAC GROUP / BRIDGESTONE | C81: ADV014268 | D81: Bridgestone/25-26/Digital/Scatter/Entertainment/2Q | E81: 265754 | F81: DIO - LFV - Entertainment ROS Preemptible - Package | G81: 1754 | H81: 576695 | I81: Bridgestone - DIO - LFV - Entertainment ROS Preemptible - Package | J81: 46113 | K81: 46201 | M81: CPM | N81: 12.5 | O81: 4640000 | P81: 58000 | Q81: Impressions | R81: performance | S81: 0 | T81: 0 | U81: performance | V81: 495547 | W81: invoice_schedule | X81: 6194.3375 | Y81: 6194.3375 | Z81: 6194.3375 | AA81: 494517 | AB81: 495547 | AC81: 46113 | AD81: 46201 | AE81: JohnMichael Bogusz | AF81: None | AG81: JUN'26 | AH81: 58000 | AI81: 128399 | AJ81: Tierney Flynn
A82: AGC002175 | B82: SIGNET | C82: ADV003649 | D82: Signet Kay/25-26/Digital/Upfront/Entertainment/UF 2025/26/2Q | E82: 265809 | F82: DIO - LFV - Entertainment ROS - Package | G82: 2789 | H82: 576868 | I82: Signet Kay DIO - LFV - Entertainment ROS - Package Bridal 2Q | J82: 46113 | K82: 46203 | M82: CPM | N82: 17 | O82: 4339410 | P82: 73769.98 | Q82: CoV Impressions | R82: performance | S82: 0 | T82: 0 | U82: performance | V82: 282886 | W82: invoice_schedule | X82: 4809.062 | Y82: 4809.062 | Z82: 4809.062 | AA82: 296059 | AB82: 282886 | AC82: 46113 | AD82: 46203 | AE82: Grace Stryker | AF82: None | AG82: JUN'26 | AH82: 151323.03 | AI82: 122614 | AJ82: Carly Sartwell
A83: AGC002175 | B83: SIGNET | C83: ADV003649 | D83: Signet Kay/25-26/Digital/Upfront/Entertainment/UF 2025/26/2Q | E83: 265809 | F83: DIO - LFV - Entertainment ROS - Package | G83: 2789 | H83: 576879 | I83: Signet Kay DIO - LFV - Entertainment ROS - Package Gifting 2Q | J83: 46113 | K83: 46203 | M83: CPM | N83: 17 | O83: 4561944 | P83: 77553.05 | Q83: CoV Impressions | R83: performance | S83: 0 | T83: 0 | U83: performance | V83: 427265 | W83: invoice_schedule | X83: 7263.51 | Y83: 7263.51 | Z83: 7263.51 | AA83: 448118 | AB83: 429945 | AC83: 46113 | AD83: 46203 | AE83: Grace Stryker | AF83: None | AG83: JUN'26 | AH83: 151323.03 | AI83: 122614 | AJ83: Carly Sartwell
A84: AGC002601 | B84: AUTOTRADER | C84: ADV000761 | D84: Autotrader/Digital/Direct/Upfront/Sports/25-26/2Q'26 | E84: 265850 | F84: Generic Flighted Bottom Up Package | G84: 1 | H84: 577035 | I84: Autotrader - DIO - ROV - FS - Pre/Mid - SOCCER - DT/MB/CTV - 2Q'26 | J84: 46113 | K84: 46201 | L84: FOX DCM | M84: CPM | N84: 25.7 | O84: 778211 | P84: 20000.02 | Q84: CoV Impressions | R84: performance | S84: 0 | T84: 0 | U84: performance | V84: 259405 | W84: invoice_schedule | X84: 6666.7 | Y84: 6666.7 | Z84: 6666.7 | AA84: 317582 | AB84: 315257 | AC84: 46113 | AD84: 46201 | AE84: Kailey McGinn | AF84: None | AG84: JUN'26 | AH84: 20000.02 | AI84: 123965 | AJ84: Nicole Gamache
A85: AGC002371 | B85: NUTRAFOL | C85: ADV008819 | D85: Nutrafol/25-26/Digital/Scatter/Entertainment/2Q | E85: 266130 | F85: DIO - LFV - Entertainment ROS Preemptible - Package | G85: 1754 | H85: 577967 | I85: Nutrafol - DIO - LFV - Entertainment ROS Preemptible - Package | J85: 46113 | K85: 46180 | M85: CPM | N85: 12.5 | O85: 7120000 | P85: 89000 | Q85: Impressions | R85: performance | S85: 0 | T85: 0 | U85: performance | V85: 229454 | W85: invoice_schedule | X85: 2868.17 | Y85: 2868.17 | Z85: 2868.17 | AA85: 415622 | AB85: 419230 | AC85: 46113 | AD85: 46180 | AE85: John Michael Bogusz | AF85: None | AG85: JUN'26 | AH85: 89000.01 | AI85: 128838 | AJ85: Tierney Flynn
A86: AGC003453 | B86: NATIONAL VISION INC | C86: ADV006329 | D86: National Vision/Digital/Upfront/ONEFOX/UF 2025/26/2Q'26 | E86: 266239 | F86: Generic Flighted Bottom Up Package | G86: 1 | H86: 578272 | I86: National Vision - OneFOX - A25-54 - 2Q'26 Package | J86: 46111 | K86: 46201 | L86: FOX DCM | M86: CPM | N86: 19.46 | O86: 14131552 | P86: 275000 | Q86: Impressions | R86: performance | S86: 0 | T86: 0 | U86: performance | V86: 3338126 | W86: invoice_schedule | X86: 62335.87 | Y86: 62335.87 | Z86: 62335.87 | AA86: 3724779 | AB86: 3717319 | AC86: 46111 | AD86: 46201 | AE86: Katie Johnson | AF86: None | AG86: JUN'26 | AH86: 300000.03 | AI86: 122827 | AJ86: Tim Wodzisz
A87: AGC003453 | B87: NATIONAL VISION INC | C87: ADV006329 | D87: National Vision/Digital/Upfront/ONEFOX/UF 2025/26/2Q'26 | E87: 266239 | F87: DIO - LFV - Entertainment ROS - Package | G87: 2789 | H87: 578275 | I87: National Vision - Brightline - Overlay - FOX on Hulu - P2+ - 2Q'26 Package | J87: 46111 | K87: 46201 | L87: FOX DCM | M87: CPM | N87: 24 | O87: 1041667 | P87: 25000.01 | Q87: Impressions | R87: performance | S87: 0 | T87: 0 | U87: performance | V87: 207802 | W87: invoice_schedule | X87: 5192.66 | Y87: 5192.66 | Z87: 5192.66 | AA87: 260282 | AB87: 266452 | AC87: 46111 | AD87: 46201 | AE87: Katie Johnson | AF87: None | AG87: JUN'26 | AH87: 300000.03 | AI87: 122827 | AJ87: Tim Wodzisz
A88: AGC005226 | B88: AMAZON XCM | C88: ADV011498 | D88: Amazon XCM/Digital/Direct/Upfront/Entertainment/25-26/2Q'26 | E88: 266308 | F88: LFV - RON Ent - ROS - Pre/Mid - DT/MB/CTV/VOD - Package | G88: 3535 | H88: 578379 | I88: Amazon XCM - LFV - RON Entertainment - ROS - Pre/Mid - DT/MB/CTV/VOD - A1849 AAT - Package - 2Q'26 - Project Blue | J88: 46175 | K88: 46199 | L88: FOX DCM | M88: CPM | N88: 19 | O88: 2105263 | P88: 40000 | Q88: Impressions | R88: performance | S88: 0 | T88: 0 | U88: performance | V88: 0 | W88: invoice_schedule | X88: 0 | Y88: 0 | Z88: 0 | AC88: 46175 | AD88: 46199 | AE88: Kailey McGinn | AF88: None | AG88: JUN'26 | AH88: 188965 | AI88: 122968 | AJ88: Matthew DiToro
A89: AGC002371 | B89: SAATVA | C89: ADV002782 | D89: Saatva/25-26/Digital/Scatter/Entertainment/2Q | E89: 266630 | F89: DIO - LFV - Entertainment ROS Preemptible - Package | G89: 1754 | H89: 579781 | I89: Satva - DIO - LFV - Entertainment ROS Preemptible - Package | J89: 46113 | K89: 46194 | L89: FOX Extreme Reach | M89: CPM | N89: 12.5 | O89: 16000000 | P89: 200000 | Q89: Impressions | R89: performance | S89: 0 | T89: 0 | U89: performance | V89: 418919 | W89: invoice_schedule | X89: 5236.4875 | Y89: 5236.4875 | Z89: 5236.4875 | AA89: 415144 | AB89: 418919 | AC89: 46113 | AD89: 46194 | AE89: John Michael Bogusz | AF89: None | AG89: JUN'26 | AH89: 200000.01 | AI89: 129174 | AJ89: Tierney Flynn
A90: AGC001312 | B90: RAMP.COM | C90: ADV013024 | D90: RAMP.COM / SCATTER / DIGITAL / SPORTS / FY Q4 25-26 / | E90: 266692 | F90: DIO - ROV - FS - Pre/Mid - ROS - DT/MB/CTV - Package | G90: 7968 | H90: 590840 | I90: RAMP - DIO - ROV - FS - Pre/Mid - ROS - DT/MB - 2Q'26 | J90: 46174 | K90: 46180 | L90: FOX Flashtalking | M90: CPM | N90: 28.75 | O90: 48696 | P90: 1400.01 | Q90: Impressions | R90: performance | S90: 0 | T90: 0 | U90: performance | V90: 46916 | W90: invoice_schedule | X90: 1348.835 | Y90: 1348.835 | Z90: 1348.835 | AA90: 50252 | AB90: 46916 | AC90: 46174 | AD90: 46180 | AE90: Anthony Gizzo | AF90: None | AG90: JUN'26 | AH90: 10800.12 | AI90: 129296 | AJ90: Adam Chardavoyne
A91: AGC001312 | B91: RAMP.COM | C91: ADV013024 | D91: RAMP.COM / SCATTER / DIGITAL / SPORTS / FY Q4 25-26 / | E91: 266692 | F91: DIO - ROV - FS - Pre/Mid - ROS - DT/MB/CTV - Package | G91: 7968 | H91: 590842 | I91: RAMP - DIO - ROV - FS - Pre/Mid - ROS - DT/MB - 2Q'26 | J91: 46181 | K91: 46187 | L91: FOX Flashtalking | M91: CPM | N91: 28.75 | O91: 48696 | P91: 1400.01 | Q91: Impressions | R91: performance | S91: 0 | T91: 0 | U91: performance | V91: 14246 | W91: invoice_schedule | X91: 409.5725 | Y91: 409.5725 | Z91: 409.5725 | AA91: 15017 | AB91: 14246 | AC91: 46181 | AD91: 46187 | AE91: Anthony Gizzo | AF91: None | AG91: JUN'26 | AH91: 10800.12 | AI91: 129296 | AJ91: Adam Chardavoyne
A92: AGC001312 | B92: RAMP.COM | C92: ADV013024 | D92: RAMP.COM / SCATTER / DIGITAL / SPORTS / FY Q4 25-26 / | E92: 266692 | F92: DIO - ROV - FS - Pre/Mid - ROS - DT/MB/CTV - Package | G92: 7968 | H92: 590844 | I92: RAMP - DIO - ROV - FS - Pre/Mid - ROS - DT/MB - 2Q'26 | J92: 46188 | K92: 46194 | L92: FOX Flashtalking | M92: CPM | N92: 28.75 | O92: 48696 | P92: 1400.01 | Q92: Impressions | R92: performance | S92: 0 | T92: 0 | U92: performance | V92: 820 | W92: invoice_schedule | X92: 23.575 | Y92: 23.575 | Z92: 23.575 | AA92: 830 | AB92: 820 | AC92: 46188 | AD92: 46194 | AE92: Anthony Gizzo | AF92: None | AG92: JUN'26 | AH92: 10800.12 | AI92: 129296 | AJ92: Adam Chardavoyne
A93: AGC001312 | B93: RAMP.COM | C93: ADV013024 | D93: RAMP.COM / SCATTER / DIGITAL / SPORTS / FY Q4 25-26 / | E93: 266692 | F93: DIO - ROV - FS - Pre/Mid - ROS - DT/MB/CTV - Package | G93: 7968 | H93: 590846 | I93: RAMP - DIO - ROV - FS - Pre/Mid - ROS - DT/MB - 2Q'26 | J93: 46195 | K93: 46201 | L93: FOX Flashtalking | M93: CPM | N93: 28.75 | O93: 48696 | P93: 1400.01 | Q93: Impressions | R93: performance | S93: 0 | T93: 0 | U93: performance | V93: 695 | W93: invoice_schedule | X93: 19.9813 | Y93: 19.9813 | Z93: 19.9813 | AA93: 758 | AB93: 695 | AC93: 46195 | AD93: 46201 | AE93: Anthony Gizzo | AF93: None | AG93: JUN'26 | AH93: 10800.12 | AI93: 129296 | AJ93: Adam Chardavoyne
A94: AGC003068 | B94: UNILEVER | C94: ADV000661 | D94: Unilever/MWC Digital/2026 - Dove MB | E94: 266866 | F94: Run of World Cup Video - Package | G94: 8005 | H94: 581108 | I94: OMP - Unilever - Dove MB - Run of World Cup Video - Package | J94: 46184 | K94: 46222 | L94: FOX Flashtalking | M94: CPM | N94: 40 | O94: 2997900 | P94: 119916 | Q94: Impressions | R94: prorated | S94: 1537385 | T94: 61495.385 | U94: prorated | V94: 1537385 | W94: invoice_schedule | X94: 61495.385 | Y94: 61495.385 | Z94: 61495.385 | AA94: 2001193 | AB94: 2008864 | AC94: 46184 | AD94: 46222 | AE94: Mia Bonvissuto | AF94: None | AG94: JUN'26 | AH94: 119916 | AI94: 126815 | AJ94: Leslie Lowenthal
A95: AGC002408 | B95: ANHEUSER BUSCH | C95: ADV001839 | D95: AB/DIGITAL/SCATTER/SPORTS/MWC/X AMPLIFY | E95: 266911 | F95: World Cup Social Sponsorship Content - Package | G95: 8000 | H95: 581387 | I95: Anheuser Busch - OMP - World Cup Social Sponsorship Content - X Amplify - 2026 Package | J95: 46174 | K95: 46222 | L95: FOX 1st Party | M95: SOV-Flat Rate | N95: 500000 | O95: 1 | P95: 500000 | Q95: n/a | R95: prorated | S95: 1 | T95: 306122.45 | U95: prorated | V95: 1 | W95: invoice_schedule | X95: 306122.45 | Y95: 306122.45 | Z95: 306122.45 | AC95: 46174 | AD95: 46222 | AE95: Megan Sileo | AF95: None | AG95: JUN'26 | AH95: 500000 | AI95: 125698 | AJ95: Janna Goldstein
A96: AGC002371 | B96: CHIME | C96: ADV002070 | D96: Chime/25-26/Digital/Scatter/Entertainment/2Q | E96: 266929 | F96: DIO - LFV - Entertainment ROS Preemptible - Package | G96: 1754 | H96: 581417 | I96: Chime - DIO - LFV - Entertainment ROS Preemptible - Package | J96: 46118 | K96: 46201 | M96: CPM | N96: 12.5 | O96: 3600000 | P96: 45000 | Q96: Impressions | R96: performance | S96: 0 | T96: 0 | U96: manual | V96: 1942587 | W96: manual | X96: 24282.425 | Y96: 24282.425 | Z96: 24282.425 | AC96: 46118 | AD96: 46201 | AE96: John Michael Bogusz | AF96: None | AG96: JUN'26 | AH96: 45000 | AI96: 130276 | AJ96: Tierney Flynn
A97: AGC001926 | B97: BMW | C97: ADV004582 | D97: BMW / SCATTER / DIGITAL / SPORTS / FY Q4 25-26 / World Cup | E97: 266966 | F97: Run of World Cup Display - Package | G97: 8004 | H97: 581635 | I97: BMW - Run of World Cup Display - Men's World Cup 26' - 300x250, 320x50, 728x90 | J97: 46184 | K97: 46222 | L97: FOX DCM | M97: CPM | N97: 6 | O97: 13333333 | P97: 80000 | Q97: Impressions | R97: performance | S97: 0 | T97: 0 | U97: performance | V97: 4682373 | W97: invoice_schedule | X97: 28094.238 | Y97: 28094.238 | Z97: 28094.238 | AA97: 4683082 | AB97: 4682373 | AC97: 46184 | AD97: 46222 | AE97: Anthony Gizzo | AF97: None | AG97: JUN'26 | AH97: 1180000 | AI97: 128177 | AJ97: Adam Chardavoyne
A98: AGC001926 | B98: BMW | C98: ADV004582 | D98: BMW / SCATTER / DIGITAL / SPORTS / FY Q4 25-26 / World Cup | E98: 266966 | F98: World Cup Social Sponsorship Content - Package | G98: 8000 | H98: 581649 | I98: BMW - World Cup Social Sponsorship Content - Men's World Cup | J98: 46184 | K98: 46222 | M98: Cost Per Unit | N98: 0.15 | O98: 4000000 | P98: 600000 | Q98: Placements | R98: prorated | S98: 2051283 | T98: 307692.31 | U98: prorated | V98: 2051283 | W98: invoice_schedule | X98: 307692.31 | Y98: 307692.31 | Z98: 307692.31 | AC98: 46184 | AD98: 46222 | AE98: Anthony Gizzo | AF98: None | AG98: JUN'26 | AH98: 1180000 | AI98: 128177 | AJ98: Adam Chardavoyne
A99: AGC001926 | B99: BMW | C99: ADV004582 | D99: BMW / SCATTER / DIGITAL / SPORTS / FY Q4 25-26 / World Cup | E99: 266966 | F99: World Cup FOX Sports Site & App Takeover - Package | G99: 8003 | H99: 587742 | I99: BMW - World Cup FOX Sports Site & App Takeover - Non - OMP 6/20/2026 | J99: 46193 | K99: 46193 | L99: FOX DCM | M99: Cost Per Day | N99: 41666.67 | O99: 6 | P99: 250000 | Q99: Days | R99: prorated | S99: 6 | T99: 250000 | U99: prorated | V99: 6 | W99: invoice_schedule | X99: 250000 | Y99: 250000 | Z99: 250000 | AA99: 0 | AB99: 0 | AC99: 46193 | AD99: 46193 | AE99: Anthony Gizzo | AF99: None | AG99: JUN'26 | AH99: 1180000 | AI99: 128177 | AJ99: Adam Chardavoyne
A100: AGC004344 | B100: FERRARA CANDY COMPANY | C100: ADV013598 | D100: Ferrara/Digital/Scatter/World Cup/25-26 | E100: 267002 | F100: Run of World Cup Video - Package | G100: 8005 | H100: 581781 | I100: Ferrara - Nerds - Run of World Cup Video - Package | J100: 46174 | K100: 46222 | L100: FOX DCM | M100: CPM | N100: 40 | O100: 6055550 | P100: 242222 | Q100: Impressions | R100: performance | S100: 0 | T100: 0 | U100: performance | V100: 4058316 | W100: invoice_schedule | X100: 162332.64 | Y100: 162332.64 | Z100: 162332.64 | AA100: 4059723 | AB100: 4058316 | AC100: 46174 | AD100: 46222 | AE100: Jessica Lang | AF100: None | AG100: JUN'26 | AH100: 1666668.2 | AI100: 127993 | AJ100: Mike Maresca
...
